Workbook

Sheet Base_IFData_Original
A1: BASE DE DADOS | IFData Junho 2026
A2: Fonte: IF.data, Banco Central do Brasil (https://www3.bcb.gov.br/ifdata)
A4: Instituição | B4: Código | C4: Conglomerado Prudencial (Nome) | D4: Conglomerado Financeiro (Cód.) | E4: Conglomerado Prudencial (Cód.) | F4: TCB | G4: TC | H4: TI | I4: Cidade | J4: UF | K4: Data | L4: Ativo Total (R$ mil) | M4: Carteira de Crédito (R$ mil) | N4: Títulos e Valores Mobiliários (R$ mil) | O4: Passivo Exigível (R$ mil) | P4: Captações (R$ mil) | Q4: Patrimônio Líquido (R$ mil) | R4: Lucro Líquido (R$ mil) | S4: Número de Agências | T4: Postos de Atendimento
A5: BANCO DO BRASIL S.A. | B5: 0 | C5: BB - PRUDENCIAL | D5: C0049906 | E5: C0080329 | F5: b1 | G5: 1 | H5: 1 | I5: BRASILIA | J5: DF | K5: 06/2026 | L5: 2461086914 | M5: 1065710905 | N5: 714731784 | O5: 2279753810 | P5: 1974660924 | Q5: 181333105 | R5: 6216056 | S5: 3932 | T5: 309
A6: CAIXA ECONOMICA FEDERAL | B6: 360305 | C6: CAIXA ECONÔMICA FEDERAL - PRUDENCIAL | D6: C0051626 | E6: C0080738 | F6: b1 | G6: 1 | H6: 6 | I6: BRASILIA | J6: DF | K6: 06/2026 | L6: 2368147225 | M6: 1362330927 | N6: 452416774 | O6: 2249779433 | P6: 2063880327 | Q6: 118367792 | R6: 6585794 | S6: 3000 | T6: 868
A7: ITAÚ UNIBANCO S.A. | B7: 60701190 | C7: ITAU - PRUDENCIAL | D7: C0010069 | E7: C0080099 | F7: b1 | G7: 2 | H7: 8 | I7: SAO PAULO | J7: SP | K7: 06/2026 | L7: 2169409565 | M7: 700105223 | N7: 559549223 | O7: 2006548179 | P7: 1842394345 | Q7: 162861385 | R7: 19759837 | S7: 1345 | T7: 1403
A8: BANCO BRADESCO S.A. | B8: 60746948 | C8: BRADESCO - PRUDENCIAL | D8: C0010045 | E8: C0080075 | F8: b1 | G8: 2 | H8: 8 | I8: OSASCO | J8: SP | K8: 06/2026 | L8: 1952464273 | M8: 756014814 | N8: 322119751 | O8: 1777233946 | P8: 1545720299 | Q8: 175230327 | R8: 12080064 | S8: 2026 | T8: 762
A9: BANCO SANTANDER (BRASIL) S.A. | B9: 90400888 | C9: SANTANDER - PRUDENCIAL | D9: C0030379 | E9: C0080185 | F9: b1 | G9: 3 | H9: 8 | I9: SAO PAULO | J9: SP | K9: 06/2026 | L9: 1209443083 | M9: 365285710 | N9: 260716671 | O9: 1110706856 | P9: 953249578 | Q9: 98736227 | R9: 7382760 | S9: 1196 | T9: 2516
A10: BANCO NACIONAL DE DESENVOLVIMENTO ECONOMICO E SOCIAL | B10: 33657248 | C10: BNDES - PRUDENCIAL | E10: C0081847 | F10: b4 | G10: 1 | H10: 4 | I10: RIO DE JANEIRO | J10: RJ | K10: 06/2026 | L10: 1073403746 | M10: 375703869 | N10: 209161034 | O10: 892700475 | P10: 661452493 | Q10: 180703272 | R10: 11153448 | S10: 5 | T10: 0
A11: BANCO BTG PACTUAL S.A. | B11: 30306294 | C11: BTG PACTUAL - PRUDENCIAL | D11: C0049944 | E11: C0080336 | F11: b1 | G11: 2 | H11: 8 | I11: RIO DE JANEIRO | J11: RJ | K11: 06/2026 | L11: 743258957 | M11: 81617597 | N11: 228588076 | O11: 663705470 | P11: 548000573 | Q11: 79553487 | R11: 9471540 | S11: 28 | T11: 0
A12: ITAÚ UNIBANCO HOLDING S.A. | B12: 60872504 | C12: ITAU - PRUDENCIAL | D12: C0010069 | E12: C0080099 | F12: b2 | G12: 2 | H12: 8 | I12: SAO PAULO | J12: SP | K12: 06/2026 | L12: 493183395 | M12: 172877389 | N12: 41855441 | O12: 285535078 | P12: 107861159 | Q12: 207648317 | R12: 23205024 | S12: 2 | T12: 7
A13: NU FINANCEIRA S.A. - SOCIEDADE DE CRÉDITO, FINANCIAMENTO E INVESTIMENTO | B13: 30680829 | C13: NU PAGAMENTOS - PRUDENCIAL | D13: C0052058 | E13: C0084693 | F13: n1 | G13: 3 | H13: 14 | I13: SAO PAULO | J13: SP | K13: 06/2026 | L13: 267624695 | M13: 76080601 | N13: 80369899 | O13: 252606112 | P13: 225759535 | Q13: 15018583 | R13: 4194823 | S13: 2 | T13: 0
A14: BANCO SAFRA S.A. | B14: 58160789 | C14: SAFRA - PRUDENCIAL | D14: C0010083 | E14: C0080109 | F14: b1 | G14: 2 | H14: 8 | I14: SAO PAULO | J14: SP | K14: 06/2026 | L14: 256683465 | M14: 93167603 | N14: 46773165 | O14: 238676254 | P14: 204635211 | Q14: 18007212 | R14: 1885083 | S14: 133 | T14: 3
A15: BANCO COOPERATIVO SICREDI S.A. | B15: 1181521 | C15: BCO COOPERATIVO SICREDI - PRUDENCIAL | E15: C0080745 | F15: b1 | G15: 2 | H15: 11 | I15: PORTO ALEGRE | J15: RS | K15: 06/2026 | L15: 234406077 | M15: 50267293 | N15: 49289841 | O15: 228925803 | P15: 202089776 | Q15: 5480274 | R15: 162608 | S15: 6 | T15: 0
A16: BANCO COOPERATIVO SICOOB S.A. - BANCO SICOOB | B16: 2038232 | C16: BANCO SICOOB - PRUDENCIAL | D16: C0051750 | E16: C0080879 | F16: b1 | G16: 2 | H16: 11 | I16: BRASILIA | J16: DF | K16: 06/2026 | L16: 223159409 | M16: 44908980 | N16: 68401403 | O16: 216175011 | P16: 188203009 | Q16: 6984398 | R16: 458952 | S16: 5 | T16: 0
A17: BANCO XP S.A. | B17: 33264668 | C17: XP - PRUDENCIAL | D17: C0052120 | E17: C0082475 | F17: b1 | G17: 2 | H17: 8 | I17: RIO DE JANEIRO | J17: RJ | K17: 06/2026 | L17: 221732251 | M17: 32257267 | N17: 75852463 | O17: 209296234 | P17: 169190938 | Q17: 12436018 | R17: 366732 | S17: 2 | T17: 0
A18: REDECARD INSTITUIÇÃO DE PAGAMENTO S.A. | B18: 1425787 | C18: ITAU - PRUDENCIAL | E18: C0080099 | F18: n4 | G18: 2 | H18: 41 | I18: SAO PAULO | J18: SP | K18: 06/2026 | L18: 178389094 | M18: 0 | N18: 18863330 | O18: 137181221 | P18: 16821616 | Q18: 41207873 | R18: 1497264 | S18: 1 | T18: 0
A19: BANCO DO ESTADO DO RIO GRANDE DO SUL S.A. | B19: 92702067 | C19: BANRISUL - PRUDENCIAL | D19: C0030173 | E19: C0080154 | F19: b1 | G19: 1 | H19: 8 | I19: PORTO ALEGRE | J19: RS | K19: 06/2026 | L19: 172827959 | M19: 60414676 | N19: 75506552 | O19: 161276935 | P19: 150456265 | Q19: 11551023 | R19: 546547 | S19: 506 | T19: 43
A20: BANCO CITIBANK S.A. | B20: 33479023 | C20: CITIBANK - PRUDENCIAL | D20: C0030403 | E20: C0080192 | F20: b1 | G20: 3 | H20: 8 | I20: SAO PAULO | J20: SP | K20: 06/2026 | L20: 169403341 | M20: 26037160 | N20: 46301711 | O20: 164218702 | P20: 145825012 | Q20: 5184639 | R20: 880369 | S20: 44 | T20: 8
A21: BANCO VOTORANTIM S.A. | B21: 59588111 | C21: VOTORANTIM - PRUDENCIAL | D21: C0051011 | E21: C0080484 | F21: b1 | G21: 2 | H21: 8 | I21: SAO PAULO | J21: SP | K21: 06/2026 | L21: 147547552 | M21: 71981491 | N21: 32816913 | O21: 134575200 | P21: 111045483 | Q21: 12972352 | R21: 961452 | S21: 4 | T21: 3
A22: XP INVESTIMENTOS CORRETORA DE CÂMBIO,TÍTULOS E VALORES MOBILIÁRIOS S/A | B22: 2332886 | C22: XP - PRUDENCIAL | D22: C0052120 | E22: C0082475 | F22: n2 | G22: 2 | H22: 15 | I22: RIO DE JANEIRO | J22: RJ | K22: 06/2026 | L22: 132450653 | M22: 147006 | N22: 39754591 | O22: 125124019 | P22: 91424497 | Q22: 7326634 | R22: -40139 | S22: 5 | T22: 0
A23: NU PAGAMENTOS S.A. - INSTITUIÇÃO DE PAGAMENTO | B23: 18236120 | C23: NU PAGAMENTOS - PRUDENCIAL | E23: C0084693 | F23: n4 | G23: 3 | H23: 41 | I23: SAO PAULO | J23: SP | K23: 06/2026 | L23: 122363230 | M23: 75801555 | N23: 684426 | O23: 99117282 | P23: 3084398 | Q23: 23245948 | R23: 4093013 | S23: 1 | T23: 0
A24: BANCO C6 S.A. | B24: 31872495 | C24: BANCO C6 - PRUDENCIAL | D24: C0052072 | E24: C0084844 | F24: b1 | G24: 2 | H24: 8 | I24: SAO PAULO | J24: SP | K24: 06/2026 | L24: 117193733 | M24: 52508241 | N24: 43492491 | O24: 114382052 | P24: 87601269 | Q24: 2811681 | R24: 662077 | S24: 2 | T24: 0
A25: CIELO S.A. - INSTITUIÇÃO DE PAGAMENTO | B25: 1027058 | C25: CIELO IP - PRUDENCIAL | E25: C0084710 | F25: n4 | G25: 2 | H25: 41 | I25: BARUERI | J25: SP | K25: 06/2026 | L25: 116680888 | M25: 0 | N25: 6134397 | O25: 105006218 | P25: 10367314 | Q25: 11674670 | R25: 566759 | S25: 1 | T25: 0
A26: BANCO J.P. MORGAN S.A. | B26: 33172537 | C26: JP MORGAN CHASE - PRUDENCIAL | D26: C0020107 | E26: C0080116 | F26: b1 | G26: 3 | H26: 8 | I26: SAO PAULO | J26: SP | K26: 06/2026 | L26: 110025345 | M26: 3735715 | N26: 62256458 | O26: 98253022 | P26: 84833031 | Q26: 11772323 | R26: 1038284 | S26: 3 | T26: 0
A27: MERCADO PAGO INSTITUIÇÃO DE PAGAMENTO LTDA. | B27: 10573521 | C27: MERCADO PAGO IP - PRUDENCIAL | E27: C0084820 | F27: n4 | G27: 3 | H27: 41 | I27: OSASCO | J27: SP | K27: 06/2026 | L27: 105731564 | M27: 22485259 | N27: 1505659 | O27: 102742356 | P27: 59815921 | Q27: 2989208 | R27: -189822 | S27: 1 | T27: 0
A28: BANCO INTER S.A. | B28: 416968 | C28: INTER - PRUDENCIAL | D28: C0051884 | E28: C0080996 | F28: b1 | G28: 2 | H28: 8 | I28: BELO HORIZONTE | J28: MG | K28: 06/2026 | L28: 100898332 | M28: 46141022 | N28: 28722089 | O28: 93446498 | P28: 77773587 | Q28: 7451834 | R28: 712041 | S28: 2 | T28: 0
A29: BANCO DAYCOVAL S.A. | B29: 62232889 | C29: BCO DAYCOVAL S.A - PRUDENCIAL | D29: C0051987 | E29: C0081744 | F29: b1 | G29: 2 | H29: 8 | I29: SAO PAULO | J29: SP | K29: 06/2026 | L29: 99778656 | M29: 53810851 | N29: 24713706 | O29: 92122935 | P29: 82698919 | Q29: 7655721 | R29: 901621 | S29: 53 | T29: 0
A30: SANTANDER SOCIEDADE DE CRÉDITO, FINANCIAMENTO E INVESTIMENTO S.A. | B30: 7707650 | C30: SANTANDER - PRUDENCIAL | D30: C0030379 | E30: C0080185 | F30: n1 | G30: 3 | H30: 14 | I30: SAO PAULO | J30: SP | K30: 06/2026 | L30: 94908733 | M30: 78916545 | N30: 8626164 | O30: 90101084 | P30: 84719722 | Q30: 4807649 | R30: 361088 | S30: 1 | T30: 0
A31: STONE INSTITUIÇÃO DE PAGAMENTO S.A. | B31: 16501555 | C31: STONE IP - PRUDENCIAL | E31: C0084686 | F31: n4 | G31: 3 | H31: 41 | I31: SAO PAULO | J31: SP | K31: 06/2026 | L31: 89229885 | M31: 0 | N31: 33856104 | O31: 86020632 | P31: 35329072 | Q31: 3209254 | R31: 867035 | S31: 1 | T31: 0
A32: BANCO DO NORDESTE DO BRASIL S.A. | B32: 7237373 | C32: BCO DO NORDESTE DO BRASIL S.A. - PRUDENCIAL | E32: C0081593 | F32: b1 | G32: 1 | H32: 8 | I32: FORTALEZA | J32: CE | K32: 06/2026 | L32: 81039783 | M32: 17779920 | N32: 44768452 | O32: 64226772 | P32: 23269171 | Q32: 16813010 | R32: 1057412 | S32: 301 | T32: 1
A33: BANCO PAN S.A. | B33: 59285411 | C33: BTG PACTUAL - PRUDENCIAL | D33: C0049944 | E33: C0080336 | F33: b1 | G33: 2 | H33: 8 | I33: RIO DE JANEIRO | J33: RJ | K33: 06/2026 | L33: 77255474 | M33: 35566859 | N33: 24319234 | O33: 68495128 | P33: 64315922 | Q33: 8760346 | R33: 689725 | S33: 2 | T33: 0
A34: GETNET ADQUIRÊNCIA E SERVIÇOS PARA MEIOS DE PAGAMENTO S.A. INSTITUIÇÃO DE PAGAMENTO | B34: 10440482 | C34: SANTANDER - PRUDENCIAL | E34: C0080185 | F34: n4 | G34: 3 | H34: 41 | I34: SAO PAULO | J34: SP | K34: 06/2026 | L34: 74198667 | M34: 0 | N34: 471650 | O34: 70373351 | P34: 457227 | Q34: 3825316 | R34: 529101 | S34: 1 | T34: 0
A35: PAGSEGURO INTERNET INSTITUIÇÃO DE PAGAMENTO S.A. | B35: 8561701 | C35: PAGSEGURO - PRUDENCIAL | E35: C0084813 | F35: n4 | G35: 2 | H35: 41 | I35: SAO PAULO | J35: SP | K35: 06/2026 | L35: 73530147 | M35: 746551 | N35: 5259611 | O35: 67499312 | P35: 46766864 | Q35: 6030835 | R35: 463519 | S35: 1 | T35: 0
A36: BANCO BRADESCO FINANCIAMENTOS S.A. | B36: 7207996 | C36: BRADESCO - PRUDENCIAL | D36: C0010045 | E36: C0080075 | F36: b1 | G36: 2 | H36: 8 | I36: OSASCO | J36: SP | K36: 06/2026 | L36: 68748096 | M36: 52483412 | N36: 60748 | O36: 68114489 | P36: 65248099 | Q36: 633608 | R36: 12331 | S36: 2 | T36: 5
A37: BANCO DA AMAZONIA S.A. | B37: 4902979 | C37: BCO DA AMAZONIA S.A. - PRUDENCIAL | E37: C0081249 | F37: b1 | G37: 1 | H37: 2 | I37: BELEM | J37: PA | K37: 06/2026 | L37: 67352881 | M37: 38713829 | N37: 21699434 | O37: 60078810 | P37: 15601132 | Q37: 7274071 | R37: 353060 | S37: 115 | T37: 0
A38: BANCO ABC BRASIL S.A. | B38: 28195667 | C38: ABC-BRASIL - PRUDENCIAL | D38: C0041856 | E38: C0080312 | F38: b1 | G38: 3 | H38: 8 | I38: SAO PAULO | J38: SP | K38: 06/2026 | L38: 66147427 | M38: 18520743 | N38: 29173812 | O38: 58888511 | P38: 50226679 | Q38: 7258915 | R38: 487535 | S38: 13 | T38: 0
A39: BANCO VOLKSWAGEN S.A. | B39: 59109165 | C39: VOLKSWAGEN - PRUDENCIAL | E39: C0080202 | F39: b2 | G39: 3 | H39: 8 | I39: SAO PAULO | J39: SP | K39: 06/2026 | L39: 61250495 | M39: 50345582 | N39: 819927 | O39: 55986251 | P39: 47916041 | Q39: 5264244 | R39: -203091 | S39: 2 | T39: 0
A40: BANCO BNP PARIBAS BRASIL S.A. | B40: 1522368 | C40: BNP PARIBAS - PRUDENCIAL | E40: C0080673 | F40: b1 | G40: 3 | H40: 8 | I40: SAO PAULO | J40: SP | K40: 06/2026 | L40: 58787929 | M40: 6716037 | N40: 21646070 | O40: 54077310 | P40: 34516225 | Q40: 4710619 | R40: 86546 | S40: 2 | T40: 0
A41: BANCO C6 CONSIGNADO S.A. | B41: 61348538 | C41: BANCO C6 - PRUDENCIAL | D41: C0052072 | E41: C0084844 | F41: b1 | G41: 2 | H41: 8 | I41: SAO PAULO | J41: SP | K41: 06/2026 | L41: 56164263 | M41: 42537256 | N41: 7432727 | O41: 52511688 | P41: 39443515 | Q41: 3652575 | R41: 559375 | S41: 2 | T41: 0
A42: BANCO RABOBANK INTERNATIONAL BRASIL S.A. | B42: 1023570 | C42: BCO RABOBANK INTL BRASIL S.A. - PRUDENCIAL | E42: C0081555 | F42: b1 | G42: 3 | H42: 8 | I42: SAO PAULO | J42: SP | K42: 06/2026 | L42: 54678970 | M42: 37932273 | N42: 7485572 | O42: 48983962 | P42: 44719472 | Q42: 5695008 | R42: 270816 | S42: 19 | T42: 0
A43: BANCOSEGURO S.A. | B43: 10264663 | C43: PAGSEGURO - PRUDENCIAL | D43: C0052182 | E43: C0084813 | F43: b1 | G43: 2 | H43: 8 | I43: SAO PAULO | J43: SP | K43: 06/2026 | L43: 52291197 | M43: 47649262 | N43: 355175 | O43: 50569304 | P43: 50254095 | Q43: 1721893 | R43: 66118 | S43: 2 | T43: 0
A44: BANCO AGIBANK S.A. | B44: 10664513 | C44: AGIBANK - PRUDENCIAL | D44: C0051956 | E44: C0083694 | F44: b1 | G44: 3 | H44: 2 | I44: CAMPINAS | J44: SP | K44: 06/2026 | L44: 51241770 | M44: 34675580 | N44: 10607480 | O44: 47809811 | P44: 31576717 | Q44: 3431960 | R44: 167735 | S44: 2 | T44: 340
A45: BANCO BMG S.A. | B45: 61186680 | C45: BMG - PRUDENCIAL | D45: C0030290 | E45: C0080178 | F45: b1 | G45: 2 | H45: 8 | I45: SAO PAULO | J45: SP | K45: 06/2026 | L45: 50846808 | M45: 21352794 | N45: 13897187 | O45: 46527758 | P45: 37011430 | Q45: 4319050 | R45: 304550 | S45: 27 | T45: 2
A46: PICPAY BANK - BANCO MÚLTIPLO S.A | B46: 9516419 | C46: PICPAY - PRUDENCIAL | D46: C0052632 | E46: C0088022 | F46: b1 | G46: 2 | H46: 8 | I46: SAO PAULO | J46: SP | K46: 06/2026 | L46: 48954093 | M46: 28852169 | N46: 10196292 | O46: 46414805 | P46: 34871092 | Q46: 2539288 | R46: 8433 | S46: 2 | T46: 0
A47: BANCO MERCANTIL DO BRASIL S.A. | B47: 17184037 | C47: MERCANTIL DO BRASIL - PRUDENCIAL | D47: C0020152 | E47: C0080123 | F47: b1 | G47: 2 | H47: 8 | I47: BELO HORIZONTE | J47: MG | K47: 06/2026 | L47: 43054391 | M47: 23085077 | N47: 4252511 | O47: 39931439 | P47: 31586492 | Q47: 3122951 | R47: 548541 | S47: 3 | T47: 298
A48: BANESTES S.A. BANCO DO ESTADO DO ESPIRITO SANTO | B48: 28127603 | C48: BANESTES - PRUDENCIAL | D48: C0030159 | E48: C0080147 | F48: b1 | G48: 1 | H48: 8 | I48: VITORIA | J48: ES | K48: 06/2026 | L48: 42689901 | M48: 12460035 | N48: 21316783 | O48: 40185159 | P48: 38716345 | Q48: 2504742 | R48: 226057 | S48: 86 | T48: 63
A49: BANCO CLASSICO S.A. | B49: 31597552 | C49: BCO CLASSICO S.A. - PRUDENCIAL | E49: C0081665 | F49: b1 | G49: 2 | H49: 8 | I49: RIO DE JANEIRO | J49: RJ | K49: 06/2026 | L49: 40612776 | M49: 0 | N49: 34521002 | O49: 19060286 | P49: 5629524 | Q49: 21552491 | R49: 52934 | S49: 2 | T49: 0
A50: BANK OF AMERICA MERRILL LYNCH BANCO MÚLTIPLO S.A. | B50: 62073200 | C50: BOFA MERRILL LYNCH - PRUDENCIAL | D50: C0051255 | E50: C0080556 | F50: b1 | G50: 3 | H50: 8 | I50: SAO PAULO | J50: SP | K50: 06/2026 | L50: 40609859 | M50: 2646247 | N50: 13444360 | O50: 33810603 | P50: 22340451 | Q50: 6799255 | R50: 511110 | S50: 2 | T50: 0
A51: BANCO PINE S.A. | B51: 62144175 | C51: PINE - PRUDENCIAL | D51: C0050304 | E51: C0080374 | F51: b1 | G51: 2 | H51: 8 | I51: SAO PAULO | J51: SP | K51: 06/2026 | L51: 37647108 | M51: 19314789 | N51: 13824794 | O51: 35844473 | P51: 31432120 | Q51: 1802635 | R51: 315564 | S51: 3 | T51: 0
A52: BANCO ORIGINAL S.A. | B52: 92894922 | C52: ORIGINAL - PRUDENCIAL | E52: C0080903 | F52: b1 | G52: 2 | H52: 8 | I52: SAO PAULO | J52: SP | K52: 06/2026 | L52: 37169761 | M52: 17893178 | N52: 6467856 | O52: 34845614 | P52: 32608252 | Q52: 2324147 | R52: 156076 | S52: 2 | T52: 0
A53: COOPERATIVA CENTRAL DE CRÉDITO DE MINAS GERAIS LTDA. - SICOOB CENTRAL CREDIMINAS | B53: 25683434 | F53: b3C | G53: 2 | H53: 9 | I53: BELO HORIZONTE | J53: MG | K53: 06/2026 | L53: 34542515 | M53: 93624 | N53: 16768612 | O53: 32723827 | P53: 884328 | Q53: 1818687 | R53: 118531 | S53: 0 | T53: 0
A54: GOLDMAN SACHS DO BRASIL BANCO MULTIPLO S.A. | B54: 4332281 | C54: GOLDMAN SACHS - PRUDENCIAL | D54: C0051585 | E54: C0080714 | F54: b2 | G54: 3 | H54: 8 | I54: SAO PAULO | J54: SP | K54: 06/2026 | L54: 34267958 | M54: 5685 | N54: 20186889 | O54: 28404250 | P54: 14608413 | Q54: 5863708 | R54: 686226 | S54: 2 | T54: 0
A55: STONE SOCIEDADE DE CREDITO, FINANCIAMENTO E INVESTIMENTO S.A. | B55: 53505601 | C55: STONE IP - PRUDENCIAL | D55: C0084686 | E55: C0084686 | F55: n1 | G55: 3 | H55: 14 | I55: SAO PAULO | J55: SP | K55: 06/2026 | L55: 33803605 | M55: 30264738 | N55: 32559 | O55: 33678082 | P55: 33153032 | Q55: 125523 | R55: 46816 | S55: 2 | T55: 0
A56: SAFRA SOCIEDADE DE CRÉDITO, FINANCIAMENTO E INVESTIMENTO S.A. | B56: 45437547 | C56: SAFRA - PRUDENCIAL | D56: C0010083 | E56: C0080109 | F56: n1 | G56: 2 | H56: 14 | I56: SAO PAULO | J56: SP | K56: 06/2026 | L56: 33188402 | M56: 21325158 | N56: 1657536 | O56: 32730969 | P56: 32013875 | Q56: 457433 | R56: 74616 | S56: 2 | T56: 0
A57: BANCO BOCOM BBM S.A. | B57: 15114366 | C57: BOCOM - PRUDENCIAL | D57: C0052003 | E57: C0084624 | F57: b1 | G57: 3 | H57: 8 | I57: SALVADOR | J57: BA | K57: 06/2026 | L57: 32001928 | M57: 14049138 | N57: 8031598 | O57: 30176603 | P57: 27817408 | Q57: 1825324 | R57: 257821 | S57: 4 | T57: 0
A58: BANCO REGIONAL DE DESENVOLVIMENTO DO EXTREMO SUL | B58: 92816560 | C58: BD REGIONAL DO EXTREMO SUL - PRUDENCIAL | E58: C0081311 | F58: b4 | G58: 1 | H58: 5 | I58: PORTO ALEGRE | J58: RS | K58: 06/2026 | L58: 30944445 | M58: 24677869 | N58: 5511980 | O58: 25160827 | P58: 23606986 | Q58: 5783618 | R58: 315733 | S58: 4 | T58: 0
A59: COOPERATIVA CENTRAL DE CRÉDITO DE SANTA CATARINA E RIO GRANDE DO SUL - SICOOB CENTRAL SC/RS | B59: 80160260 | F59: b3C | G59: 2 | H59: 9 | I59: FLORIANOPOLIS | J59: SC | K59: 06/2026 | L59: 29002304 | M59: 302641 | N59: 5844789 | O59: 27464682 | P59: 681810 | Q59: 1537622 | R59: 73985 | S59: 0 | T59: 0
A60: BANCO DIGIO S.A. | B60: 27098060 | C60: BRADESCO - PRUDENCIAL | D60: C0010045 | E60: C0080075 | F60: b2 | G60: 2 | H60: 8 | I60: OSASCO | J60: SP | K60: 06/2026 | L60: 28060664 | M60: 20228053 | N60: 2336309 | O60: 28005231 | P60: 25773075 | Q60: 55433 | R60: -219706 | S60: 2 | T60: 0
A61: CENTRAL DAS COOPERATIVAS DE ECONOMIA E CREDITO DO ESTADO DE MINAS GERAIS LTDA. - SICOOB CENTRAL CECREMGE | B61: 309024 | F61: b3C | G61: 2 | H61: 9 | I61: BELO HORIZONTE | J61: MG | K61: 06/2026 | L61: 27630783 | M61: 643420 | N61: 10514846 | O61: 26627866 | P61: 0 | Q61: 1002917 | R61: 50294 | S61: 0 | T61: 0
A62: CITIBANK N.A. | B62: 33042953 | C62: CITIBANK - PRUDENCIAL | D62: C0030403 | E62: C0080192 | F62: b1 | G62: 3 | H62: 28 | I62: SAO PAULO | J62: SP | K62: 06/2026 | L62: 26282572 | M62: 15968 | N62: 2311009 | O62: 21074114 | P62: 15553292 | Q62: 5208458 | R62: 341539 | S62: 2 | T62: 0
A63: PORTOSEG S.A. - CREDITO, FINANCIAMENTO E INVESTIMENTO | B63: 4862600 | C63: PORTO SEGURO - PRUDENCIAL | D63: C0051444 | E63: C0080642 | F63: n1 | G63: 2 | H63: 14 | I63: SAO PAULO | J63: SP | K63: 06/2026 | L63: 25524629 | M63: 20556575 | N63: 2421316 | O63: 24209822 | P63: 6946052 | Q63: 1314807 | R63: -32886 | S63: 2 | T63: 0
A64: BANCO CNH INDUSTRIAL CAPITAL S.A. | B64: 2992446 | C64: BANCO CNH INDUSTRIAL CAPITAL S.A - PRUDENCIAL | E64: C0081407 | F64: b2 | G64: 3 | H64: 8 | I64: CURITIBA | J64: PR | K64: 06/2026 | L64: 24178316 | M64: 20416836 | N64: 1306 | O64: 21566756 | P64: 19821707 | Q64: 2611560 | R64: -99496 | S64: 2 | T64: 0
A65: BANCO CSF S.A. | B65: 8357240 | C65: BCO CSF S.A. - PRUDENCIAL | E65: C0081610 | F65: b2 | G65: 2 | H65: 8 | I65: SAO PAULO | J65: SP | K65: 06/2026 | L65: 23818077 | M65: 18220416 | N65: 1536756 | O65: 20380331 | P65: 4877271 | Q65: 3437746 | R65: 300157 | S65: 2 | T65: 0
A66: BANCO NACIONAL S.A. | B66: 17157777 | C66: BTG PACTUAL - PRUDENCIAL | D66: C0049944 | E66: C0080336 | F66: b2 | G66: 2 | H66: 8 | I66: RIO DE JANEIRO | J66: RJ | K66: 06/2026 | L66: 23199020 | M66: 362369 | N66: 198133 | O66: 11829743 | P66: 5909715 | Q66: 11369277 | R66: 1828643 | S66: 1 | T66: 0
A67: MERCADO CRÉDITO SOCIEDADE DE CRÉDITO, FINANCIAMENTO E INVESTIMENTO S.A. | B67: 37679449 | C67: MERCADO PAGO IP - PRUDENCIAL | D67: C0084820 | E67: C0084820 | F67: n1 | G67: 3 | H67: 14 | I67: OSASCO | J67: SP | K67: 06/2026 | L67: 23031915 | M67: 11218909 | N67: 3421828 | O67: 19040377 | P67: 15365256 | Q67: 3991538 | R67: 293857 | S67: 2 | T67: 0
A68: BANCO FIBRA S.A. | B68: 58616418 | C68: BCO FIBRA S.A. - PRUDENCIAL | E68: C0081483 | F68: b1 | G68: 2 | H68: 8 | I68: SAO PAULO | J68: SP | K68: 06/2026 | L68: 22655142 | M68: 5556997 | N68: 12148350 | O68: 21200920 | P68: 19896779 | Q68: 1454222 | R68: 154451 | S68: 2 | T68: 0
A69: CLOUDWALK INSTITUIÇÃO DE PAGAMENTO E SERVICOS LTDA | B69: 18189547 | C69: CLOUDWALK IP - PRUDENCIAL | E69: C0086581 | F69: n4 | G69: 2 | H69: 41 | I69: SAO PAULO | J69: SP | K69: 06/2026 | L69: 22593972 | M69: 0 | N69: 819519 | O69: 20277561 | P69: 1355863 | Q69: 2316411 | R69: 552378 | S69: 1 | T69: 0
A70: DEUTSCHE BANK S.A. - BANCO ALEMAO | B70: 62331228 | C70: DEUTSCHE - PRUDENCIAL | E70: C0080532 | F70: b1 | G70: 3 | H70: 8 | I70: SAO PAULO | J70: SP | K70: 06/2026 | L70: 21745428 | M70: 3777593 | N70: 9872679 | O70: 18666470 | P70: 15460387 | Q70: 3078957 | R70: 101246 | S70: 2 | T70: 0
A71: STELLANTIS FINANCIAMENTOS SOCIEDADE DE CRÉDITO, FINANCIAMENTO E INVESTIMENTO S.A | B71: 3502961 | C71: STELLANTIS - PRUDENCIAL | D71: C0052508 | E71: C0087298 | F71: n1 | G71: 3 | H71: 14 | I71: SAO PAULO | J71: SP | K71: 06/2026 | L71: 21539454 | M71: 18478169 | N71: 750647 | O71: 18535784 | P71: 17973893 | Q71: 3003670 | R71: 119318 | S71: 2 | T71: 0
A72: BANCO DO ESTADO DO PARÁ S.A. | B72: 4913711 | C72: BCO DO EST. DO PA S.A. - PRUDENCIAL | E72: C0081586 | F72: b1 | G72: 1 | H72: 8 | I72: BELEM | J72: PA | K72: 06/2026 | L72: 21444615 | M72: 15444766 | N72: 1420567 | O72: 19200343 | P72: 18223337 | Q72: 2244272 | R72: 100805 | S72: 165 | T72: 34
A73: BANCO MERCEDES-BENZ DO BRASIL S.A. | B73: 60814191 | C73: MERCEDES-BENZ - PRUDENCIAL | D73: C0051262 | E73: C0080563 | F73: b2 | G73: 3 | H73: 8 | I73: SAO BERNARDO DO CAMPO | J73: SP | K73: 06/2026 | L73: 20853819 | M73: 19284332 | N73: 317664 | O73: 18430109 | P73: 17728172 | Q73: 2423711 | R73: 39490 | S73: 2 | T73: 0
A74: BANCO CRÉDIT AGRICOLE BRASIL S.A. | B74: 75647891 | C74: CREDIT AGRICOLE - PRUDENCIAL | E74: C0080491 | F74: b1 | G74: 3 | H74: 8 | I74: SAO PAULO | J74: SP | K74: 06/2026 | L74: 20150414 | M74: 8746825 | N74: 4002938 | O74: 15955785 | P74: 14040180 | Q74: 4194628 | R74: 137358 | S74: 2 | T74: 0
A75: LUIZACRED S.A. SOCIEDADE DE CRÉDITO, FINANCIAMENTO E INVESTIMENTO | B75: 2206577 | C75: ITAU - PRUDENCIAL | D75: C0010069 | E75: C0080099 | F75: n1 | G75: 2 | H75: 14 | I75: SAO PAULO | J75: SP | K75: 06/2026 | L75: 19422651 | M75: 17848013 | N75: 26208 | O75: 17177854 | P75: 3392857 | Q75: 2244797 | R75: 218800 | S75: 2 | T75: 0
A76: BRADESCO LEASING S.A. - ARRENDAMENTO MERCANTIL | B76: 47509120 | C76: BRADESCO - PRUDENCIAL | D76: C0010045 | E76: C0080075 | F76: n1 | G76: 2 | H76: 19 | I76: OSASCO | J76: SP | K76: 06/2026 | L76: 19322032 | M76: 8085279 | N76: 9678666 | O76: 14638157 | P76: 13099402 | Q76: 4683875 | R76: 238141 | S76: 2 | T76: 0
A77: COOPERATIVA CENTRAL DE CRÉDITO DO ESTADO DE SÃO PAULO - SICOOB SÃO PAULO | B77: 63917579 | F77: b3C | G77: 2 | H77: 9 | I77: RIBEIRAO PRETO | J77: SP | K77: 06/2026 | L77: 19289667 | M77: 0 | N77: 6723730 | O77: 18358775 | P77: 1544428 | Q77: 930893 | R77: 61944 | S77: 0 | T77: 0
A78: BTG PACTUAL CORRETORA DE TÍTULOS E VALORES MOBILIÁRIOS S.A. | B78: 43815158 | C78: BTG PACTUAL - PRUDENCIAL | D78: C0049944 | E78: C0080336 | F78: n2 | G78: 2 | H78: 15 | I78: RIO DE JANEIRO | J78: RJ | K78: 06/2026 | L78: 19186457 | M78: 0 | N78: 1113824 | O78: 18159300 | P78: 325053 | Q78: 1027158 | R78: 180891 | S78: 6 | T78: 0
A79: COOPERATIVA DE CREDITO CREDICITRUS | B79: 54037916 | F79: b3S | G79: 2 | H79: 9 | I79: BEBEDOURO | J79: SP | K79: 06/2026 | L79: 18797895 | M79: 9038341 | N79: 3840257 | O79: 15102280 | P79: 13307188 | Q79: 3695615 | R79: 164239 | S79: 0 | T79: 127
A80: BR PARTNERS BANCO DE INVESTIMENTO S.A. | B80: 13220493 | C80: BR PARTNERS - PRUDENCIAL | E80: C0080934 | F80: b2 | G80: 2 | H80: 13 | I80: SAO PAULO | J80: SP | K80: 06/2026 | L80: 18254444 | M80: 178232 | N80: 16606264 | O80: 17676436 | P80: 16192670 | Q80: 578008 | R80: -4635 | S80: 2 | T80: 0
A81: BANCO GM S.A. | B81: 59274605 | C81: GM - PRUDENCIAL | E81: C0080848 | F81: b2 | G81: 3 | H81: 8 | I81: SAO PAULO | J81: SP | K81: 06/2026 | L81: 18035945 | M81: 13773333 | N81: 162166 | O81: 15113876 | P81: 13229613 | Q81: 2922069 | R81: 277328 | S81: 2 | T81: 0
A82: BANCO SOFISA S.A. | B82: 60889128 | C82: SOFISA - PRUDENCIAL | D82: C0031873 | E82: C0080271 | F82: b1 | G82: 2 | H82: 8 | I82: SAO PAULO | J82: SP | K82: 06/2026 | L82: 17860040 | M82: 7681224 | N82: 8389223 | O82: 16702237 | P82: 15763634 | Q82: 1157803 | R82: 39612 | S82: 24 | T82: 0
A83: COOPERATIVA CENTRAL DE CRÉDITO COM INTERAÇÃO SOLIDÁRIA - CENTRAL CRESOL BASER | B83: 1401771 | F83: b3C | G83: 2 | H83: 9 | I83: FRANCISCO BELTRAO | J83: PR | K83: 06/2026 | L83: 17754461 | M83: 99057 | N83: 4187898 | O83: 16966332 | P83: 10293913 | Q83: 788128 | R83: 57735 | S83: 0 | T83: 0
A84: COOPERATIVA CENTRAL DE CRÉDITO UNICRED DO BRASIL - UNICRED DO BRASIL | B84: 315557 | F84: b3C | G84: 2 | H84: 9 | I84: SAO PAULO | J84: SP | K84: 06/2026 | L84: 17572425 | M84: 0 | N84: 9733269 | O84: 16799091 | P84: 58 | Q84: 773335 | R84: 41955 | S84: 0 | T84: 1
A85: COOPERATIVA DE CREDITO VALE DO ITAJAI - VIACREDI | B85: 82639451 | F85: b3S | G85: 2 | H85: 9 | I85: BLUMENAU | J85: SC | K85: 06/2026 | L85: 17524030 | M85: 8725675 | N85: 721306 | O85: 13841312 | P85: 12675486 | Q85: 3682717 | R85: 405343 | S85: 0 | T85: 119
A86: BANCO JOHN DEERE S.A. | B86: 91884981 | C86: BRADESCO - PRUDENCIAL | D86: C0010045 | E86: C0080075 | F86: b1 | G86: 2 | H86: 8 | I86: OSASCO | J86: SP | K86: 06/2026 | L86: 16770609 | M86: 14635555 | N86: 30340 | O86: 12482523 | P86: 12310073 | Q86: 4288086 | R86: 65446 | S86: 2 | T86: 0
A87: BANCO BRADESCO BBI S.A. | B87: 6271464 | C87: BRADESCO - PRUDENCIAL | D87: C0010045 | E87: C0080075 | F87: b1 | G87: 2 | H87: 8 | I87: OSASCO | J87: SP | K87: 06/2026 | L87: 16757041 | M87: 0 | N87: 5081557 | O87: 10258524 | P87: 8516751 | Q87: 6498517 | R87: 803976 | S87: 5 | T87: 0
A88: SCOTIABANK BRASIL S.A. BANCO MÚLTIPLO | B88: 29030467 | C88: SCOTIABANK BRASIL - PRUDENCIAL | D88: C0052230 | E88: C0081452 | F88: b1 | G88: 3 | H88: 8 | I88: SAO PAULO | J88: SP | K88: 06/2026 | L88: 16750390 | M88: 2503686 | N88: 4358158 | O88: 13483132 | P88: 12778534 | Q88: 3267259 | R88: 156951 | S88: 2 | T88: 0
A89: BANCO MORGAN STANLEY S.A. | B89: 2801938 | C89: MORGAN STANLEY - PRUDENCIAL | D89: C0051413 | E89: C0080628 | F89: b1 | G89: 3 | H89: 8 | I89: SAO PAULO | J89: SP | K89: 06/2026 | L89: 16726636 | M89: 232468 | N89: 10148169 | O89: 11812063 | P89: 6524914 | Q89: 4914573 | R89: 315166 | S89: 2 | T89: 0
A90: BANCO HSBC S.A. | B90: 53518684 | C90: BANCO HSBC - PRUDENCIAL | E90: C0084741 | F90: b1 | G90: 3 | H90: 8 | I90: SAO PAULO | J90: SP | K90: 06/2026 | L90: 16666011 | M90: 5254439 | N90: 6256048 | O90: 15037777 | P90: 12899483 | Q90: 1628234 | R90: 91854 | S90: 2 | T90: 0
A91: BANK OF CHINA (BRASIL) BANCO MÚLTIPLO S/A | B91: 7450604 | C91: BANK OF CHINA (BRASIL) - PRUDENCIAL | D91: C0032119 | E91: C0080295 | F91: b1 | G91: 3 | H91: 8 | I91: SAO PAULO | J91: SP | K91: 06/2026 | L91: 16639710 | M91: 7784956 | N91: 5876990 | O91: 15385491 | P91: 14157109 | Q91: 1254219 | R91: -26542 | S91: 8 | T91: 0
A92: BANCO RCI BRASIL S.A. | B92: 62307848 | C92: SANTANDER - PRUDENCIAL | D92: C0030379 | E92: C0080185 | F92: b2 | G92: 3 | H92: 8 | I92: SAO PAULO | J92: SP | K92: 06/2026 | L92: 16401701 | M92: 10365397 | N92: 4387693 | O92: 14986286 | P92: 13736063 | Q92: 1415415 | R92: 149582 | S92: 2 | T92: 0
A93: BANCO VOLVO BRASIL S.A. | B93: 58017179 | C93: VOLVO - PRUDENCIAL | E93: C0080769 | F93: b2 | G93: 3 | H93: 8 | I93: CURITIBA | J93: PR | K93: 06/2026 | L93: 16337893 | M93: 14011636 | N93: 1158021 | O93: 12164690 | P93: 12024746 | Q93: 4173203 | R93: 198482 | S93: 2 | T93: 0
A94: BANCO STELLANTIS S.A. | B94: 62237425 | C94: STELLANTIS - PRUDENCIAL | D94: C0052508 | E94: C0087298 | F94: b2 | G94: 3 | H94: 8 | I94: SAO PAULO | J94: SP | K94: 06/2026 | L94: 15786564 | M94: 7362599 | N94: 439799 | O94: 14258835 | P94: 13973289 | Q94: 1527729 | R94: 135403 | S94: 2 | T94: 0
A95: COOPERATIVA DE CRÉDITO, POUPANÇA E INVESTIMENTO DEXIS - SICREDI DEXIS | B95: 79342069 | F95: b3S | G95: 2 | H95: 9 | I95: MARINGA | J95: PR | K95: 06/2026 | L95: 15763618 | M95: 8895732 | N95: 5471429 | O95: 14298311 | P95: 9139325 | Q95: 1465307 | R95: 88996 | S95: 0 | T95: 114
A96: KIRTON BANK S.A. - BANCO MÚLTIPLO | B96: 1701201 | C96: BRADESCO - PRUDENCIAL | D96: C0010045 | E96: C0080075 | F96: b1 | G96: 2 | H96: 8 | I96: OSASCO | J96: SP | K96: 06/2026 | L96: 15529831 | M96: 0 | N96: 4250 | O96: 3698093 | P96: 2427709 | Q96: 11831737 | R96: 377737 | S96: 1 | T96: 0
A97: BANCO BRADESCARD S.A. | B97: 4184779 | C97: BRADESCO - PRUDENCIAL | D97: C0010045 | E97: C0080075 | F97: b1 | G97: 2 | H97: 8 | I97: OSASCO | J97: SP | K97: 06/2026 | L97: 15522406 | M97: 8283770 | N97: 18 | O97: 15413267 | P97: 7112832 | Q97: 109139 | R97: 1536 | S97: 2 | T97: 0
A98: BANCO DE DESENVOLVIMENTO DE MINAS GERAIS S.A.-BDMG | B98: 38486817 | C98: BCO DES. DE MG S.A. - PRUDENCIAL | E98: C0081328 | F98: b4 | G98: 1 | H98: 5 | I98: BELO HORIZONTE | J98: MG | K98: 06/2026 | L98: 15427555 | M98: 9253331 | N98: 4175546 | O98: 12945523 | P98: 11810887 | Q98: 2482032 | R98: 71599 | S98: 2 | T98: 0
A99: COOPERATIVA CENTRAL DE CREDITO DO ESPIRITO SANTO - SICOOB CENTRAL ES | B99: 32428294 | F99: b3C | G99: 2 | H99: 9 | I99: VITORIA | J99: ES | K99: 06/2026 | L99: 15057607 | M99: 124827 | N99: 4108110 | O99: 14252356 | P99: 282392 | Q99: 805251 | R99: 19394 | S99: 0 | T99: 0
A100: BANCO MIZUHO DO BRASIL S.A. | B100: 61088183 | C100: MIZUHO - PRUDENCIAL | E100: C0080697 | F100: b1 | G100: 3 | H100: 8 | I100: SAO PAULO | J100: SP | K100: 06/2026 | L100: 15033171 | M100: 3270316 | N100: 5891940 | O100: 13699571 | P100: 12505201 | Q100: 1333599 | R100: 40301 | S100: 2 | T100: 0
A101: COOPERATIVA CENTRAL DE CRÉDITO - AILOS | B101: 5463212 | F101: b3C | G101: 2 | H101: 9 | I101: BLUMENAU | J101: SC | K101: 06/2026 | L101: 15013283 | M101: 867026 | N101: 10349258 | O101: 13955963 | P101: 2549732 | Q101: 1057321 | R101: 0 | S101: 0 | T101: 0
...

Sheet Base_IFData
A1: BASE DE DADOS | IFData Junho 2026
A2: Fonte: IF.data, Banco Central do Brasil (https://www3.bcb.gov.br/ifdata)
A4: Instituição | B4: Código | C4: Conglomerado Prudencial (Nome) | D4: Conglomerado Financeiro (Cód.) | E4: Conglomerado Prudencial (Cód.) | F4: TCB | G4: TC | H4: TI | I4: Cidade | J4: UF | K4: Data | L4: Ativo Total (R$ mil) | M4: Carteira de Crédito (R$ mil) | N4: Títulos e Valores Mobiliários (R$ mil) | O4: Passivo Exigível (R$ mil) | P4: Captações (R$ mil) | Q4: Patrimônio Líquido (R$ mil) | R4: Lucro Líquido (R$ mil) | S4: Número de Agências | T4: Postos de Atendimento | U4: Tipo de Controle | V4: Índice Crédito/Ativo | W4: ROE do semestre | X4: Porte | Y4: Classe ROE
A5: BANCO DO BRASIL S.A. | B5: 0 | C5: BB - PRUDENCIAL | D5: C0049906 | E5: C0080329 | F5: b1 | G5: 1 | H5: 1 | I5: BRASILIA | J5: DF | K5: 06/2026 | L5: 2461086914 | M5: 1065710905 | N5: 714731784 | O5: 2279753810 | P5: 1974660924 | Q5: 181333105 | R5: 6216056 | S5: 3932 | T5: 309 | U5: =IFERROR(CHOOSE(G5,"Público","Privado Nacional","Privado Estrangeiro"),"n.d.") -> Público | V5: =IF(AND(ISNUMBER(M5),ISNUMBER(L5)),IF(L5>0,M5/L5,"n.d."),"NI") -> 0.43302449 | W5: =IF(AND(ISNUMBER(R5),ISNUMBER(Q5)),IF(Q5>0,R5/Q5,"n.d."),"NI") -> 0.034279764 | X5: =IF(ISNUMBER(L5),IF(L5>100000000,"Grande","Média/Pequena"),"Sem dado") -> Grande | Y5: {=_xlfn.IFS(ISNUMBER(W5)=FALSE,"Sem dado",W5>0.075,"Excelente",W5>0.04,"Bom",W5>0,"Fraco",TRUE,"Prejuízo")} -> Fraco
A6: CAIXA ECONOMICA FEDERAL | B6: 360305 | C6: CAIXA ECONÔMICA FEDERAL - PRUDENCIAL | D6: C0051626 | E6: C0080738 | F6: b1 | G6: 1 | H6: 6 | I6: BRASILIA | J6: DF | K6: 06/2026 | L6: 2368147225 | M6: 1362330927 | N6: 452416774 | O6: 2249779433 | P6: 2063880327 | Q6: 118367792 | R6: 6585794 | S6: 3000 | T6: 868 | U6: =IFERROR(CHOOSE(G6,"Público","Privado Nacional","Privado Estrangeiro"),"n.d.") -> Público | V6: =IF(AND(ISNUMBER(M6),ISNUMBER(L6)),IF(L6>0,M6/L6,"n.d."),"NI") -> 0.5752729 | W6: =IF(AND(ISNUMBER(R6),ISNUMBER(Q6)),IF(Q6>0,R6/Q6,"n.d."),"NI") -> 0.055638395 | X6: =IF(ISNUMBER(L6),IF(L6>100000000,"Grande","Média/Pequena"),"Sem dado") -> Grande | Y6: {=_xlfn.IFS(ISNUMBER(W6)=FALSE,"Sem dado",W6>0.075,"Excelente",W6>0.04,"Bom",W6>0,"Fraco",TRUE,"Prejuízo")} -> Bom
A7: ITAÚ UNIBANCO S.A. | B7: 60701190 | C7: ITAU - PRUDENCIAL | D7: C0010069 | E7: C0080099 | F7: b1 | G7: 2 | H7: 8 | I7: SAO PAULO | J7: SP | K7: 06/2026 | L7: 2169409565 | M7: 700105223 | N7: 559549223 | O7: 2006548179 | P7: 1842394345 | Q7: 162861385 | R7: 19759837 | S7: 1345 | T7: 1403 | U7: =IFERROR(CHOOSE(G7,"Público","Privado Nacional","Privado Estrangeiro"),"n.d.") -> Privado Nacional | V7: =IF(AND(ISNUMBER(M7),ISNUMBER(L7)),IF(L7>0,M7/L7,"n.d."),"NI") -> 0.32271694 | W7: =IF(AND(ISNUMBER(R7),ISNUMBER(Q7)),IF(Q7>0,R7/Q7,"n.d."),"NI") -> 0.12132917 | X7: =IF(ISNUMBER(L7),IF(L7>100000000,"Grande","Média/Pequena"),"Sem dado") -> Grande | Y7: {=_xlfn.IFS(ISNUMBER(W7)=FALSE,"Sem dado",W7>0.075,"Excelente",W7>0.04,"Bom",W7>0,"Fraco",TRUE,"Prejuízo")} -> Excelente
A8: BANCO BRADESCO S.A. | B8: 60746948 | C8: BRADESCO - PRUDENCIAL | D8: C0010045 | E8: C0080075 | F8: b1 | G8: 2 | H8: 8 | I8: OSASCO | J8: SP | K8: 06/2026 | L8: 1952464273 | M8: 756014814 | N8: 322119751 | O8: 1777233946 | P8: 1545720299 | Q8: 175230327 | R8: 12080064 | S8: 2026 | T8: 762 | U8: =IFERROR(CHOOSE(G8,"Público","Privado Nacional","Privado Estrangeiro"),"n.d.") -> Privado Nacional | V8: =IF(AND(ISNUMBER(M8),ISNUMBER(L8)),IF(L8>0,M8/L8,"n.d."),"NI") -> 0.38721058 | W8: =IF(AND(ISNUMBER(R8),ISNUMBER(Q8)),IF(Q8>0,R8/Q8,"n.d."),"NI") -> 0.068938204 | X8: =IF(ISNUMBER(L8),IF(L8>100000000,"Grande","Média/Pequena"),"Sem dado") -> Grande | Y8: {=_xlfn.IFS(ISNUMBER(W8)=FALSE,"Sem dado",W8>0.075,"Excelente",W8>0.04,"Bom",W8>0,"Fraco",TRUE,"Prejuízo")} -> Bom
A9: BANCO SANTANDER (BRASIL) S.A. | B9: 90400888 | C9: SANTANDER - PRUDENCIAL | D9: C0030379 | E9: C0080185 | F9: b1 | G9: 3 | H9: 8 | I9: SAO PAULO | J9: SP | K9: 06/2026 | L9: 1209443083 | M9: 365285710 | N9: 260716671 | O9: 1110706856 | P9: 953249578 | Q9: 98736227 | R9: 7382760 | S9: 1196 | T9: 2516 | U9: =IFERROR(CHOOSE(G9,"Público","Privado Nacional","Privado Estrangeiro"),"n.d.") -> Privado Estrangeiro | V9: =IF(AND(ISNUMBER(M9),ISNUMBER(L9)),IF(L9>0,M9/L9,"n.d."),"NI") -> 0.30202803 | W9: =IF(AND(ISNUMBER(R9),ISNUMBER(Q9)),IF(Q9>0,R9/Q9,"n.d."),"NI") -> 0.074772555 | X9: =IF(ISNUMBER(L9),IF(L9>100000000,"Grande","Média/Pequena"),"Sem dado") -> Grande | Y9: {=_xlfn.IFS(ISNUMBER(W9)=FALSE,"Sem dado",W9>0.075,"Excelente",W9>0.04,"Bom",W9>0,"Fraco",TRUE,"Prejuízo")} -> Bom
A10: BANCO NACIONAL DE DESENVOLVIMENTO ECONOMICO E SOCIAL | B10: 33657248 | C10: BNDES - PRUDENCIAL | E10: C0081847 | F10: b4 | G10: 1 | H10: 4 | I10: RIO DE JANEIRO | J10: RJ | K10: 06/2026 | L10: 1073403746 | M10: 375703869 | N10: 209161034 | O10: 892700475 | P10: 661452493 | Q10: 180703272 | R10: 11153448 | S10: 5 | T10: 0 | U10: =IFERROR(CHOOSE(G10,"Público","Privado Nacional","Privado Estrangeiro"),"n.d.") -> Público | V10: =IF(AND(ISNUMBER(M10),ISNUMBER(L10)),IF(L10>0,M10/L10,"n.d."),"NI") -> 0.3500117 | W10: =IF(AND(ISNUMBER(R10),ISNUMBER(Q10)),IF(Q10>0,R10/Q10,"n.d."),"NI") -> 0.061722446 | X10: =IF(ISNUMBER(L10),IF(L10>100000000,"Grande","Média/Pequena"),"Sem dado") -> Grande | Y10: {=_xlfn.IFS(ISNUMBER(W10)=FALSE,"Sem dado",W10>0.075,"Excelente",W10>0.04,"Bom",W10>0,"Fraco",TRUE,"Prejuízo")} -> Bom
A11: BANCO BTG PACTUAL S.A. | B11: 30306294 | C11: BTG PACTUAL - PRUDENCIAL | D11: C0049944 | E11: C0080336 | F11: b1 | G11: 2 | H11: 8 | I11: RIO DE JANEIRO | J11: RJ | K11: 06/2026 | L11: 743258957 | M11: 81617597 | N11: 228588076 | O11: 663705470 | P11: 548000573 | Q11: 79553487 | R11: 9471540 | S11: 28 | T11: 0 | U11: =IFERROR(CHOOSE(G11,"Público","Privado Nacional","Privado Estrangeiro"),"n.d.") -> Privado Nacional | V11: =IF(AND(ISNUMBER(M11),ISNUMBER(L11)),IF(L11>0,M11/L11,"n.d."),"NI") -> 0.10981045 | W11: =IF(AND(ISNUMBER(R11),ISNUMBER(Q11)),IF(Q11>0,R11/Q11,"n.d."),"NI") -> 0.11905877 | X11: =IF(ISNUMBER(L11),IF(L11>100000000,"Grande","Média/Pequena"),"Sem dado") -> Grande | Y11: {=_xlfn.IFS(ISNUMBER(W11)=FALSE,"Sem dado",W11>0.075,"Excelente",W11>0.04,"Bom",W11>0,"Fraco",TRUE,"Prejuízo")} -> Excelente
A12: ITAÚ UNIBANCO HOLDING S.A. | B12: 60872504 | C12: ITAU - PRUDENCIAL | D12: C0010069 | E12: C0080099 | F12: b2 | G12: 2 | H12: 8 | I12: SAO PAULO | J12: SP | K12: 06/2026 | L12: 493183395 | M12: 172877389 | N12: 41855441 | O12: 285535078 | P12: 107861159 | Q12: 207648317 | R12: 23205024 | S12: 2 | T12: 7 | U12: =IFERROR(CHOOSE(G12,"Público","Privado Nacional","Privado Estrangeiro"),"n.d.") -> Privado Nacional | V12: =IF(AND(ISNUMBER(M12),ISNUMBER(L12)),IF(L12>0,M12/L12,"n.d."),"NI") -> 0.35053368 | W12: =IF(AND(ISNUMBER(R12),ISNUMBER(Q12)),IF(Q12>0,R12/Q12,"n.d."),"NI") -> 0.11175156 | X12: =IF(ISNUMBER(L12),IF(L12>100000000,"Grande","Média/Pequena"),"Sem dado") -> Grande | Y12: {=_xlfn.IFS(ISNUMBER(W12)=FALSE,"Sem dado",W12>0.075,"Excelente",W12>0.04,"Bom",W12>0,"Fraco",TRUE,"Prejuízo")} -> Excelente
A13: NU FINANCEIRA S.A. - SOCIEDADE DE CRÉDITO, FINANCIAMENTO E INVESTIMENTO | B13: 30680829 | C13: NU PAGAMENTOS - PRUDENCIAL | D13: C0052058 | E13: C0084693 | F13: n1 | G13: 3 | H13: 14 | I13: SAO PAULO | J13: SP | K13: 06/2026 | L13: 267624695 | M13: 76080601 | N13: 80369899 | O13: 252606112 | P13: 225759535 | Q13: 15018583 | R13: 4194823 | S13: 2 | T13: 0 | U13: =IFERROR(CHOOSE(G13,"Público","Privado Nacional","Privado Estrangeiro"),"n.d.") -> Privado Estrangeiro | V13: =IF(AND(ISNUMBER(M13),ISNUMBER(L13)),IF(L13>0,M13/L13,"n.d."),"NI") -> 0.28428094 | W13: =IF(AND(ISNUMBER(R13),ISNUMBER(Q13)),IF(Q13>0,R13/Q13,"n.d."),"NI") -> 0.27930884 | X13: =IF(ISNUMBER(L13),IF(L13>100000000,"Grande","Média/Pequena"),"Sem dado") -> Grande | Y13: {=_xlfn.IFS(ISNUMBER(W13)=FALSE,"Sem dado",W13>0.075,"Excelente",W13>0.04,"Bom",W13>0,"Fraco",TRUE,"Prejuízo")} -> Excelente
A14: BANCO SAFRA S.A. | B14: 58160789 | C14: SAFRA - PRUDENCIAL | D14: C0010083 | E14: C0080109 | F14: b1 | G14: 2 | H14: 8 | I14: SAO PAULO | J14: SP | K14: 06/2026 | L14: 256683465 | M14: 93167603 | N14: 46773165 | O14: 238676254 | P14: 204635211 | Q14: 18007212 | R14: 1885083 | S14: 133 | T14: 3 | U14: =IFERROR(CHOOSE(G14,"Público","Privado Nacional","Privado Estrangeiro"),"n.d.") -> Privado Nacional | V14: =IF(AND(ISNUMBER(M14),ISNUMBER(L14)),IF(L14>0,M14/L14,"n.d."),"NI") -> 0.36296691 | W14: =IF(AND(ISNUMBER(R14),ISNUMBER(Q14)),IF(Q14>0,R14/Q14,"n.d."),"NI") -> 0.10468489 | X14: =IF(ISNUMBER(L14),IF(L14>100000000,"Grande","Média/Pequena"),"Sem dado") -> Grande | Y14: {=_xlfn.IFS(ISNUMBER(W14)=FALSE,"Sem dado",W14>0.075,"Excelente",W14>0.04,"Bom",W14>0,"Fraco",TRUE,"Prejuízo")} -> Excelente
A15: BANCO COOPERATIVO SICREDI S.A. | B15: 1181521 | C15: BCO COOPERATIVO SICREDI - PRUDENCIAL | E15: C0080745 | F15: b1 | G15: 2 | H15: 11 | I15: PORTO ALEGRE | J15: RS | K15: 06/2026 | L15: 234406077 | M15: 50267293 | N15: 49289841 | O15: 228925803 | P15: 202089776 | Q15: 5480274 | R15: 162608 | S15: 6 | T15: 0 | U15: =IFERROR(CHOOSE(G15,"Público","Privado Nacional","Privado Estrangeiro"),"n.d.") -> Privado Nacional | V15: =IF(AND(ISNUMBER(M15),ISNUMBER(L15)),IF(L15>0,M15/L15,"n.d."),"NI") -> 0.21444535 | W15: =IF(AND(ISNUMBER(R15),ISNUMBER(Q15)),IF(Q15>0,R15/Q15,"n.d."),"NI") -> 0.029671509 | X15: =IF(ISNUMBER(L15),IF(L15>100000000,"Grande","Média/Pequena"),"Sem dado") -> Grande | Y15: {=_xlfn.IFS(ISNUMBER(W15)=FALSE,"Sem dado",W15>0.075,"Excelente",W15>0.04,"Bom",W15>0,"Fraco",TRUE,"Prejuízo")} -> Fraco
A16: BANCO COOPERATIVO SICOOB S.A. - BANCO SICOOB | B16: 2038232 | C16: BANCO SICOOB - PRUDENCIAL | D16: C0051750 | E16: C0080879 | F16: b1 | G16: 2 | H16: 11 | I16: BRASILIA | J16: DF | K16: 06/2026 | L16: 223159409 | M16: 44908980 | N16: 68401403 | O16: 216175011 | P16: 188203009 | Q16: 6984398 | R16: 458952 | S16: 5 | T16: 0 | U16: =IFERROR(CHOOSE(G16,"Público","Privado Nacional","Privado Estrangeiro"),"n.d.") -> Privado Nacional | V16: =IF(AND(ISNUMBER(M16),ISNUMBER(L16)),IF(L16>0,M16/L16,"n.d."),"NI") -> 0.20124171 | W16: =IF(AND(ISNUMBER(R16),ISNUMBER(Q16)),IF(Q16>0,R16/Q16,"n.d."),"NI") -> 0.065711032 | X16: =IF(ISNUMBER(L16),IF(L16>100000000,"Grande","Média/Pequena"),"Sem dado") -> Grande | Y16: {=_xlfn.IFS(ISNUMBER(W16)=FALSE,"Sem dado",W16>0.075,"Excelente",W16>0.04,"Bom",W16>0,"Fraco",TRUE,"Prejuízo")} -> Bom
A17: BANCO XP S.A. | B17: 33264668 | C17: XP - PRUDENCIAL | D17: C0052120 | E17: C0082475 | F17: b1 | G17: 2 | H17: 8 | I17: RIO DE JANEIRO | J17: RJ | K17: 06/2026 | L17: 221732251 | M17: 32257267 | N17: 75852463 | O17: 209296234 | P17: 169190938 | Q17: 12436018 | R17: 366732 | S17: 2 | T17: 0 | U17: =IFERROR(CHOOSE(G17,"Público","Privado Nacional","Privado Estrangeiro"),"n.d.") -> Privado Nacional | V17: =IF(AND(ISNUMBER(M17),ISNUMBER(L17)),IF(L17>0,M17/L17,"n.d."),"NI") -> 0.14547846 | W17: =IF(AND(ISNUMBER(R17),ISNUMBER(Q17)),IF(Q17>0,R17/Q17,"n.d."),"NI") -> 0.029489504 | X17: =IF(ISNUMBER(L17),IF(L17>100000000,"Grande","Média/Pequena"),"Sem dado") -> Grande | Y17: {=_xlfn.IFS(ISNUMBER(W17)=FALSE,"Sem dado",W17>0.075,"Excelente",W17>0.04,"Bom",W17>0,"Fraco",TRUE,"Prejuízo")} -> Fraco
A18: REDECARD INSTITUIÇÃO DE PAGAMENTO S.A. | B18: 1425787 | C18: ITAU - PRUDENCIAL | E18: C0080099 | F18: n4 | G18: 2 | H18: 41 | I18: SAO PAULO | J18: SP | K18: 06/2026 | L18: 178389094 | M18: 0 | N18: 18863330 | O18: 137181221 | P18: 16821616 | Q18: 41207873 | R18: 1497264 | S18: 1 | T18: 0 | U18: =IFERROR(CHOOSE(G18,"Público","Privado Nacional","Privado Estrangeiro"),"n.d.") -> Privado Nacional | V18: =IF(AND(ISNUMBER(M18),ISNUMBER(L18)),IF(L18>0,M18/L18,"n.d."),"NI") -> 0 | W18: =IF(AND(ISNUMBER(R18),ISNUMBER(Q18)),IF(Q18>0,R18/Q18,"n.d."),"NI") -> 0.036334416 | X18: =IF(ISNUMBER(L18),IF(L18>100000000,"Grande","Média/Pequena"),"Sem dado") -> Grande | Y18: {=_xlfn.IFS(ISNUMBER(W18)=FALSE,"Sem dado",W18>0.075,"Excelente",W18>0.04,"Bom",W18>0,"Fraco",TRUE,"Prejuízo")} -> Fraco
A19: BANCO DO ESTADO DO RIO GRANDE DO SUL S.A. | B19: 92702067 | C19: BANRISUL - PRUDENCIAL | D19: C0030173 | E19: C0080154 | F19: b1 | G19: 1 | H19: 8 | I19: PORTO ALEGRE | J19: RS | K19: 06/2026 | L19: 172827959 | M19: 60414676 | N19: 75506552 | O19: 161276935 | P19: 150456265 | Q19: 11551023 | R19: 546547 | S19: 506 | T19: 43 | U19: =IFERROR(CHOOSE(G19,"Público","Privado Nacional","Privado Estrangeiro"),"n.d.") -> Público | V19: =IF(AND(ISNUMBER(M19),ISNUMBER(L19)),IF(L19>0,M19/L19,"n.d."),"NI") -> 0.34956541 | W19: =IF(AND(ISNUMBER(R19),ISNUMBER(Q19)),IF(Q19>0,R19/Q19,"n.d."),"NI") -> 0.047315896 | X19: =IF(ISNUMBER(L19),IF(L19>100000000,"Grande","Média/Pequena"),"Sem dado") -> Grande | Y19: {=_xlfn.IFS(ISNUMBER(W19)=FALSE,"Sem dado",W19>0.075,"Excelente",W19>0.04,"Bom",W19>0,"Fraco",TRUE,"Prejuízo")} -> Bom
A20: BANCO CITIBANK S.A. | B20: 33479023 | C20: CITIBANK - PRUDENCIAL | D20: C0030403 | E20: C0080192 | F20: b1 | G20: 3 | H20: 8 | I20: SAO PAULO | J20: SP | K20: 06/2026 | L20: 169403341 | M20: 26037160 | N20: 46301711 | O20: 164218702 | P20: 145825012 | Q20: 5184639 | R20: 880369 | S20: 44 | T20: 8 | U20: =IFERROR(CHOOSE(G20,"Público","Privado Nacional","Privado Estrangeiro"),"n.d.") -> Privado Estrangeiro | V20: =IF(AND(ISNUMBER(M20),ISNUMBER(L20)),IF(L20>0,M20/L20,"n.d."),"NI") -> 0.15369921 | W20: =IF(AND(ISNUMBER(R20),ISNUMBER(Q20)),IF(Q20>0,R20/Q20,"n.d."),"NI") -> 0.16980334 | X20: =IF(ISNUMBER(L20),IF(L20>100000000,"Grande","Média/Pequena"),"Sem dado") -> Grande | Y20: {=_xlfn.IFS(ISNUMBER(W20)=FALSE,"Sem dado",W20>0.075,"Excelente",W20>0.04,"Bom",W20>0,"Fraco",TRUE,"Prejuízo")} -> Excelente
A21: BANCO VOTORANTIM S.A. | B21: 59588111 | C21: VOTORANTIM - PRUDENCIAL | D21: C0051011 | E21: C0080484 | F21: b1 | G21: 2 | H21: 8 | I21: SAO PAULO | J21: SP | K21: 06/2026 | L21: 147547552 | M21: 71981491 | N21: 32816913 | O21: 134575200 | P21: 111045483 | Q21: 12972352 | R21: 961452 | S21: 4 | T21: 3 | U21: =IFERROR(CHOOSE(G21,"Público","Privado Nacional","Privado Estrangeiro"),"n.d.") -> Privado Nacional | V21: =IF(AND(ISNUMBER(M21),ISNUMBER(L21)),IF(L21>0,M21/L21,"n.d."),"NI") -> 0.48785283 | W21: =IF(AND(ISNUMBER(R21),ISNUMBER(Q21)),IF(Q21>0,R21/Q21,"n.d."),"NI") -> 0.074115473 | X21: =IF(ISNUMBER(L21),IF(L21>100000000,"Grande","Média/Pequena"),"Sem dado") -> Grande | Y21: {=_xlfn.IFS(ISNUMBER(W21)=FALSE,"Sem dado",W21>0.075,"Excelente",W21>0.04,"Bom",W21>0,"Fraco",TRUE,"Prejuízo")} -> Bom
A22: XP INVESTIMENTOS CORRETORA DE CÂMBIO,TÍTULOS E VALORES MOBILIÁRIOS S/A | B22: 2332886 | C22: XP - PRUDENCIAL | D22: C0052120 | E22: C0082475 | F22: n2 | G22: 2 | H22: 15 | I22: RIO DE JANEIRO | J22: RJ | K22: 06/2026 | L22: 132450653 | M22: 147006 | N22: 39754591 | O22: 125124019 | P22: 91424497 | Q22: 7326634 | R22: -40139 | S22: 5 | T22: 0 | U22: =IFERROR(CHOOSE(G22,"Público","Privado Nacional","Privado Estrangeiro"),"n.d.") -> Privado Nacional | V22: =IF(AND(ISNUMBER(M22),ISNUMBER(L22)),IF(L22>0,M22/L22,"n.d."),"NI") -> 0.0011098926 | W22: =IF(AND(ISNUMBER(R22),ISNUMBER(Q22)),IF(Q22>0,R22/Q22,"n.d."),"NI") -> -0.0054785049 | X22: =IF(ISNUMBER(L22),IF(L22>100000000,"Grande","Média/Pequena"),"Sem dado") -> Grande | Y22: {=_xlfn.IFS(ISNUMBER(W22)=FALSE,"Sem dado",W22>0.075,"Excelente",W22>0.04,"Bom",W22>0,"Fraco",TRUE,"Prejuízo")} -> Prejuízo
A23: NU PAGAMENTOS S.A. - INSTITUIÇÃO DE PAGAMENTO | B23: 18236120 | C23: NU PAGAMENTOS - PRUDENCIAL | E23: C0084693 | F23: n4 | G23: 3 | H23: 41 | I23: SAO PAULO | J23: SP | K23: 06/2026 | L23: 122363230 | M23: 75801555 | N23: 684426 | O23: 99117282 | P23: 3084398 | Q23: 23245948 | R23: 4093013 | S23: 1 | T23: 0 | U23: =IFERROR(CHOOSE(G23,"Público","Privado Nacional","Privado Estrangeiro"),"n.d.") -> Privado Estrangeiro | V23: =IF(AND(ISNUMBER(M23),ISNUMBER(L23)),IF(L23>0,M23/L23,"n.d."),"NI") -> 0.61947985 | W23: =IF(AND(ISNUMBER(R23),ISNUMBER(Q23)),IF(Q23>0,R23/Q23,"n.d."),"NI") -> 0.17607426 | X23: =IF(ISNUMBER(L23),IF(L23>100000000,"Grande","Média/Pequena"),"Sem dado") -> Grande | Y23: {=_xlfn.IFS(ISNUMBER(W23)=FALSE,"Sem dado",W23>0.075,"Excelente",W23>0.04,"Bom",W23>0,"Fraco",TRUE,"Prejuízo")} -> Excelente
A24: BANCO C6 S.A. | B24: 31872495 | C24: BANCO C6 - PRUDENCIAL | D24: C0052072 | E24: C0084844 | F24: b1 | G24: 2 | H24: 8 | I24: SAO PAULO | J24: SP | K24: 06/2026 | L24: 117193733 | M24: 52508241 | N24: 43492491 | O24: 114382052 | P24: 87601269 | Q24: 2811681 | R24: 662077 | S24: 2 | T24: 0 | U24: =IFERROR(CHOOSE(G24,"Público","Privado Nacional","Privado Estrangeiro"),"n.d.") -> Privado Nacional | V24: =IF(AND(ISNUMBER(M24),ISNUMBER(L24)),IF(L24>0,M24/L24,"n.d."),"NI") -> 0.44804649 | W24: =IF(AND(ISNUMBER(R24),ISNUMBER(Q24)),IF(Q24>0,R24/Q24,"n.d."),"NI") -> 0.23547373 | X24: =IF(ISNUMBER(L24),IF(L24>100000000,"Grande","Média/Pequena"),"Sem dado") -> Grande | Y24: {=_xlfn.IFS(ISNUMBER(W24)=FALSE,"Sem dado",W24>0.075,"Excelente",W24>0.04,"Bom",W24>0,"Fraco",TRUE,"Prejuízo")} -> Excelente
A25: CIELO S.A. - INSTITUIÇÃO DE PAGAMENTO | B25: 1027058 | C25: CIELO IP - PRUDENCIAL | E25: C0084710 | F25: n4 | G25: 2 | H25: 41 | I25: BARUERI | J25: SP | K25: 06/2026 | L25: 116680888 | M25: 0 | N25: 6134397 | O25: 105006218 | P25: 10367314 | Q25: 11674670 | R25: 566759 | S25: 1 | T25: 0 | U25: =IFERROR(CHOOSE(G25,"Público","Privado Nacional","Privado Estrangeiro"),"n.d.") -> Privado Nacional | V25: =IF(AND(ISNUMBER(M25),ISNUMBER(L25)),IF(L25>0,M25/L25,"n.d."),"NI") -> 0 | W25: =IF(AND(ISNUMBER(R25),ISNUMBER(Q25)),IF(Q25>0,R25/Q25,"n.d."),"NI") -> 0.04854604 | X25: =IF(ISNUMBER(L25),IF(L25>100000000,"Grande","Média/Pequena"),"Sem dado") -> Grande | Y25: {=_xlfn.IFS(ISNUMBER(W25)=FALSE,"Sem dado",W25>0.075,"Excelente",W25>0.04,"Bom",W25>0,"Fraco",TRUE,"Prejuízo")} -> Bom
A26: BANCO J.P. MORGAN S.A. | B26: 33172537 | C26: JP MORGAN CHASE - PRUDENCIAL | D26: C0020107 | E26: C0080116 | F26: b1 | G26: 3 | H26: 8 | I26: SAO PAULO | J26: SP | K26: 06/2026 | L26: 110025345 | M26: 3735715 | N26: 62256458 | O26: 98253022 | P26: 84833031 | Q26: 11772323 | R26: 1038284 | S26: 3 | T26: 0 | U26: =IFERROR(CHOOSE(G26,"Público","Privado Nacional","Privado Estrangeiro"),"n.d.") -> Privado Estrangeiro | V26: =IF(AND(ISNUMBER(M26),ISNUMBER(L26)),IF(L26>0,M26/L26,"n.d."),"NI") -> 0.033953222 | W26: =IF(AND(ISNUMBER(R26),ISNUMBER(Q26)),IF(Q26>0,R26/Q26,"n.d."),"NI") -> 0.088197036 | X26: =IF(ISNUMBER(L26),IF(L26>100000000,"Grande","Média/Pequena"),"Sem dado") -> Grande | Y26: {=_xlfn.IFS(ISNUMBER(W26)=FALSE,"Sem dado",W26>0.075,"Excelente",W26>0.04,"Bom",W26>0,"Fraco",TRUE,"Prejuízo")} -> Excelente
A27: MERCADO PAGO INSTITUIÇÃO DE PAGAMENTO LTDA. | B27: 10573521 | C27: MERCADO PAGO IP - PRUDENCIAL | E27: C0084820 | F27: n4 | G27: 3 | H27: 41 | I27: OSASCO | J27: SP | K27: 06/2026 | L27: 105731564 | M27: 22485259 | N27: 1505659 | O27: 102742356 | P27: 59815921 | Q27: 2989208 | R27: -189822 | S27: 1 | T27: 0 | U27: =IFERROR(CHOOSE(G27,"Público","Privado Nacional","Privado Estrangeiro"),"n.d.") -> Privado Estrangeiro | V27: =IF(AND(ISNUMBER(M27),ISNUMBER(L27)),IF(L27>0,M27/L27,"n.d."),"NI") -> 0.21266364 | W27: =IF(AND(ISNUMBER(R27),ISNUMBER(Q27)),IF(Q27>0,R27/Q27,"n.d."),"NI") -> -0.063502439 | X27: =IF(ISNUMBER(L27),IF(L27>100000000,"Grande","Média/Pequena"),"Sem dado") -> Grande | Y27: {=_xlfn.IFS(ISNUMBER(W27)=FALSE,"Sem dado",W27>0.075,"Excelente",W27>0.04,"Bom",W27>0,"Fraco",TRUE,"Prejuízo")} -> Prejuízo
A28: BANCO INTER S.A. | B28: 416968 | C28: INTER - PRUDENCIAL | D28: C0051884 | E28: C0080996 | F28: b1 | G28: 2 | H28: 8 | I28: BELO HORIZONTE | J28: MG | K28: 06/2026 | L28: 100898332 | M28: 46141022 | N28: 28722089 | O28: 93446498 | P28: 77773587 | Q28: 7451834 | R28: 712041 | S28: 2 | T28: 0 | U28: =IFERROR(CHOOSE(G28,"Público","Privado Nacional","Privado Estrangeiro"),"n.d.") -> Privado Nacional | V28: =IF(AND(ISNUMBER(M28),ISNUMBER(L28)),IF(L28>0,M28/L28,"n.d."),"NI") -> 0.45730213 | W28: =IF(AND(ISNUMBER(R28),ISNUMBER(Q28)),IF(Q28>0,R28/Q28,"n.d."),"NI") -> 0.095552451 | X28: =IF(ISNUMBER(L28),IF(L28>100000000,"Grande","Média/Pequena"),"Sem dado") -> Grande | Y28: {=_xlfn.IFS(ISNUMBER(W28)=FALSE,"Sem dado",W28>0.075,"Excelente",W28>0.04,"Bom",W28>0,"Fraco",TRUE,"Prejuízo")} -> Excelente
A29: BANCO DAYCOVAL S.A. | B29: 62232889 | C29: BCO DAYCOVAL S.A - PRUDENCIAL | D29: C0051987 | E29: C0081744 | F29: b1 | G29: 2 | H29: 8 | I29: SAO PAULO | J29: SP | K29: 06/2026 | L29: 99778656 | M29: 53810851 | N29: 24713706 | O29: 92122935 | P29: 82698919 | Q29: 7655721 | R29: 901621 | S29: 53 | T29: 0 | U29: =IFERROR(CHOOSE(G29,"Público","Privado Nacional","Privado Estrangeiro"),"n.d.") -> Privado Nacional | V29: =IF(AND(ISNUMBER(M29),ISNUMBER(L29)),IF(L29>0,M29/L29,"n.d."),"NI") -> 0.53930222 | W29: =IF(AND(ISNUMBER(R29),ISNUMBER(Q29)),IF(Q29>0,R29/Q29,"n.d."),"NI") -> 0.11777088 | X29: =IF(ISNUMBER(L29),IF(L29>100000000,"Grande","Média/Pequena"),"Sem dado") -> Média/Pequena | Y29: {=_xlfn.IFS(ISNUMBER(W29)=FALSE,"Sem dado",W29>0.075,"Excelente",W29>0.04,"Bom",W29>0,"Fraco",TRUE,"Prejuízo")} -> Excelente
A30: SANTANDER SOCIEDADE DE CRÉDITO, FINANCIAMENTO E INVESTIMENTO S.A. | B30: 7707650 | C30: SANTANDER - PRUDENCIAL | D30: C0030379 | E30: C0080185 | F30: n1 | G30: 3 | H30: 14 | I30: SAO PAULO | J30: SP | K30: 06/2026 | L30: 94908733 | M30: 78916545 | N30: 8626164 | O30: 90101084 | P30: 84719722 | Q30: 4807649 | R30: 361088 | S30: 1 | T30: 0 | U30: =IFERROR(CHOOSE(G30,"Público","Privado Nacional","Privado Estrangeiro"),"n.d.") -> Privado Estrangeiro | V30: =IF(AND(ISNUMBER(M30),ISNUMBER(L30)),IF(L30>0,M30/L30,"n.d."),"NI") -> 0.8314993 | W30: =IF(AND(ISNUMBER(R30),ISNUMBER(Q30)),IF(Q30>0,R30/Q30,"n.d."),"NI") -> 0.075106981 | X30: =IF(ISNUMBER(L30),IF(L30>100000000,"Grande","Média/Pequena"),"Sem dado") -> Média/Pequena | Y30: {=_xlfn.IFS(ISNUMBER(W30)=FALSE,"Sem dado",W30>0.075,"Excelente",W30>0.04,"Bom",W30>0,"Fraco",TRUE,"Prejuízo")} -> Excelente
A31: STONE INSTITUIÇÃO DE PAGAMENTO S.A. | B31: 16501555 | C31: STONE IP - PRUDENCIAL | E31: C0084686 | F31: n4 | G31: 3 | H31: 41 | I31: SAO PAULO | J31: SP | K31: 06/2026 | L31: 89229885 | M31: 0 | N31: 33856104 | O31: 86020632 | P31: 35329072 | Q31: 3209254 | R31: 867035 | S31: 1 | T31: 0 | U31: =IFERROR(CHOOSE(G31,"Público","Privado Nacional","Privado Estrangeiro"),"n.d.") -> Privado Estrangeiro | V31: =IF(AND(ISNUMBER(M31),ISNUMBER(L31)),IF(L31>0,M31/L31,"n.d."),"NI") -> 0 | W31: =IF(AND(ISNUMBER(R31),ISNUMBER(Q31)),IF(Q31>0,R31/Q31,"n.d."),"NI") -> 0.27016715 | X31: =IF(ISNUMBER(L31),IF(L31>100000000,"Grande","Média/Pequena"),"Sem dado") -> Média/Pequena | Y31: {=_xlfn.IFS(ISNUMBER(W31)=FALSE,"Sem dado",W31>0.075,"Excelente",W31>0.04,"Bom",W31>0,"Fraco",TRUE,"Prejuízo")} -> Excelente
A32: BANCO DO NORDESTE DO BRASIL S.A. | B32: 7237373 | C32: BCO DO NORDESTE DO BRASIL S.A. - PRUDENCIAL | E32: C0081593 | F32: b1 | G32: 1 | H32: 8 | I32: FORTALEZA | J32: CE | K32: 06/2026 | L32: 81039783 | M32: 17779920 | N32: 44768452 | O32: 64226772 | P32: 23269171 | Q32: 16813010 | R32: 1057412 | S32: 301 | T32: 1 | U32: =IFERROR(CHOOSE(G32,"Público","Privado Nacional","Privado Estrangeiro"),"n.d.") -> Público | V32: =IF(AND(ISNUMBER(M32),ISNUMBER(L32)),IF(L32>0,M32/L32,"n.d."),"NI") -> 0.21939743 | W32: =IF(AND(ISNUMBER(R32),ISNUMBER(Q32)),IF(Q32>0,R32/Q32,"n.d."),"NI") -> 0.062892486 | X32: =IF(ISNUMBER(L32),IF(L32>100000000,"Grande","Média/Pequena"),"Sem dado") -> Média/Pequena | Y32: {=_xlfn.IFS(ISNUMBER(W32)=FALSE,"Sem dado",W32>0.075,"Excelente",W32>0.04,"Bom",W32>0,"Fraco",TRUE,"Prejuízo")} -> Bom
A33: BANCO PAN S.A. | B33: 59285411 | C33: BTG PACTUAL - PRUDENCIAL | D33: C0049944 | E33: C0080336 | F33: b1 | G33: 2 | H33: 8 | I33: RIO DE JANEIRO | J33: RJ | K33: 06/2026 | L33: 77255474 | M33: 35566859 | N33: 24319234 | O33: 68495128 | P33: 64315922 | Q33: 8760346 | R33: 689725 | S33: 2 | T33: 0 | U33: =IFERROR(CHOOSE(G33,"Público","Privado Nacional","Privado Estrangeiro"),"n.d.") -> Privado Nacional | V33: =IF(AND(ISNUMBER(M33),ISNUMBER(L33)),IF(L33>0,M33/L33,"n.d."),"NI") -> 0.46037979 | W33: =IF(AND(ISNUMBER(R33),ISNUMBER(Q33)),IF(Q33>0,R33/Q33,"n.d."),"NI") -> 0.078732621 | X33: =IF(ISNUMBER(L33),IF(L33>100000000,"Grande","Média/Pequena"),"Sem dado") -> Média/Pequena | Y33: {=_xlfn.IFS(ISNUMBER(W33)=FALSE,"Sem dado",W33>0.075,"Excelente",W33>0.04,"Bom",W33>0,"Fraco",TRUE,"Prejuízo")} -> Excelente
A34: GETNET ADQUIRÊNCIA E SERVIÇOS PARA MEIOS DE PAGAMENTO S.A. INSTITUIÇÃO DE PAGAMENTO | B34: 10440482 | C34: SANTANDER - PRUDENCIAL | E34: C0080185 | F34: n4 | G34: 3 | H34: 41 | I34: SAO PAULO | J34: SP | K34: 06/2026 | L34: 74198667 | M34: 0 | N34: 471650 | O34: 70373351 | P34: 457227 | Q34: 3825316 | R34: 529101 | S34: 1 | T34: 0 | U34: =IFERROR(CHOOSE(G34,"Público","Privado Nacional","Privado Estrangeiro"),"n.d.") -> Privado Estrangeiro | V34: =IF(AND(ISNUMBER(M34),ISNUMBER(L34)),IF(L34>0,M34/L34,"n.d."),"NI") -> 0 | W34: =IF(AND(ISNUMBER(R34),ISNUMBER(Q34)),IF(Q34>0,R34/Q34,"n.d."),"NI") -> 0.13831563 | X34: =IF(ISNUMBER(L34),IF(L34>100000000,"Grande","Média/Pequena"),"Sem dado") -> Média/Pequena | Y34: {=_xlfn.IFS(ISNUMBER(W34)=FALSE,"Sem dado",W34>0.075,"Excelente",W34>0.04,"Bom",W34>0,"Fraco",TRUE,"Prejuízo")} -> Excelente
A35: PAGSEGURO INTERNET INSTITUIÇÃO DE PAGAMENTO S.A. | B35: 8561701 | C35: PAGSEGURO - PRUDENCIAL | E35: C0084813 | F35: n4 | G35: 2 | H35: 41 | I35: SAO PAULO | J35: SP | K35: 06/2026 | L35: 73530147 | M35: 746551 | N35: 5259611 | O35: 67499312 | P35: 46766864 | Q35: 6030835 | R35: 463519 | S35: 1 | T35: 0 | U35: =IFERROR(CHOOSE(G35,"Público","Privado Nacional","Privado Estrangeiro"),"n.d.") -> Privado Nacional | V35: =IF(AND(ISNUMBER(M35),ISNUMBER(L35)),IF(L35>0,M35/L35,"n.d."),"NI") -> 0.010152992 | W35: =IF(AND(ISNUMBER(R35),ISNUMBER(Q35)),IF(Q35>0,R35/Q35,"n.d."),"NI") -> 0.07685818 | X35: =IF(ISNUMBER(L35),IF(L35>100000000,"Grande","Média/Pequena"),"Sem dado") -> Média/Pequena | Y35: {=_xlfn.IFS(ISNUMBER(W35)=FALSE,"Sem dado",W35>0.075,"Excelente",W35>0.04,"Bom",W35>0,"Fraco",TRUE,"Prejuízo")} -> Excelente
A36: BANCO BRADESCO FINANCIAMENTOS S.A. | B36: 7207996 | C36: BRADESCO - PRUDENCIAL | D36: C0010045 | E36: C0080075 | F36: b1 | G36: 2 | H36: 8 | I36: OSASCO | J36: SP | K36: 06/2026 | L36: 68748096 | M36: 52483412 | N36: 60748 | O36: 68114489 | P36: 65248099 | Q36: 633608 | R36: 12331 | S36: 2 | T36: 5 | U36: =IFERROR(CHOOSE(G36,"Público","Privado Nacional","Privado Estrangeiro"),"n.d.") -> Privado Nacional | V36: =IF(AND(ISNUMBER(M36),ISNUMBER(L36)),IF(L36>0,M36/L36,"n.d."),"NI") -> 0.76341623 | W36: =IF(AND(ISNUMBER(R36),ISNUMBER(Q36)),IF(Q36>0,R36/Q36,"n.d."),"NI") -> 0.01946156 | X36: =IF(ISNUMBER(L36),IF(L36>100000000,"Grande","Média/Pequena"),"Sem dado") -> Média/Pequena | Y36: {=_xlfn.IFS(ISNUMBER(W36)=FALSE,"Sem dado",W36>0.075,"Excelente",W36>0.04,"Bom",W36>0,"Fraco",TRUE,"Prejuízo")} -> Fraco
A37: BANCO DA AMAZONIA S.A. | B37: 4902979 | C37: BCO DA AMAZONIA S.A. - PRUDENCIAL | E37: C0081249 | F37: b1 | G37: 1 | H37: 2 | I37: BELEM | J37: PA | K37: 06/2026 | L37: 67352881 | M37: 38713829 | N37: 21699434 | O37: 60078810 | P37: 15601132 | Q37: 7274071 | R37: 353060 | S37: 115 | T37: 0 | U37: =IFERROR(CHOOSE(G37,"Público","Privado Nacional","Privado Estrangeiro"),"n.d.") -> Público | V37: =IF(AND(ISNUMBER(M37),ISNUMBER(L37)),IF(L37>0,M37/L37,"n.d."),"NI") -> 0.57479099 | W37: =IF(AND(ISNUMBER(R37),ISNUMBER(Q37)),IF(Q37>0,R37/Q37,"n.d."),"NI") -> 0.048536782 | X37: =IF(ISNUMBER(L37),IF(L37>100000000,"Grande","Média/Pequena"),"Sem dado") -> Média/Pequena | Y37: {=_xlfn.IFS(ISNUMBER(W37)=FALSE,"Sem dado",W37>0.075,"Excelente",W37>0.04,"Bom",W37>0,"Fraco",TRUE,"Prejuízo")} -> Bom
A38: BANCO ABC BRASIL S.A. | B38: 28195667 | C38: ABC-BRASIL - PRUDENCIAL | D38: C0041856 | E38: C0080312 | F38: b1 | G38: 3 | H38: 8 | I38: SAO PAULO | J38: SP | K38: 06/2026 | L38: 66147427 | M38: 18520743 | N38: 29173812 | O38: 58888511 | P38: 50226679 | Q38: 7258915 | R38: 487535 | S38: 13 | T38: 0 | U38: =IFERROR(CHOOSE(G38,"Público","Privado Nacional","Privado Estrangeiro"),"n.d.") -> Privado Estrangeiro | V38: =IF(AND(ISNUMBER(M38),ISNUMBER(L38)),IF(L38>0,M38/L38,"n.d."),"NI") -> 0.27999189 | W38: =IF(AND(ISNUMBER(R38),ISNUMBER(Q38)),IF(Q38>0,R38/Q38,"n.d."),"NI") -> 0.067163619 | X38: =IF(ISNUMBER(L38),IF(L38>100000000,"Grande","Média/Pequena"),"Sem dado") -> Média/Pequena | Y38: {=_xlfn.IFS(ISNUMBER(W38)=FALSE,"Sem dado",W38>0.075,"Excelente",W38>0.04,"Bom",W38>0,"Fraco",TRUE,"Prejuízo")} -> Bom
A39: BANCO VOLKSWAGEN S.A. | B39: 59109165 | C39: VOLKSWAGEN - PRUDENCIAL | E39: C0080202 | F39: b2 | G39: 3 | H39: 8 | I39: SAO PAULO | J39: SP | K39: 06/2026 | L39: 61250495 | M39: 50345582 | N39: 819927 | O39: 55986251 | P39: 47916041 | Q39: 5264244 | R39: -203091 | S39: 2 | T39: 0 | U39: =IFERROR(CHOOSE(G39,"Público","Privado Nacional","Privado Estrangeiro"),"n.d.") -> Privado Estrangeiro | V39: =IF(AND(ISNUMBER(M39),ISNUMBER(L39)),IF(L39>0,M39/L39,"n.d."),"NI") -> 0.82196204 | W39: =IF(AND(ISNUMBER(R39),ISNUMBER(Q39)),IF(Q39>0,R39/Q39,"n.d."),"NI") -> -0.038579329 | X39: =IF(ISNUMBER(L39),IF(L39>100000000,"Grande","Média/Pequena"),"Sem dado") -> Média/Pequena | Y39: {=_xlfn.IFS(ISNUMBER(W39)=FALSE,"Sem dado",W39>0.075,"Excelente",W39>0.04,"Bom",W39>0,"Fraco",TRUE,"Prejuízo")} -> Prejuízo
A40: BANCO BNP PARIBAS BRASIL S.A. | B40: 1522368 | C40: BNP PARIBAS - PRUDENCIAL | E40: C0080673 | F40: b1 | G40: 3 | H40: 8 | I40: SAO PAULO | J40: SP | K40: 06/2026 | L40: 58787929 | M40: 6716037 | N40: 21646070 | O40: 54077310 | P40: 34516225 | Q40: 4710619 | R40: 86546 | S40: 2 | T40: 0 | U40: =IFERROR(CHOOSE(G40,"Público","Privado Nacional","Privado Estrangeiro"),"n.d.") -> Privado Estrangeiro | V40: =IF(AND(ISNUMBER(M40),ISNUMBER(L40)),IF(L40>0,M40/L40,"n.d."),"NI") -> 0.11424177 | W40: =IF(AND(ISNUMBER(R40),ISNUMBER(Q40)),IF(Q40>0,R40/Q40,"n.d."),"NI") -> 0.018372532 | X40: =IF(ISNUMBER(L40),IF(L40>100000000,"Grande","Média/Pequena"),"Sem dado") -> Média/Pequena | Y40: {=_xlfn.IFS(ISNUMBER(W40)=FALSE,"Sem dado",W40>0.075,"Excelente",W40>0.04,"Bom",W40>0,"Fraco",TRUE,"Prejuízo")} -> Fraco
A41: BANCO C6 CONSIGNADO S.A. | B41: 61348538 | C41: BANCO C6 - PRUDENCIAL | D41: C0052072 | E41: C0084844 | F41: b1 | G41: 2 | H41: 8 | I41: SAO PAULO | J41: SP | K41: 06/2026 | L41: 56164263 | M41: 42537256 | N41: 7432727 | O41: 52511688 | P41: 39443515 | Q41: 3652575 | R41: 559375 | S41: 2 | T41: 0 | U41: =IFERROR(CHOOSE(G41,"Público","Privado Nacional","Privado Estrangeiro"),"n.d.") -> Privado Nacional | V41: =IF(AND(ISNUMBER(M41),ISNUMBER(L41)),IF(L41>0,M41/L41,"n.d."),"NI") -> 0.75737228 | W41: =IF(AND(ISNUMBER(R41),ISNUMBER(Q41)),IF(Q41>0,R41/Q41,"n.d."),"NI") -> 0.15314538 | X41: =IF(ISNUMBER(L41),IF(L41>100000000,"Grande","Média/Pequena"),"Sem dado") -> Média/Pequena | Y41: {=_xlfn.IFS(ISNUMBER(W41)=FALSE,"Sem dado",W41>0.075,"Excelente",W41>0.04,"Bom",W41>0,"Fraco",TRUE,"Prejuízo")} -> Excelente
A42: BANCO RABOBANK INTERNATIONAL BRASIL S.A. | B42: 1023570 | C42: BCO RABOBANK INTL BRASIL S.A. - PRUDENCIAL | E42: C0081555 | F42: b1 | G42: 3 | H42: 8 | I42: SAO PAULO | J42: SP | K42: 06/2026 | L42: 54678970 | M42: 37932273 | N42: 7485572 | O42: 48983962 | P42: 44719472 | Q42: 5695008 | R42: 270816 | S42: 19 | T42: 0 | U42: =IFERROR(CHOOSE(G42,"Público","Privado Nacional","Privado Estrangeiro"),"n.d.") -> Privado Estrangeiro | V42: =IF(AND(ISNUMBER(M42),ISNUMBER(L42)),IF(L42>0,M42/L42,"n.d."),"NI") -> 0.69372691 | W42: =IF(AND(ISNUMBER(R42),ISNUMBER(Q42)),IF(Q42>0,R42/Q42,"n.d."),"NI") -> 0.047553226 | X42: =IF(ISNUMBER(L42),IF(L42>100000000,"Grande","Média/Pequena"),"Sem dado") -> Média/Pequena | Y42: {=_xlfn.IFS(ISNUMBER(W42)=FALSE,"Sem dado",W42>0.075,"Excelente",W42>0.04,"Bom",W42>0,"Fraco",TRUE,"Prejuízo")} -> Bom
A43: BANCOSEGURO S.A. | B43: 10264663 | C43: PAGSEGURO - PRUDENCIAL | D43: C0052182 | E43: C0084813 | F43: b1 | G43: 2 | H43: 8 | I43: SAO PAULO | J43: SP | K43: 06/2026 | L43: 52291197 | M43: 47649262 | N43: 355175 | O43: 50569304 | P43: 50254095 | Q43: 1721893 | R43: 66118 | S43: 2 | T43: 0 | U43: =IFERROR(CHOOSE(G43,"Público","Privado Nacional","Privado Estrangeiro"),"n.d.") -> Privado Nacional | V43: =IF(AND(ISNUMBER(M43),ISNUMBER(L43)),IF(L43>0,M43/L43,"n.d."),"NI") -> 0.91122913 | W43: =IF(AND(ISNUMBER(R43),ISNUMBER(Q43)),IF(Q43>0,R43/Q43,"n.d."),"NI") -> 0.038398437 | X43: =IF(ISNUMBER(L43),IF(L43>100000000,"Grande","Média/Pequena"),"Sem dado") -> Média/Pequena | Y43: {=_xlfn.IFS(ISNUMBER(W43)=FALSE,"Sem dado",W43>0.075,"Excelente",W43>0.04,"Bom",W43>0,"Fraco",TRUE,"Prejuízo")} -> Fraco
A44: BANCO AGIBANK S.A. | B44: 10664513 | C44: AGIBANK - PRUDENCIAL | D44: C0051956 | E44: C0083694 | F44: b1 | G44: 3 | H44: 2 | I44: CAMPINAS | J44: SP | K44: 06/2026 | L44: 51241770 | M44: 34675580 | N44: 10607480 | O44: 47809811 | P44: 31576717 | Q44: 3431960 | R44: 167735 | S44: 2 | T44: 340 | U44: =IFERROR(CHOOSE(G44,"Público","Privado Nacional","Privado Estrangeiro"),"n.d.") -> Privado Estrangeiro | V44: =IF(AND(ISNUMBER(M44),ISNUMBER(L44)),IF(L44>0,M44/L44,"n.d."),"NI") -> 0.67670535 | W44: =IF(AND(ISNUMBER(R44),ISNUMBER(Q44)),IF(Q44>0,R44/Q44,"n.d."),"NI") -> 0.048874404 | X44: =IF(ISNUMBER(L44),IF(L44>100000000,"Grande","Média/Pequena"),"Sem dado") -> Média/Pequena | Y44: {=_xlfn.IFS(ISNUMBER(W44)=FALSE,"Sem dado",W44>0.075,"Excelente",W44>0.04,"Bom",W44>0,"Fraco",TRUE,"Prejuízo")} -> Bom
A45: BANCO BMG S.A. | B45: 61186680 | C45: BMG - PRUDENCIAL | D45: C0030290 | E45: C0080178 | F45: b1 | G45: 2 | H45: 8 | I45: SAO PAULO | J45: SP | K45: 06/2026 | L45: 50846808 | M45: 21352794 | N45: 13897187 | O45: 46527758 | P45: 37011430 | Q45: 4319050 | R45: 304550 | S45: 27 | T45: 2 | U45: =IFERROR(CHOOSE(G45,"Público","Privado Nacional","Privado Estrangeiro"),"n.d.") -> Privado Nacional | V45: =IF(AND(ISNUMBER(M45),ISNUMBER(L45)),IF(L45>0,M45/L45,"n.d."),"NI") -> 0.41994365 | W45: =IF(AND(ISNUMBER(R45),ISNUMBER(Q45)),IF(Q45>0,R45/Q45,"n.d."),"NI") -> 0.070513192 | X45: =IF(ISNUMBER(L45),IF(L45>100000000,"Grande","Média/Pequena"),"Sem dado") -> Média/Pequena | Y45: {=_xlfn.IFS(ISNUMBER(W45)=FALSE,"Sem dado",W45>0.075,"Excelente",W45>0.04,"Bom",W45>0,"Fraco",TRUE,"Prejuízo")} -> Bom
A46: PICPAY BANK - BANCO MÚLTIPLO S.A | B46: 9516419 | C46: PICPAY - PRUDENCIAL | D46: C0052632 | E46: C0088022 | F46: b1 | G46: 2 | H46: 8 | I46: SAO PAULO | J46: SP | K46: 06/2026 | L46: 48954093 | M46: 28852169 | N46: 10196292 | O46: 46414805 | P46: 34871092 | Q46: 2539288 | R46: 8433 | S46: 2 | T46: 0 | U46: =IFERROR(CHOOSE(G46,"Público","Privado Nacional","Privado Estrangeiro"),"n.d.") -> Privado Nacional | V46: =IF(AND(ISNUMBER(M46),ISNUMBER(L46)),IF(L46>0,M46/L46,"n.d."),"NI") -> 0.58937194 | W46: =IF(AND(ISNUMBER(R46),ISNUMBER(Q46)),IF(Q46>0,R46/Q46,"n.d."),"NI") -> 0.0033210097 | X46: =IF(ISNUMBER(L46),IF(L46>100000000,"Grande","Média/Pequena"),"Sem dado") -> Média/Pequena | Y46: {=_xlfn.IFS(ISNUMBER(W46)=FALSE,"Sem dado",W46>0.075,"Excelente",W46>0.04,"Bom",W46>0,"Fraco",TRUE,"Prejuízo")} -> Fraco
A47: BANCO MERCANTIL DO BRASIL S.A. | B47: 17184037 | C47: MERCANTIL DO BRASIL - PRUDENCIAL | D47: C0020152 | E47: C0080123 | F47: b1 | G47: 2 | H47: 8 | I47: BELO HORIZONTE | J47: MG | K47: 06/2026 | L47: 43054391 | M47: 23085077 | N47: 4252511 | O47: 39931439 | P47: 31586492 | Q47: 3122951 | R47: 548541 | S47: 3 | T47: 298 | U47: =IFERROR(CHOOSE(G47,"Público","Privado Nacional","Privado Estrangeiro"),"n.d.") -> Privado Nacional | V47: =IF(AND(ISNUMBER(M47),ISNUMBER(L47)),IF(L47>0,M47/L47,"n.d."),"NI") -> 0.53618403 | W47: =IF(AND(ISNUMBER(R47),ISNUMBER(Q47)),IF(Q47>0,R47/Q47,"n.d."),"NI") -> 0.17564829 | X47: =IF(ISNUMBER(L47),IF(L47>100000000,"Grande","Média/Pequena"),"Sem dado") -> Média/Pequena | Y47: {=_xlfn.IFS(ISNUMBER(W47)=FALSE,"Sem dado",W47>0.075,"Excelente",W47>0.04,"Bom",W47>0,"Fraco",TRUE,"Prejuízo")} -> Excelente
A48: BANESTES S.A. BANCO DO ESTADO DO ESPIRITO SANTO | B48: 28127603 | C48: BANESTES - PRUDENCIAL | D48: C0030159 | E48: C0080147 | F48: b1 | G48: 1 | H48: 8 | I48: VITORIA | J48: ES | K48: 06/2026 | L48: 42689901 | M48: 12460035 | N48: 21316783 | O48: 40185159 | P48: 38716345 | Q48: 2504742 | R48: 226057 | S48: 86 | T48: 63 | U48: =IFERROR(CHOOSE(G48,"Público","Privado Nacional","Privado Estrangeiro"),"n.d.") -> Público | V48: =IF(AND(ISNUMBER(M48),ISNUMBER(L48)),IF(L48>0,M48/L48,"n.d."),"NI") -> 0.29187313 | W48: =IF(AND(ISNUMBER(R48),ISNUMBER(Q48)),IF(Q48>0,R48/Q48,"n.d."),"NI") -> 0.090251611 | X48: =IF(ISNUMBER(L48),IF(L48>100000000,"Grande","Média/Pequena"),"Sem dado") -> Média/Pequena | Y48: {=_xlfn.IFS(ISNUMBER(W48)=FALSE,"Sem dado",W48>0.075,"Excelente",W48>0.04,"Bom",W48>0,"Fraco",TRUE,"Prejuízo")} -> Excelente
A49: BANCO CLASSICO S.A. | B49: 31597552 | C49: BCO CLASSICO S.A. - PRUDENCIAL | E49: C0081665 | F49: b1 | G49: 2 | H49: 8 | I49: RIO DE JANEIRO | J49: RJ | K49: 06/2026 | L49: 40612776 | M49: 0 | N49: 34521002 | O49: 19060286 | P49: 5629524 | Q49: 21552491 | R49: 52934 | S49: 2 | T49: 0 | U49: =IFERROR(CHOOSE(G49,"Público","Privado Nacional","Privado Estrangeiro"),"n.d.") -> Privado Nacional | V49: =IF(AND(ISNUMBER(M49),ISNUMBER(L49)),IF(L49>0,M49/L49,"n.d."),"NI") -> 0 | W49: =IF(AND(ISNUMBER(R49),ISNUMBER(Q49)),IF(Q49>0,R49/Q49,"n.d."),"NI") -> 0.0024560502 | X49: =IF(ISNUMBER(L49),IF(L49>100000000,"Grande","Média/Pequena"),"Sem dado") -> Média/Pequena | Y49: {=_xlfn.IFS(ISNUMBER(W49)=FALSE,"Sem dado",W49>0.075,"Excelente",W49>0.04,"Bom",W49>0,"Fraco",TRUE,"Prejuízo")} -> Fraco
A50: BANK OF AMERICA MERRILL LYNCH BANCO MÚLTIPLO S.A. | B50: 62073200 | C50: BOFA MERRILL LYNCH - PRUDENCIAL | D50: C0051255 | E50: C0080556 | F50: b1 | G50: 3 | H50: 8 | I50: SAO PAULO | J50: SP | K50: 06/2026 | L50: 40609859 | M50: 2646247 | N50: 13444360 | O50: 33810603 | P50: 22340451 | Q50: 6799255 | R50: 511110 | S50: 2 | T50: 0 | U50: =IFERROR(CHOOSE(G50,"Público","Privado Nacional","Privado Estrangeiro"),"n.d.") -> Privado Estrangeiro | V50: =IF(AND(ISNUMBER(M50),ISNUMBER(L50)),IF(L50>0,M50/L50,"n.d."),"NI") -> 0.065162674 | W50: =IF(AND(ISNUMBER(R50),ISNUMBER(Q50)),IF(Q50>0,R50/Q50,"n.d."),"NI") -> 0.075171471 | X50: =IF(ISNUMBER(L50),IF(L50>100000000,"Grande","Média/Pequena"),"Sem dado") -> Média/Pequena | Y50: {=_xlfn.IFS(ISNUMBER(W50)=FALSE,"Sem dado",W50>0.075,"Excelente",W50>0.04,"Bom",W50>0,"Fraco",TRUE,"Prejuízo")} -> Excelente
A51: BANCO PINE S.A. | B51: 62144175 | C51: PINE - PRUDENCIAL | D51: C0050304 | E51: C0080374 | F51: b1 | G51: 2 | H51: 8 | I51: SAO PAULO | J51: SP | K51: 06/2026 | L51: 37647108 | M51: 19314789 | N51: 13824794 | O51: 35844473 | P51: 31432120 | Q51: 1802635 | R51: 315564 | S51: 3 | T51: 0 | U51: =IFERROR(CHOOSE(G51,"Público","Privado Nacional","Privado Estrangeiro"),"n.d.") -> Privado Nacional | V51: =IF(AND(ISNUMBER(M51),ISNUMBER(L51)),IF(L51>0,M51/L51,"n.d."),"NI") -> 0.51304841 | W51: =IF(AND(ISNUMBER(R51),ISNUMBER(Q51)),IF(Q51>0,R51/Q51,"n.d."),"NI") -> 0.17505707 | X51: =IF(ISNUMBER(L51),IF(L51>100000000,"Grande","Média/Pequena"),"Sem dado") -> Média/Pequena | Y51: {=_xlfn.IFS(ISNUMBER(W51)=FALSE,"Sem dado",W51>0.075,"Excelente",W51>0.04,"Bom",W51>0,"Fraco",TRUE,"Prejuízo")} -> Excelente
A52: BANCO ORIGINAL S.A. | B52: 92894922 | C52: ORIGINAL - PRUDENCIAL | E52: C0080903 | F52: b1 | G52: 2 | H52: 8 | I52: SAO PAULO | J52: SP | K52: 06/2026 | L52: 37169761 | M52: 17893178 | N52: 6467856 | O52: 34845614 | P52: 32608252 | Q52: 2324147 | R52: 156076 | S52: 2 | T52: 0 | U52: =IFERROR(CHOOSE(G52,"Público","Privado Nacional","Privado Estrangeiro"),"n.d.") -> Privado Nacional | V52: =IF(AND(ISNUMBER(M52),ISNUMBER(L52)),IF(L52>0,M52/L52,"n.d."),"NI") -> 0.48139072 | W52: =IF(AND(ISNUMBER(R52),ISNUMBER(Q52)),IF(Q52>0,R52/Q52,"n.d."),"NI") -> 0.0671541 | X52: =IF(ISNUMBER(L52),IF(L52>100000000,"Grande","Média/Pequena"),"Sem dado") -> Média/Pequena | Y52: {=_xlfn.IFS(ISNUMBER(W52)=FALSE,"Sem dado",W52>0.075,"Excelente",W52>0.04,"Bom",W52>0,"Fraco",TRUE,"Prejuízo")} -> Bom
A53: COOPERATIVA CENTRAL DE CRÉDITO DE MINAS GERAIS LTDA. - SICOOB CENTRAL CREDIMINAS | B53: 25683434 | F53: b3C | G53: 2 | H53: 9 | I53: BELO HORIZONTE | J53: MG | K53: 06/2026 | L53: 34542515 | M53: 93624 | N53: 16768612 | O53: 32723827 | P53: 884328 | Q53: 1818687 | R53: 118531 | S53: 0 | T53: 0 | U53: =IFERROR(CHOOSE(G53,"Público","Privado Nacional","Privado Estrangeiro"),"n.d.") -> Privado Nacional | V53: =IF(AND(ISNUMBER(M53),ISNUMBER(L53)),IF(L53>0,M53/L53,"n.d."),"NI") -> 0.0027103991 | W53: =IF(AND(ISNUMBER(R53),ISNUMBER(Q53)),IF(Q53>0,R53/Q53,"n.d."),"NI") -> 0.065173941 | X53: =IF(ISNUMBER(L53),IF(L53>100000000,"Grande","Média/Pequena"),"Sem dado") -> Média/Pequena | Y53: {=_xlfn.IFS(ISNUMBER(W53)=FALSE,"Sem dado",W53>0.075,"Excelente",W53>0.04,"Bom",W53>0,"Fraco",TRUE,"Prejuízo")} -> Bom
A54: GOLDMAN SACHS DO BRASIL BANCO MULTIPLO S.A. | B54: 4332281 | C54: GOLDMAN SACHS - PRUDENCIAL | D54: C0051585 | E54: C0080714 | F54: b2 | G54: 3 | H54: 8 | I54: SAO PAULO | J54: SP | K54: 06/2026 | L54: 34267958 | M54: 5685 | N54: 20186889 | O54: 28404250 | P54: 14608413 | Q54: 5863708 | R54: 686226 | S54: 2 | T54: 0 | U54: =IFERROR(CHOOSE(G54,"Público","Privado Nacional","Privado Estrangeiro"),"n.d.") -> Privado Estrangeiro | V54: =IF(AND(ISNUMBER(M54),ISNUMBER(L54)),IF(L54>0,M54/L54,"n.d."),"NI") -> 0.00016589842 | W54: =IF(AND(ISNUMBER(R54),ISNUMBER(Q54)),IF(Q54>0,R54/Q54,"n.d."),"NI") -> 0.11702936 | X54: =IF(ISNUMBER(L54),IF(L54>100000000,"Grande","Média/Pequena"),"Sem dado") -> Média/Pequena | Y54: {=_xlfn.IFS(ISNUMBER(W54)=FALSE,"Sem dado",W54>0.075,"Excelente",W54>0.04,"Bom",W54>0,"Fraco",TRUE,"Prejuízo")} -> Excelente
A55: STONE SOCIEDADE DE CREDITO, FINANCIAMENTO E INVESTIMENTO S.A. | B55: 53505601 | C55: STONE IP - PRUDENCIAL | D55: C0084686 | E55: C0084686 | F55: n1 | G55: 3 | H55: 14 | I55: SAO PAULO | J55: SP | K55: 06/2026 | L55: 33803605 | M55: 30264738 | N55: 32559 | O55: 33678082 | P55: 33153032 | Q55: 125523 | R55: 46816 | S55: 2 | T55: 0 | U55: =IFERROR(CHOOSE(G55,"Público","Privado Nacional","Privado Estrangeiro"),"n.d.") -> Privado Estrangeiro | V55: =IF(AND(ISNUMBER(M55),ISNUMBER(L55)),IF(L55>0,M55/L55,"n.d."),"NI") -> 0.89531096 | W55: =IF(AND(ISNUMBER(R55),ISNUMBER(Q55)),IF(Q55>0,R55/Q55,"n.d."),"NI") -> 0.3729675 | X55: =IF(ISNUMBER(L55),IF(L55>100000000,"Grande","Média/Pequena"),"Sem dado") -> Média/Pequena | Y55: {=_xlfn.IFS(ISNUMBER(W55)=FALSE,"Sem dado",W55>0.075,"Excelente",W55>0.04,"Bom",W55>0,"Fraco",TRUE,"Prejuízo")} -> Excelente
A56: SAFRA SOCIEDADE DE CRÉDITO, FINANCIAMENTO E INVESTIMENTO S.A. | B56: 45437547 | C56: SAFRA - PRUDENCIAL | D56: C0010083 | E56: C0080109 | F56: n1 | G56: 2 | H56: 14 | I56: SAO PAULO | J56: SP | K56: 06/2026 | L56: 33188402 | M56: 21325158 | N56: 1657536 | O56: 32730969 | P56: 32013875 | Q56: 457433 | R56: 74616 | S56: 2 | T56: 0 | U56: =IFERROR(CHOOSE(G56,"Público","Privado Nacional","Privado Estrangeiro"),"n.d.") -> Privado Nacional | V56: =IF(AND(ISNUMBER(M56),ISNUMBER(L56)),IF(L56>0,M56/L56,"n.d."),"NI") -> 0.6425485 | W56: =IF(AND(ISNUMBER(R56),ISNUMBER(Q56)),IF(Q56>0,R56/Q56,"n.d."),"NI") -> 0.16311897 | X56: =IF(ISNUMBER(L56),IF(L56>100000000,"Grande","Média/Pequena"),"Sem dado") -> Média/Pequena | Y56: {=_xlfn.IFS(ISNUMBER(W56)=FALSE,"Sem dado",W56>0.075,"Excelente",W56>0.04,"Bom",W56>0,"Fraco",TRUE,"Prejuízo")} -> Excelente
A57: BANCO BOCOM BBM S.A. | B57: 15114366 | C57: BOCOM - PRUDENCIAL | D57: C0052003 | E57: C0084624 | F57: b1 | G57: 3 | H57: 8 | I57: SALVADOR | J57: BA | K57: 06/2026 | L57: 32001928 | M57: 14049138 | N57: 8031598 | O57: 30176603 | P57: 27817408 | Q57: 1825324 | R57: 257821 | S57: 4 | T57: 0 | U57: =IFERROR(CHOOSE(G57,"Público","Privado Nacional","Privado Estrangeiro"),"n.d.") -> Privado Estrangeiro | V57: =IF(AND(ISNUMBER(M57),ISNUMBER(L57)),IF(L57>0,M57/L57,"n.d."),"NI") -> 0.43900911 | W57: =IF(AND(ISNUMBER(R57),ISNUMBER(Q57)),IF(Q57>0,R57/Q57,"n.d."),"NI") -> 0.1412467 | X57: =IF(ISNUMBER(L57),IF(L57>100000000,"Grande","Média/Pequena"),"Sem dado") -> Média/Pequena | Y57: {=_xlfn.IFS(ISNUMBER(W57)=FALSE,"Sem dado",W57>0.075,"Excelente",W57>0.04,"Bom",W57>0,"Fraco",TRUE,"Prejuízo")} -> Excelente
A58: BANCO REGIONAL DE DESENVOLVIMENTO DO EXTREMO SUL | B58: 92816560 | C58: BD REGIONAL DO EXTREMO SUL - PRUDENCIAL | E58: C0081311 | F58: b4 | G58: 1 | H58: 5 | I58: PORTO ALEGRE | J58: RS | K58: 06/2026 | L58: 30944445 | M58: 24677869 | N58: 5511980 | O58: 25160827 | P58: 23606986 | Q58: 5783618 | R58: 315733 | S58: 4 | T58: 0 | U58: =IFERROR(CHOOSE(G58,"Público","Privado Nacional","Privado Estrangeiro"),"n.d.") -> Público | V58: =IF(AND(ISNUMBER(M58),ISNUMBER(L58)),IF(L58>0,M58/L58,"n.d."),"NI") -> 0.79748947 | W58: =IF(AND(ISNUMBER(R58),ISNUMBER(Q58)),IF(Q58>0,R58/Q58,"n.d."),"NI") -> 0.054590915 | X58: =IF(ISNUMBER(L58),IF(L58>100000000,"Grande","Média/Pequena"),"Sem dado") -> Média/Pequena | Y58: {=_xlfn.IFS(ISNUMBER(W58)=FALSE,"Sem dado",W58>0.075,"Excelente",W58>0.04,"Bom",W58>0,"Fraco",TRUE,"Prejuízo")} -> Bom
A59: COOPERATIVA CENTRAL DE CRÉDITO DE SANTA CATARINA E RIO GRANDE DO SUL - SICOOB CENTRAL SC/RS | B59: 80160260 | F59: b3C | G59: 2 | H59: 9 | I59: FLORIANOPOLIS | J59: SC | K59: 06/2026 | L59: 29002304 | M59: 302641 | N59: 5844789 | O59: 27464682 | P59: 681810 | Q59: 1537622 | R59: 73985 | S59: 0 | T59: 0 | U59: =IFERROR(CHOOSE(G59,"Público","Privado Nacional","Privado Estrangeiro"),"n.d.") -> Privado Nacional | V59: =IF(AND(ISNUMBER(M59),ISNUMBER(L59)),IF(L59>0,M59/L59,"n.d."),"NI") -> 0.010435068 | W59: =IF(AND(ISNUMBER(R59),ISNUMBER(Q59)),IF(Q59>0,R59/Q59,"n.d."),"NI") -> 0.048116507 | X59: =IF(ISNUMBER(L59),IF(L59>100000000,"Grande","Média/Pequena"),"Sem dado") -> Média/Pequena | Y59: {=_xlfn.IFS(ISNUMBER(W59)=FALSE,"Sem dado",W59>0.075,"Excelente",W59>0.04,"Bom",W59>0,"Fraco",TRUE,"Prejuízo")} -> Bom
A60: BANCO DIGIO S.A. | B60: 27098060 | C60: BRADESCO - PRUDENCIAL | D60: C0010045 | E60: C0080075 | F60: b2 | G60: 2 | H60: 8 | I60: OSASCO | J60: SP | K60: 06/2026 | L60: 28060664 | M60: 20228053 | N60: 2336309 | O60: 28005231 | P60: 25773075 | Q60: 55433 | R60: -219706 | S60: 2 | T60: 0 | U60: =IFERROR(CHOOSE(G60,"Público","Privado Nacional","Privado Estrangeiro"),"n.d.") -> Privado Nacional | V60: =IF(AND(ISNUMBER(M60),ISNUMBER(L60)),IF(L60>0,M60/L60,"n.d."),"NI") -> 0.72086865 | W60: =IF(AND(ISNUMBER(R60),ISNUMBER(Q60)),IF(Q60>0,R60/Q60,"n.d."),"NI") -> -3.9634514 | X60: =IF(ISNUMBER(L60),IF(L60>100000000,"Grande","Média/Pequena"),"Sem dado") -> Média/Pequena | Y60: {=_xlfn.IFS(ISNUMBER(W60)=FALSE,"Sem dado",W60>0.075,"Excelente",W60>0.04,"Bom",W60>0,"Fraco",TRUE,"Prejuízo")} -> Prejuízo
A61: CENTRAL DAS COOPERATIVAS DE ECONOMIA E CREDITO DO ESTADO DE MINAS GERAIS LTDA. - SICOOB CENTRAL CECREMGE | B61: 309024 | F61: b3C | G61: 2 | H61: 9 | I61: BELO HORIZONTE | J61: MG | K61: 06/2026 | L61: 27630783 | M61: 643420 | N61: 10514846 | O61: 26627866 | P61: 0 | Q61: 1002917 | R61: 50294 | S61: 0 | T61: 0 | U61: =IFERROR(CHOOSE(G61,"Público","Privado Nacional","Privado Estrangeiro"),"n.d.") -> Privado Nacional | V61: =IF(AND(ISNUMBER(M61),ISNUMBER(L61)),IF(L61>0,M61/L61,"n.d."),"NI") -> 0.023286347 | W61: =IF(AND(ISNUMBER(R61),ISNUMBER(Q61)),IF(Q61>0,R61/Q61,"n.d."),"NI") -> 0.050147719 | X61: =IF(ISNUMBER(L61),IF(L61>100000000,"Grande","Média/Pequena"),"Sem dado") -> Média/Pequena | Y61: {=_xlfn.IFS(ISNUMBER(W61)=FALSE,"Sem dado",W61>0.075,"Excelente",W61>0.04,"Bom",W61>0,"Fraco",TRUE,"Prejuízo")} -> Bom
A62: CITIBANK N.A. | B62: 33042953 | C62: CITIBANK - PRUDENCIAL | D62: C0030403 | E62: C0080192 | F62: b1 | G62: 3 | H62: 28 | I62: SAO PAULO | J62: SP | K62: 06/2026 | L62: 26282572 | M62: 15968 | N62: 2311009 | O62: 21074114 | P62: 15553292 | Q62: 5208458 | R62: 341539 | S62: 2 | T62: 0 | U62: =IFERROR(CHOOSE(G62,"Público","Privado Nacional","Privado Estrangeiro"),"n.d.") -> Privado Estrangeiro | V62: =IF(AND(ISNUMBER(M62),ISNUMBER(L62)),IF(L62>0,M62/L62,"n.d."),"NI") -> 0.00060755089 | W62: =IF(AND(ISNUMBER(R62),ISNUMBER(Q62)),IF(Q62>0,R62/Q62,"n.d."),"NI") -> 0.065573918 | X62: =IF(ISNUMBER(L62),IF(L62>100000000,"Grande","Média/Pequena"),"Sem dado") -> Média/Pequena | Y62: {=_xlfn.IFS(ISNUMBER(W62)=FALSE,"Sem dado",W62>0.075,"Excelente",W62>0.04,"Bom",W62>0,"Fraco",TRUE,"Prejuízo")} -> Bom
A63: PORTOSEG S.A. - CREDITO, FINANCIAMENTO E INVESTIMENTO | B63: 4862600 | C63: PORTO SEGURO - PRUDENCIAL | D63: C0051444 | E63: C0080642 | F63: n1 | G63: 2 | H63: 14 | I63: SAO PAULO | J63: SP | K63: 06/2026 | L63: 25524629 | M63: 20556575 | N63: 2421316 | O63: 24209822 | P63: 6946052 | Q63: 1314807 | R63: -32886 | S63: 2 | T63: 0 | U63: =IFERROR(CHOOSE(G63,"Público","Privado Nacional","Privado Estrangeiro"),"n.d.") -> Privado Nacional | V63: =IF(AND(ISNUMBER(M63),ISNUMBER(L63)),IF(L63>0,M63/L63,"n.d."),"NI") -> 0.80536234 | W63: =IF(AND(ISNUMBER(R63),ISNUMBER(Q63)),IF(Q63>0,R63/Q63,"n.d."),"NI") -> -0.025012036 | X63: =IF(ISNUMBER(L63),IF(L63>100000000,"Grande","Média/Pequena"),"Sem dado") -> Média/Pequena | Y63: {=_xlfn.IFS(ISNUMBER(W63)=FALSE,"Sem dado",W63>0.075,"Excelente",W63>0.04,"Bom",W63>0,"Fraco",TRUE,"Prejuízo")} -> Prejuízo
A64: BANCO CNH INDUSTRIAL CAPITAL S.A. | B64: 2992446 | C64: BANCO CNH INDUSTRIAL CAPITAL S.A - PRUDENCIAL | E64: C0081407 | F64: b2 | G64: 3 | H64: 8 | I64: CURITIBA | J64: PR | K64: 06/2026 | L64: 24178316 | M64: 20416836 | N64: 1306 | O64: 21566756 | P64: 19821707 | Q64: 2611560 | R64: -99496 | S64: 2 | T64: 0 | U64: =IFERROR(CHOOSE(G64,"Público","Privado Nacional","Privado Estrangeiro"),"n.d.") -> Privado Estrangeiro | V64: =IF(AND(ISNUMBER(M64),ISNUMBER(L64)),IF(L64>0,M64/L64,"n.d."),"NI") -> 0.84442754 | W64: =IF(AND(ISNUMBER(R64),ISNUMBER(Q64)),IF(Q64>0,R64/Q64,"n.d."),"NI") -> -0.038098301 | X64: =IF(ISNUMBER(L64),IF(L64>100000000,"Grande","Média/Pequena"),"Sem dado") -> Média/Pequena | Y64: {=_xlfn.IFS(ISNUMBER(W64)=FALSE,"Sem dado",W64>0.075,"Excelente",W64>0.04,"Bom",W64>0,"Fraco",TRUE,"Prejuízo")} -> Prejuízo
A65: BANCO CSF S.A. | B65: 8357240 | C65: BCO CSF S.A. - PRUDENCIAL | E65: C0081610 | F65: b2 | G65: 2 | H65: 8 | I65: SAO PAULO | J65: SP | K65: 06/2026 | L65: 23818077 | M65: 18220416 | N65: 1536756 | O65: 20380331 | P65: 4877271 | Q65: 3437746 | R65: 300157 | S65: 2 | T65: 0 | U65: =IFERROR(CHOOSE(G65,"Público","Privado Nacional","Privado Estrangeiro"),"n.d.") -> Privado Nacional | V65: =IF(AND(ISNUMBER(M65),ISNUMBER(L65)),IF(L65>0,M65/L65,"n.d."),"NI") -> 0.76498266 | W65: =IF(AND(ISNUMBER(R65),ISNUMBER(Q65)),IF(Q65>0,R65/Q65,"n.d."),"NI") -> 0.087312152 | X65: =IF(ISNUMBER(L65),IF(L65>100000000,"Grande","Média/Pequena"),"Sem dado") -> Média/Pequena | Y65: {=_xlfn.IFS(ISNUMBER(W65)=FALSE,"Sem dado",W65>0.075,"Excelente",W65>0.04,"Bom",W65>0,"Fraco",TRUE,"Prejuízo")} -> Excelente
A66: BANCO NACIONAL S.A. | B66: 17157777 | C66: BTG PACTUAL - PRUDENCIAL | D66: C0049944 | E66: C0080336 | F66: b2 | G66: 2 | H66: 8 | I66: RIO DE JANEIRO | J66: RJ | K66: 06/2026 | L66: 23199020 | M66: 362369 | N66: 198133 | O66: 11829743 | P66: 5909715 | Q66: 11369277 | R66: 1828643 | S66: 1 | T66: 0 | U66: =IFERROR(CHOOSE(G66,"Público","Privado Nacional","Privado Estrangeiro"),"n.d.") -> Privado Nacional | V66: =IF(AND(ISNUMBER(M66),ISNUMBER(L66)),IF(L66>0,M66/L66,"n.d."),"NI") -> 0.015620013 | W66: =IF(AND(ISNUMBER(R66),ISNUMBER(Q66)),IF(Q66>0,R66/Q66,"n.d."),"NI") -> 0.16084075 | X66: =IF(ISNUMBER(L66),IF(L66>100000000,"Grande","Média/Pequena"),"Sem dado") -> Média/Pequena | Y66: {=_xlfn.IFS(ISNUMBER(W66)=FALSE,"Sem dado",W66>0.075,"Excelente",W66>0.04,"Bom",W66>0,"Fraco",TRUE,"Prejuízo")} -> Excelente
A67: MERCADO CRÉDITO SOCIEDADE DE CRÉDITO, FINANCIAMENTO E INVESTIMENTO S.A. | B67: 37679449 | C67: MERCADO PAGO IP - PRUDENCIAL | D67: C0084820 | E67: C0084820 | F67: n1 | G67: 3 | H67: 14 | I67: OSASCO | J67: SP | K67: 06/2026 | L67: 23031915 | M67: 11218909 | N67: 3421828 | O67: 19040377 | P67: 15365256 | Q67: 3991538 | R67: 293857 | S67: 2 | T67: 0 | U67: =IFERROR(CHOOSE(G67,"Público","Privado Nacional","Privado Estrangeiro"),"n.d.") -> Privado Estrangeiro | V67: =IF(AND(ISNUMBER(M67),ISNUMBER(L67)),IF(L67>0,M67/L67,"n.d."),"NI") -> 0.48710274 | W67: =IF(AND(ISNUMBER(R67),ISNUMBER(Q67)),IF(Q67>0,R67/Q67,"n.d."),"NI") -> 0.073619993 | X67: =IF(ISNUMBER(L67),IF(L67>100000000,"Grande","Média/Pequena"),"Sem dado") -> Média/Pequena | Y67: {=_xlfn.IFS(ISNUMBER(W67)=FALSE,"Sem dado",W67>0.075,"Excelente",W67>0.04,"Bom",W67>0,"Fraco",TRUE,"Prejuízo")} -> Bom
A68: BANCO FIBRA S.A. | B68: 58616418 | C68: BCO FIBRA S.A. - PRUDENCIAL | E68: C0081483 | F68: b1 | G68: 2 | H68: 8 | I68: SAO PAULO | J68: SP | K68: 06/2026 | L68: 22655142 | M68: 5556997 | N68: 12148350 | O68: 21200920 | P68: 19896779 | Q68: 1454222 | R68: 154451 | S68: 2 | T68: 0 | U68: =IFERROR(CHOOSE(G68,"Público","Privado Nacional","Privado Estrangeiro"),"n.d.") -> Privado Nacional | V68: =IF(AND(ISNUMBER(M68),ISNUMBER(L68)),IF(L68>0,M68/L68,"n.d."),"NI") -> 0.24528635 | W68: =IF(AND(ISNUMBER(R68),ISNUMBER(Q68)),IF(Q68>0,R68/Q68,"n.d."),"NI") -> 0.10620868 | X68: =IF(ISNUMBER(L68),IF(L68>100000000,"Grande","Média/Pequena"),"Sem dado") -> Média/Pequena | Y68: {=_xlfn.IFS(ISNUMBER(W68)=FALSE,"Sem dado",W68>0.075,"Excelente",W68>0.04,"Bom",W68>0,"Fraco",TRUE,"Prejuízo")} -> Excelente
A69: CLOUDWALK INSTITUIÇÃO DE PAGAMENTO E SERVICOS LTDA | B69: 18189547 | C69: CLOUDWALK IP - PRUDENCIAL | E69: C0086581 | F69: n4 | G69: 2 | H69: 41 | I69: SAO PAULO | J69: SP | K69: 06/2026 | L69: 22593972 | M69: 0 | N69: 819519 | O69: 20277561 | P69: 1355863 | Q69: 2316411 | R69: 552378 | S69: 1 | T69: 0 | U69: =IFERROR(CHOOSE(G69,"Público","Privado Nacional","Privado Estrangeiro"),"n.d.") -> Privado Nacional | V69: =IF(AND(ISNUMBER(M69),ISNUMBER(L69)),IF(L69>0,M69/L69,"n.d."),"NI") -> 0 | W69: =IF(AND(ISNUMBER(R69),ISNUMBER(Q69)),IF(Q69>0,R69/Q69,"n.d."),"NI") -> 0.23846286 | X69: =IF(ISNUMBER(L69),IF(L69>100000000,"Grande","Média/Pequena"),"Sem dado") -> Média/Pequena | Y69: {=_xlfn.IFS(ISNUMBER(W69)=FALSE,"Sem dado",W69>0.075,"Excelente",W69>0.04,"Bom",W69>0,"Fraco",TRUE,"Prejuízo")} -> Excelente
A70: DEUTSCHE BANK S.A. - BANCO ALEMAO | B70: 62331228 | C70: DEUTSCHE - PRUDENCIAL | E70: C0080532 | F70: b1 | G70: 3 | H70: 8 | I70: SAO PAULO | J70: SP | K70: 06/2026 | L70: 21745428 | M70: 3777593 | N70: 9872679 | O70: 18666470 | P70: 15460387 | Q70: 3078957 | R70: 101246 | S70: 2 | T70: 0 | U70: =IFERROR(CHOOSE(G70,"Público","Privado Nacional","Privado Estrangeiro"),"n.d.") -> Privado Estrangeiro | V70: =IF(AND(ISNUMBER(M70),ISNUMBER(L70)),IF(L70>0,M70/L70,"n.d."),"NI") -> 0.17371895 | W70: =IF(AND(ISNUMBER(R70),ISNUMBER(Q70)),IF(Q70>0,R70/Q70,"n.d."),"NI") -> 0.032883213 | X70: =IF(ISNUMBER(L70),IF(L70>100000000,"Grande","Média/Pequena"),"Sem dado") -> Média/Pequena | Y70: {=_xlfn.IFS(ISNUMBER(W70)=FALSE,"Sem dado",W70>0.075,"Excelente",W70>0.04,"Bom",W70>0,"Fraco",TRUE,"Prejuízo")} -> Fraco
A71: STELLANTIS FINANCIAMENTOS SOCIEDADE DE CRÉDITO, FINANCIAMENTO E INVESTIMENTO S.A | B71: 3502961 | C71: STELLANTIS - PRUDENCIAL | D71: C0052508 | E71: C0087298 | F71: n1 | G71: 3 | H71: 14 | I71: SAO PAULO | J71: SP | K71: 06/2026 | L71: 21539454 | M71: 18478169 | N71: 750647 | O71: 18535784 | P71: 17973893 | Q71: 3003670 | R71: 119318 | S71: 2 | T71: 0 | U71: =IFERROR(CHOOSE(G71,"Público","Privado Nacional","Privado Estrangeiro"),"n.d.") -> Privado Estrangeiro | V71: =IF(AND(ISNUMBER(M71),ISNUMBER(L71)),IF(L71>0,M71/L71,"n.d."),"NI") -> 0.85787546 | W71: =IF(AND(ISNUMBER(R71),ISNUMBER(Q71)),IF(Q71>0,R71/Q71,"n.d."),"NI") -> 0.039724071 | X71: =IF(ISNUMBER(L71),IF(L71>100000000,"Grande","Média/Pequena"),"Sem dado") -> Média/Pequena | Y71: {=_xlfn.IFS(ISNUMBER(W71)=FALSE,"Sem dado",W71>0.075,"Excelente",W71>0.04,"Bom",W71>0,"Fraco",TRUE,"Prejuízo")} -> Fraco
A72: BANCO DO ESTADO DO PARÁ S.A. | B72: 4913711 | C72: BCO DO EST. DO PA S.A. - PRUDENCIAL | E72: C0081586 | F72: b1 | G72: 1 | H72: 8 | I72: BELEM | J72: PA | K72: 06/2026 | L72: 21444615 | M72: 15444766 | N72: 1420567 | O72: 19200343 | P72: 18223337 | Q72: 2244272 | R72: 100805 | S72: 165 | T72: 34 | U72: =IFERROR(CHOOSE(G72,"Público","Privado Nacional","Privado Estrangeiro"),"n.d.") -> Público | V72: =IF(AND(ISNUMBER(M72),ISNUMBER(L72)),IF(L72>0,M72/L72,"n.d."),"NI") -> 0.72021652 | W72: =IF(AND(ISNUMBER(R72),ISNUMBER(Q72)),IF(Q72>0,R72/Q72,"n.d."),"NI") -> 0.04491657 | X72: =IF(ISNUMBER(L72),IF(L72>100000000,"Grande","Média/Pequena"),"Sem dado") -> Média/Pequena | Y72: {=_xlfn.IFS(ISNUMBER(W72)=FALSE,"Sem dado",W72>0.075,"Excelente",W72>0.04,"Bom",W72>0,"Fraco",TRUE,"Prejuízo")} -> Bom
A73: BANCO MERCEDES-BENZ DO BRASIL S.A. | B73: 60814191 | C73: MERCEDES-BENZ - PRUDENCIAL | D73: C0051262 | E73: C0080563 | F73: b2 | G73: 3 | H73: 8 | I73: SAO BERNARDO DO CAMPO | J73: SP | K73: 06/2026 | L73: 20853819 | M73: 19284332 | N73: 317664 | O73: 18430109 | P73: 17728172 | Q73: 2423711 | R73: 39490 | S73: 2 | T73: 0 | U73: =IFERROR(CHOOSE(G73,"Público","Privado Nacional","Privado Estrangeiro"),"n.d.") -> Privado Estrangeiro | V73: =IF(AND(ISNUMBER(M73),ISNUMBER(L73)),IF(L73>0,M73/L73,"n.d."),"NI") -> 0.92473863 | W73: =IF(AND(ISNUMBER(R73),ISNUMBER(Q73)),IF(Q73>0,R73/Q73,"n.d."),"NI") -> 0.016293197 | X73: =IF(ISNUMBER(L73),IF(L73>100000000,"Grande","Média/Pequena"),"Sem dado") -> Média/Pequena | Y73: {=_xlfn.IFS(ISNUMBER(W73)=FALSE,"Sem dado",W73>0.075,"Excelente",W73>0.04,"Bom",W73>0,"Fraco",TRUE,"Prejuízo")} -> Fraco
A74: BANCO CRÉDIT AGRICOLE BRASIL S.A. | B74: 75647891 | C74: CREDIT AGRICOLE - PRUDENCIAL | E74: C0080491 | F74: b1 | G74: 3 | H74: 8 | I74: SAO PAULO | J74: SP | K74: 06/2026 | L74: 20150414 | M74: 8746825 | N74: 4002938 | O74: 15955785 | P74: 14040180 | Q74: 4194628 | R74: 137358 | S74: 2 | T74: 0 | U74: =IFERROR(CHOOSE(G74,"Público","Privado Nacional","Privado Estrangeiro"),"n.d.") -> Privado Estrangeiro | V74: =IF(AND(ISNUMBER(M74),ISNUMBER(L74)),IF(L74>0,M74/L74,"n.d."),"NI") -> 0.43407669 | W74: =IF(AND(ISNUMBER(R74),ISNUMBER(Q74)),IF(Q74>0,R74/Q74,"n.d."),"NI") -> 0.03274617 | X74: =IF(ISNUMBER(L74),IF(L74>100000000,"Grande","Média/Pequena"),"Sem dado") -> Média/Pequena | Y74: {=_xlfn.IFS(ISNUMBER(W74)=FALSE,"Sem dado",W74>0.075,"Excelente",W74>0.04,"Bom",W74>0,"Fraco",TRUE,"Prejuízo")} -> Fraco
A75: LUIZACRED S.A. SOCIEDADE DE CRÉDITO, FINANCIAMENTO E INVESTIMENTO | B75: 2206577 | C75: ITAU - PRUDENCIAL | D75: C0010069 | E75: C0080099 | F75: n1 | G75: 2 | H75: 14 | I75: SAO PAULO | J75: SP | K75: 06/2026 | L75: 19422651 | M75: 17848013 | N75: 26208 | O75: 17177854 | P75: 3392857 | Q75: 2244797 | R75: 218800 | S75: 2 | T75: 0 | U75: =IFERROR(CHOOSE(G75,"Público","Privado Nacional","Privado Estrangeiro"),"n.d.") -> Privado Nacional | V75: =IF(AND(ISNUMBER(M75),ISNUMBER(L75)),IF(L75>0,M75/L75,"n.d."),"NI") -> 0.91892775 | W75: =IF(AND(ISNUMBER(R75),ISNUMBER(Q75)),IF(Q75>0,R75/Q75,"n.d."),"NI") -> 0.097469838 | X75: =IF(ISNUMBER(L75),IF(L75>100000000,"Grande","Média/Pequena"),"Sem dado") -> Média/Pequena | Y75: {=_xlfn.IFS(ISNUMBER(W75)=FALSE,"Sem dado",W75>0.075,"Excelente",W75>0.04,"Bom",W75>0,"Fraco",TRUE,"Prejuízo")} -> Excelente
A76: BRADESCO LEASING S.A. - ARRENDAMENTO MERCANTIL | B76: 47509120 | C76: BRADESCO - PRUDENCIAL | D76: C0010045 | E76: C0080075 | F76: n1 | G76: 2 | H76: 19 | I76: OSASCO | J76: SP | K76: 06/2026 | L76: 19322032 | M76: 8085279 | N76: 9678666 | O76: 14638157 | P76: 13099402 | Q76: 4683875 | R76: 238141 | S76: 2 | T76: 0 | U76: =IFERROR(CHOOSE(G76,"Público","Privado Nacional","Privado Estrangeiro"),"n.d.") -> Privado Nacional | V76: =IF(AND(ISNUMBER(M76),ISNUMBER(L76)),IF(L76>0,M76/L76,"n.d."),"NI") -> 0.41844869 | W76: =IF(AND(ISNUMBER(R76),ISNUMBER(Q76)),IF(Q76>0,R76/Q76,"n.d."),"NI") -> 0.050842732 | X76: =IF(ISNUMBER(L76),IF(L76>100000000,"Grande","Média/Pequena"),"Sem dado") -> Média/Pequena | Y76: {=_xlfn.IFS(ISNUMBER(W76)=FALSE,"Sem dado",W76>0.075,"Excelente",W76>0.04,"Bom",W76>0,"Fraco",TRUE,"Prejuízo")} -> Bom
A77: COOPERATIVA CENTRAL DE CRÉDITO DO ESTADO DE SÃO PAULO - SICOOB SÃO PAULO | B77: 63917579 | F77: b3C | G77: 2 | H77: 9 | I77: RIBEIRAO PRETO | J77: SP | K77: 06/2026 | L77: 19289667 | M77: 0 | N77: 6723730 | O77: 18358775 | P77: 1544428 | Q77: 930893 | R77: 61944 | S77: 0 | T77: 0 | U77: =IFERROR(CHOOSE(G77,"Público","Privado Nacional","Privado Estrangeiro"),"n.d.") -> Privado Nacional | V77: =IF(AND(ISNUMBER(M77),ISNUMBER(L77)),IF(L77>0,M77/L77,"n.d."),"NI") -> 0 | W77: =IF(AND(ISNUMBER(R77),ISNUMBER(Q77)),IF(Q77>0,R77/Q77,"n.d."),"NI") -> 0.066542556 | X77: =IF(ISNUMBER(L77),IF(L77>100000000,"Grande","Média/Pequena"),"Sem dado") -> Média/Pequena | Y77: {=_xlfn.IFS(ISNUMBER(W77)=FALSE,"Sem dado",W77>0.075,"Excelente",W77>0.04,"Bom",W77>0,"Fraco",TRUE,"Prejuízo")} -> Bom
A78: BTG PACTUAL CORRETORA DE TÍTULOS E VALORES MOBILIÁRIOS S.A. | B78: 43815158 | C78: BTG PACTUAL - PRUDENCIAL | D78: C0049944 | E78: C0080336 | F78: n2 | G78: 2 | H78: 15 | I78: RIO DE JANEIRO | J78: RJ | K78: 06/2026 | L78: 19186457 | M78: 0 | N78: 1113824 | O78: 18159300 | P78: 325053 | Q78: 1027158 | R78: 180891 | S78: 6 | T78: 0 | U78: =IFERROR(CHOOSE(G78,"Público","Privado Nacional","Privado Estrangeiro"),"n.d.") -> Privado Nacional | V78: =IF(AND(ISNUMBER(M78),ISNUMBER(L78)),IF(L78>0,M78/L78,"n.d."),"NI") -> 0 | W78: =IF(AND(ISNUMBER(R78),ISNUMBER(Q78)),IF(Q78>0,R78/Q78,"n.d."),"NI") -> 0.17610825 | X78: =IF(ISNUMBER(L78),IF(L78>100000000,"Grande","Média/Pequena"),"Sem dado") -> Média/Pequena | Y78: {=_xlfn.IFS(ISNUMBER(W78)=FALSE,"Sem dado",W78>0.075,"Excelente",W78>0.04,"Bom",W78>0,"Fraco",TRUE,"Prejuízo")} -> Excelente
A79: COOPERATIVA DE CREDITO CREDICITRUS | B79: 54037916 | F79: b3S | G79: 2 | H79: 9 | I79: BEBEDOURO | J79: SP | K79: 06/2026 | L79: 18797895 | M79: 9038341 | N79: 3840257 | O79: 15102280 | P79: 13307188 | Q79: 3695615 | R79: 164239 | S79: 0 | T79: 127 | U79: =IFERROR(CHOOSE(G79,"Público","Privado Nacional","Privado Estrangeiro"),"n.d.") -> Privado Nacional | V79: =IF(AND(ISNUMBER(M79),ISNUMBER(L79)),IF(L79>0,M79/L79,"n.d."),"NI") -> 0.48081666 | W79: =IF(AND(ISNUMBER(R79),ISNUMBER(Q79)),IF(Q79>0,R79/Q79,"n.d."),"NI") -> 0.044441588 | X79: =IF(ISNUMBER(L79),IF(L79>100000000,"Grande","Média/Pequena"),"Sem dado") -> Média/Pequena | Y79: {=_xlfn.IFS(ISNUMBER(W79)=FALSE,"Sem dado",W79>0.075,"Excelente",W79>0.04,"Bom",W79>0,"Fraco",TRUE,"Prejuízo")} -> Bom
A80: BR PARTNERS BANCO DE INVESTIMENTO S.A. | B80: 13220493 | C80: BR PARTNERS - PRUDENCIAL | E80: C0080934 | F80: b2 | G80: 2 | H80: 13 | I80: SAO PAULO | J80: SP | K80: 06/2026 | L80: 18254444 | M80: 178232 | N80: 16606264 | O80: 17676436 | P80: 16192670 | Q80: 578008 | R80: -4635 | S80: 2 | T80: 0 | U80: =IFERROR(CHOOSE(G80,"Público","Privado Nacional","Privado Estrangeiro"),"n.d.") -> Privado Nacional | V80: =IF(AND(ISNUMBER(M80),ISNUMBER(L80)),IF(L80>0,M80/L80,"n.d."),"NI") -> 0.0097637594 | W80: =IF(AND(ISNUMBER(R80),ISNUMBER(Q80)),IF(Q80>0,R80/Q80,"n.d."),"NI") -> -0.0080189202 | X80: =IF(ISNUMBER(L80),IF(L80>100000000,"Grande","Média/Pequena"),"Sem dado") -> Média/Pequena | Y80: {=_xlfn.IFS(ISNUMBER(W80)=FALSE,"Sem dado",W80>0.075,"Excelente",W80>0.04,"Bom",W80>0,"Fraco",TRUE,"Prejuízo")} -> Prejuízo
A81: BANCO GM S.A. | B81: 59274605 | C81: GM - PRUDENCIAL | E81: C0080848 | F81: b2 | G81: 3 | H81: 8 | I81: SAO PAULO | J81: SP | K81: 06/2026 | L81: 18035945 | M81: 13773333 | N81: 162166 | O81: 15113876 | P81: 13229613 | Q81: 2922069 | R81: 277328 | S81: 2 | T81: 0 | U81: =IFERROR(CHOOSE(G81,"Público","Privado Nacional","Privado Estrangeiro"),"n.d.") -> Privado Estrangeiro | V81: =IF(AND(ISNUMBER(M81),ISNUMBER(L81)),IF(L81>0,M81/L81,"n.d."),"NI") -> 0.76366018 | W81: =IF(AND(ISNUMBER(R81),ISNUMBER(Q81)),IF(Q81>0,R81/Q81,"n.d."),"NI") -> 0.094908094 | X81: =IF(ISNUMBER(L81),IF(L81>100000000,"Grande","Média/Pequena"),"Sem dado") -> Média/Pequena | Y81: {=_xlfn.IFS(ISNUMBER(W81)=FALSE,"Sem dado",W81>0.075,"Excelente",W81>0.04,"Bom",W81>0,"Fraco",TRUE,"Prejuízo")} -> Excelente
A82: BANCO SOFISA S.A. | B82: 60889128 | C82: SOFISA - PRUDENCIAL | D82: C0031873 | E82: C0080271 | F82: b1 | G82: 2 | H82: 8 | I82: SAO PAULO | J82: SP | K82: 06/2026 | L82: 17860040 | M82: 7681224 | N82: 8389223 | O82: 16702237 | P82: 15763634 | Q82: 1157803 | R82: 39612 | S82: 24 | T82: 0 | U82: =IFERROR(CHOOSE(G82,"Público","Privado Nacional","Privado Estrangeiro"),"n.d.") -> Privado Nacional | V82: =IF(AND(ISNUMBER(M82),ISNUMBER(L82)),IF(L82>0,M82/L82,"n.d."),"NI") -> 0.43007877 | W82: =IF(AND(ISNUMBER(R82),ISNUMBER(Q82)),IF(Q82>0,R82/Q82,"n.d."),"NI") -> 0.034213074 | X82: =IF(ISNUMBER(L82),IF(L82>100000000,"Grande","Média/Pequena"),"Sem dado") -> Média/Pequena | Y82: {=_xlfn.IFS(ISNUMBER(W82)=FALSE,"Sem dado",W82>0.075,"Excelente",W82>0.04,"Bom",W82>0,"Fraco",TRUE,"Prejuízo")} -> Fraco
A83: COOPERATIVA CENTRAL DE CRÉDITO COM INTERAÇÃO SOLIDÁRIA - CENTRAL CRESOL BASER | B83: 1401771 | F83: b3C | G83: 2 | H83: 9 | I83: FRANCISCO BELTRAO | J83: PR | K83: 06/2026 | L83: 17754461 | M83: 99057 | N83: 4187898 | O83: 16966332 | P83: 10293913 | Q83: 788128 | R83: 57735 | S83: 0 | T83: 0 | U83: =IFERROR(CHOOSE(G83,"Público","Privado Nacional","Privado Estrangeiro"),"n.d.") -> Privado Nacional | V83: =IF(AND(ISNUMBER(M83),ISNUMBER(L83)),IF(L83>0,M83/L83,"n.d."),"NI") -> 0.0055792739 | W83: =IF(AND(ISNUMBER(R83),ISNUMBER(Q83)),IF(Q83>0,R83/Q83,"n.d."),"NI") -> 0.073255867 | X83: =IF(ISNUMBER(L83),IF(L83>100000000,"Grande","Média/Pequena"),"Sem dado") -> Média/Pequena | Y83: {=_xlfn.IFS(ISNUMBER(W83)=FALSE,"Sem dado",W83>0.075,"Excelente",W83>0.04,"Bom",W83>0,"Fraco",TRUE,"Prejuízo")} -> Bom
A84: COOPERATIVA CENTRAL DE CRÉDITO UNICRED DO BRASIL - UNICRED DO BRASIL | B84: 315557 | F84: b3C | G84: 2 | H84: 9 | I84: SAO PAULO | J84: SP | K84: 06/2026 | L84: 17572425 | M84: 0 | N84: 9733269 | O84: 16799091 | P84: 58 | Q84: 773335 | R84: 41955 | S84: 0 | T84: 1 | U84: =IFERROR(CHOOSE(G84,"Público","Privado Nacional","Privado Estrangeiro"),"n.d.") -> Privado Nacional | V84: =IF(AND(ISNUMBER(M84),ISNUMBER(L84)),IF(L84>0,M84/L84,"n.d."),"NI") -> 0 | W84: =IF(AND(ISNUMBER(R84),ISNUMBER(Q84)),IF(Q84>0,R84/Q84,"n.d."),"NI") -> 0.054252038 | X84: =IF(ISNUMBER(L84),IF(L84>100000000,"Grande","Média/Pequena"),"Sem dado") -> Média/Pequena | Y84: {=_xlfn.IFS(ISNUMBER(W84)=FALSE,"Sem dado",W84>0.075,"Excelente",W84>0.04,"Bom",W84>0,"Fraco",TRUE,"Prejuízo")} -> Bom
A85: COOPERATIVA DE CREDITO VALE DO ITAJAI - VIACREDI | B85: 82639451 | F85: b3S | G85: 2 | H85: 9 | I85: BLUMENAU | J85: SC | K85: 06/2026 | L85: 17524030 | M85: 8725675 | N85: 721306 | O85: 13841312 | P85: 12675486 | Q85: 3682717 | R85: 405343 | S85: 0 | T85: 119 | U85: =IFERROR(CHOOSE(G85,"Público","Privado Nacional","Privado Estrangeiro"),"n.d.") -> Privado Nacional | V85: =IF(AND(ISNUMBER(M85),ISNUMBER(L85)),IF(L85>0,M85/L85,"n.d."),"NI") -> 0.49792628 | W85: =IF(AND(ISNUMBER(R85),ISNUMBER(Q85)),IF(Q85>0,R85/Q85,"n.d."),"NI") -> 0.11006629 | X85: =IF(ISNUMBER(L85),IF(L85>100000000,"Grande","Média/Pequena"),"Sem dado") -> Média/Pequena | Y85: {=_xlfn.IFS(ISNUMBER(W85)=FALSE,"Sem dado",W85>0.075,"Excelente",W85>0.04,"Bom",W85>0,"Fraco",TRUE,"Prejuízo")} -> Excelente
A86: BANCO JOHN DEERE S.A. | B86: 91884981 | C86: BRADESCO - PRUDENCIAL | D86: C0010045 | E86: C0080075 | F86: b1 | G86: 2 | H86: 8 | I86: OSASCO | J86: SP | K86: 06/2026 | L86: 16770609 | M86: 14635555 | N86: 30340 | O86: 12482523 | P86: 12310073 | Q86: 4288086 | R86: 65446 | S86: 2 | T86: 0 | U86: =IFERROR(CHOOSE(G86,"Público","Privado Nacional","Privado Estrangeiro"),"n.d.") -> Privado Nacional | V86: =IF(AND(ISNUMBER(M86),ISNUMBER(L86)),IF(L86>0,M86/L86,"n.d."),"NI") -> 0.87269073 | W86: =IF(AND(ISNUMBER(R86),ISNUMBER(Q86)),IF(Q86>0,R86/Q86,"n.d."),"NI") -> 0.015262287 | X86: =IF(ISNUMBER(L86),IF(L86>100000000,"Grande","Média/Pequena"),"Sem dado") -> Média/Pequena | Y86: {=_xlfn.IFS(ISNUMBER(W86)=FALSE,"Sem dado",W86>0.075,"Excelente",W86>0.04,"Bom",W86>0,"Fraco",TRUE,"Prejuízo")} -> Fraco
A87: BANCO BRADESCO BBI S.A. | B87: 6271464 | C87: BRADESCO - PRUDENCIAL | D87: C0010045 | E87: C0080075 | F87: b1 | G87: 2 | H87: 8 | I87: OSASCO | J87: SP | K87: 06/2026 | L87: 16757041 | M87: 0 | N87: 5081557 | O87: 10258524 | P87: 8516751 | Q87: 6498517 | R87: 803976 | S87: 5 | T87: 0 | U87: =IFERROR(CHOOSE(G87,"Público","Privado Nacional","Privado Estrangeiro"),"n.d.") -> Privado Nacional | V87: =IF(AND(ISNUMBER(M87),ISNUMBER(L87)),IF(L87>0,M87/L87,"n.d."),"NI") -> 0 | W87: =IF(AND(ISNUMBER(R87),ISNUMBER(Q87)),IF(Q87>0,R87/Q87,"n.d."),"NI") -> 0.12371684 | X87: =IF(ISNUMBER(L87),IF(L87>100000000,"Grande","Média/Pequena"),"Sem dado") -> Média/Pequena | Y87: {=_xlfn.IFS(ISNUMBER(W87)=FALSE,"Sem dado",W87>0.075,"Excelente",W87>0.04,"Bom",W87>0,"Fraco",TRUE,"Prejuízo")} -> Excelente
A88: SCOTIABANK BRASIL S.A. BANCO MÚLTIPLO | B88: 29030467 | C88: SCOTIABANK BRASIL - PRUDENCIAL | D88: C0052230 | E88: C0081452 | F88: b1 | G88: 3 | H88: 8 | I88: SAO PAULO | J88: SP | K88: 06/2026 | L88: 16750390 | M88: 2503686 | N88: 4358158 | O88: 13483132 | P88: 12778534 | Q88: 3267259 | R88: 156951 | S88: 2 | T88: 0 | U88: =IFERROR(CHOOSE(G88,"Público","Privado Nacional","Privado Estrangeiro"),"n.d.") -> Privado Estrangeiro | V88: =IF(AND(ISNUMBER(M88),ISNUMBER(L88)),IF(L88>0,M88/L88,"n.d."),"NI") -> 0.14947031 | W88: =IF(AND(ISNUMBER(R88),ISNUMBER(Q88)),IF(Q88>0,R88/Q88,"n.d."),"NI") -> 0.048037514 | X88: =IF(ISNUMBER(L88),IF(L88>100000000,"Grande","Média/Pequena"),"Sem dado") -> Média/Pequena | Y88: {=_xlfn.IFS(ISNUMBER(W88)=FALSE,"Sem dado",W88>0.075,"Excelente",W88>0.04,"Bom",W88>0,"Fraco",TRUE,"Prejuízo")} -> Bom
A89: BANCO MORGAN STANLEY S.A. | B89: 2801938 | C89: MORGAN STANLEY - PRUDENCIAL | D89: C0051413 | E89: C0080628 | F89: b1 | G89: 3 | H89: 8 | I89: SAO PAULO | J89: SP | K89: 06/2026 | L89: 16726636 | M89: 232468 | N89: 10148169 | O89: 11812063 | P89: 6524914 | Q89: 4914573 | R89: 315166 | S89: 2 | T89: 0 | U89: =IFERROR(CHOOSE(G89,"Público","Privado Nacional","Privado Estrangeiro"),"n.d.") -> Privado Estrangeiro | V89: =IF(AND(ISNUMBER(M89),ISNUMBER(L89)),IF(L89>0,M89/L89,"n.d."),"NI") -> 0.013898073 | W89: =IF(AND(ISNUMBER(R89),ISNUMBER(Q89)),IF(Q89>0,R89/Q89,"n.d."),"NI") -> 0.064128867 | X89: =IF(ISNUMBER(L89),IF(L89>100000000,"Grande","Média/Pequena"),"Sem dado") -> Média/Pequena | Y89: {=_xlfn.IFS(ISNUMBER(W89)=FALSE,"Sem dado",W89>0.075,"Excelente",W89>0.04,"Bom",W89>0,"Fraco",TRUE,"Prejuízo")} -> Bom
A90: BANCO HSBC S.A. | B90: 53518684 | C90: BANCO HSBC - PRUDENCIAL | E90: C0084741 | F90: b1 | G90: 3 | H90: 8 | I90: SAO PAULO | J90: SP | K90: 06/2026 | L90: 16666011 | M90: 5254439 | N90: 6256048 | O90: 15037777 | P90: 12899483 | Q90: 1628234 | R90: 91854 | S90: 2 | T90: 0 | U90: =IFERROR(CHOOSE(G90,"Público","Privado Nacional","Privado Estrangeiro"),"n.d.") -> Privado Estrangeiro | V90: =IF(AND(ISNUMBER(M90),ISNUMBER(L90)),IF(L90>0,M90/L90,"n.d."),"NI") -> 0.31527874 | W90: =IF(AND(ISNUMBER(R90),ISNUMBER(Q90)),IF(Q90>0,R90/Q90,"n.d."),"NI") -> 0.056413267 | X90: =IF(ISNUMBER(L90),IF(L90>100000000,"Grande","Média/Pequena"),"Sem dado") -> Média/Pequena | Y90: {=_xlfn.IFS(ISNUMBER(W90)=FALSE,"Sem dado",W90>0.075,"Excelente",W90>0.04,"Bom",W90>0,"Fraco",TRUE,"Prejuízo")} -> Bom
A91: BANK OF CHINA (BRASIL) BANCO MÚLTIPLO S/A | B91: 7450604 | C91: BANK OF CHINA (BRASIL) - PRUDENCIAL | D91: C0032119 | E91: C0080295 | F91: b1 | G91: 3 | H91: 8 | I91: SAO PAULO | J91: SP | K91: 06/2026 | L91: 16639710 | M91: 7784956 | N91: 5876990 | O91: 15385491 | P91: 14157109 | Q91: 1254219 | R91: -26542 | S91: 8 | T91: 0 | U91: =IFERROR(CHOOSE(G91,"Público","Privado Nacional","Privado Estrangeiro"),"n.d.") -> Privado Estrangeiro | V91: =IF(AND(ISNUMBER(M91),ISNUMBER(L91)),IF(L91>0,M91/L91,"n.d."),"NI") -> 0.46785407 | W91: =IF(AND(ISNUMBER(R91),ISNUMBER(Q91)),IF(Q91>0,R91/Q91,"n.d."),"NI") -> -0.021162173 | X91: =IF(ISNUMBER(L91),IF(L91>100000000,"Grande","Média/Pequena"),"Sem dado") -> Média/Pequena | Y91: {=_xlfn.IFS(ISNUMBER(W91)=FALSE,"Sem dado",W91>0.075,"Excelente",W91>0.04,"Bom",W91>0,"Fraco",TRUE,"Prejuízo")} -> Prejuízo
A92: BANCO RCI BRASIL S.A. | B92: 62307848 | C92: SANTANDER - PRUDENCIAL | D92: C0030379 | E92: C0080185 | F92: b2 | G92: 3 | H92: 8 | I92: SAO PAULO | J92: SP | K92: 06/2026 | L92: 16401701 | M92: 10365397 | N92: 4387693 | O92: 14986286 | P92: 13736063 | Q92: 1415415 | R92: 149582 | S92: 2 | T92: 0 | U92: =IFERROR(CHOOSE(G92,"Público","Privado Nacional","Privado Estrangeiro"),"n.d.") -> Privado Estrangeiro | V92: =IF(AND(ISNUMBER(M92),ISNUMBER(L92)),IF(L92>0,M92/L92,"n.d."),"NI") -> 0.63197085 | W92: =IF(AND(ISNUMBER(R92),ISNUMBER(Q92)),IF(Q92>0,R92/Q92,"n.d."),"NI") -> 0.10568067 | X92: =IF(ISNUMBER(L92),IF(L92>100000000,"Grande","Média/Pequena"),"Sem dado") -> Média/Pequena | Y92: {=_xlfn.IFS(ISNUMBER(W92)=FALSE,"Sem dado",W92>0.075,"Excelente",W92>0.04,"Bom",W92>0,"Fraco",TRUE,"Prejuízo")} -> Excelente
A93: BANCO VOLVO BRASIL S.A. | B93: 58017179 | C93: VOLVO - PRUDENCIAL | E93: C0080769 | F93: b2 | G93: 3 | H93: 8 | I93: CURITIBA | J93: PR | K93: 06/2026 | L93: 16337893 | M93: 14011636 | N93: 1158021 | O93: 12164690 | P93: 12024746 | Q93: 4173203 | R93: 198482 | S93: 2 | T93: 0 | U93: =IFERROR(CHOOSE(G93,"Público","Privado Nacional","Privado Estrangeiro"),"n.d.") -> Privado Estrangeiro | V93: =IF(AND(ISNUMBER(M93),ISNUMBER(L93)),IF(L93>0,M93/L93,"n.d."),"NI") -> 0.85761585 | W93: =IF(AND(ISNUMBER(R93),ISNUMBER(Q93)),IF(Q93>0,R93/Q93,"n.d."),"NI") -> 0.04756107 | X93: =IF(ISNUMBER(L93),IF(L93>100000000,"Grande","Média/Pequena"),"Sem dado") -> Média/Pequena | Y93: {=_xlfn.IFS(ISNUMBER(W93)=FALSE,"Sem dado",W93>0.075,"Excelente",W93>0.04,"Bom",W93>0,"Fraco",TRUE,"Prejuízo")} -> Bom
A94: BANCO STELLANTIS S.A. | B94: 62237425 | C94: STELLANTIS - PRUDENCIAL | D94: C0052508 | E94: C0087298 | F94: b2 | G94: 3 | H94: 8 | I94: SAO PAULO | J94: SP | K94: 06/2026 | L94: 15786564 | M94: 7362599 | N94: 439799 | O94: 14258835 | P94: 13973289 | Q94: 1527729 | R94: 135403 | S94: 2 | T94: 0 | U94: =IFERROR(CHOOSE(G94,"Público","Privado Nacional","Privado Estrangeiro"),"n.d.") -> Privado Estrangeiro | V94: =IF(AND(ISNUMBER(M94),ISNUMBER(L94)),IF(L94>0,M94/L94,"n.d."),"NI") -> 0.46638388 | W94: =IF(AND(ISNUMBER(R94),ISNUMBER(Q94)),IF(Q94>0,R94/Q94,"n.d."),"NI") -> 0.088630248 | X94: =IF(ISNUMBER(L94),IF(L94>100000000,"Grande","Média/Pequena"),"Sem dado") -> Média/Pequena | Y94: {=_xlfn.IFS(ISNUMBER(W94)=FALSE,"Sem dado",W94>0.075,"Excelente",W94>0.04,"Bom",W94>0,"Fraco",TRUE,"Prejuízo")} -> Excelente
A95: COOPERATIVA DE CRÉDITO, POUPANÇA E INVESTIMENTO DEXIS - SICREDI DEXIS | B95: 79342069 | F95: b3S | G95: 2 | H95: 9 | I95: MARINGA | J95: PR | K95: 06/2026 | L95: 15763618 | M95: 8895732 | N95: 5471429 | O95: 14298311 | P95: 9139325 | Q95: 1465307 | R95: 88996 | S95: 0 | T95: 114 | U95: =IFERROR(CHOOSE(G95,"Público","Privado Nacional","Privado Estrangeiro"),"n.d.") -> Privado Nacional | V95: =IF(AND(ISNUMBER(M95),ISNUMBER(L95)),IF(L95>0,M95/L95,"n.d."),"NI") -> 0.56432045 | W95: =IF(AND(ISNUMBER(R95),ISNUMBER(Q95)),IF(Q95>0,R95/Q95,"n.d."),"NI") -> 0.060735395 | X95: =IF(ISNUMBER(L95),IF(L95>100000000,"Grande","Média/Pequena"),"Sem dado") -> Média/Pequena | Y95: {=_xlfn.IFS(ISNUMBER(W95)=FALSE,"Sem dado",W95>0.075,"Excelente",W95>0.04,"Bom",W95>0,"Fraco",TRUE,"Prejuízo")} -> Bom
A96: KIRTON BANK S.A. - BANCO MÚLTIPLO | B96: 1701201 | C96: BRADESCO - PRUDENCIAL | D96: C0010045 | E96: C0080075 | F96: b1 | G96: 2 | H96: 8 | I96: OSASCO | J96: SP | K96: 06/2026 | L96: 15529831 | M96: 0 | N96: 4250 | O96: 3698093 | P96: 2427709 | Q96: 11831737 | R96: 377737 | S96: 1 | T96: 0 | U96: =IFERROR(CHOOSE(G96,"Público","Privado Nacional","Privado Estrangeiro"),"n.d.") -> Privado Nacional | V96: =IF(AND(ISNUMBER(M96),ISNUMBER(L96)),IF(L96>0,M96/L96,"n.d."),"NI") -> 0 | W96: =IF(AND(ISNUMBER(R96),ISNUMBER(Q96)),IF(Q96>0,R96/Q96,"n.d."),"NI") -> 0.031925743 | X96: =IF(ISNUMBER(L96),IF(L96>100000000,"Grande","Média/Pequena"),"Sem dado") -> Média/Pequena | Y96: {=_xlfn.IFS(ISNUMBER(W96)=FALSE,"Sem dado",W96>0.075,"Excelente",W96>0.04,"Bom",W96>0,"Fraco",TRUE,"Prejuízo")} -> Fraco
A97: BANCO BRADESCARD S.A. | B97: 4184779 | C97: BRADESCO - PRUDENCIAL | D97: C0010045 | E97: C0080075 | F97: b1 | G97: 2 | H97: 8 | I97: OSASCO | J97: SP | K97: 06/2026 | L97: 15522406 | M97: 8283770 | N97: 18 | O97: 15413267 | P97: 7112832 | Q97: 109139 | R97: 1536 | S97: 2 | T97: 0 | U97: =IFERROR(CHOOSE(G97,"Público","Privado Nacional","Privado Estrangeiro"),"n.d.") -> Privado Nacional | V97: =IF(AND(ISNUMBER(M97),ISNUMBER(L97)),IF(L97>0,M97/L97,"n.d."),"NI") -> 0.53366534 | W97: =IF(AND(ISNUMBER(R97),ISNUMBER(Q97)),IF(Q97>0,R97/Q97,"n.d."),"NI") -> 0.014073796 | X97: =IF(ISNUMBER(L97),IF(L97>100000000,"Grande","Média/Pequena"),"Sem dado") -> Média/Pequena | Y97: {=_xlfn.IFS(ISNUMBER(W97)=FALSE,"Sem dado",W97>0.075,"Excelente",W97>0.04,"Bom",W97>0,"Fraco",TRUE,"Prejuízo")} -> Fraco
A98: BANCO DE DESENVOLVIMENTO DE MINAS GERAIS S.A.-BDMG | B98: 38486817 | C98: BCO DES. DE MG S.A. - PRUDENCIAL | E98: C0081328 | F98: b4 | G98: 1 | H98: 5 | I98: BELO HORIZONTE | J98: MG | K98: 06/2026 | L98: 15427555 | M98: 9253331 | N98: 4175546 | O98: 12945523 | P98: 11810887 | Q98: 2482032 | R98: 71599 | S98: 2 | T98: 0 | U98: =IFERROR(CHOOSE(G98,"Público","Privado Nacional","Privado Estrangeiro"),"n.d.") -> Público | V98: =IF(AND(ISNUMBER(M98),ISNUMBER(L98)),IF(L98>0,M98/L98,"n.d."),"NI") -> 0.59979245 | W98: =IF(AND(ISNUMBER(R98),ISNUMBER(Q98)),IF(Q98>0,R98/Q98,"n.d."),"NI") -> 0.028846929 | X98: =IF(ISNUMBER(L98),IF(L98>100000000,"Grande","Média/Pequena"),"Sem dado") -> Média/Pequena | Y98: {=_xlfn.IFS(ISNUMBER(W98)=FALSE,"Sem dado",W98>0.075,"Excelente",W98>0.04,"Bom",W98>0,"Fraco",TRUE,"Prejuízo")} -> Fraco
A99: COOPERATIVA CENTRAL DE CREDITO DO ESPIRITO SANTO - SICOOB CENTRAL ES | B99: 32428294 | F99: b3C | G99: 2 | H99: 9 | I99: VITORIA | J99: ES | K99: 06/2026 | L99: 15057607 | M99: 124827 | N99: 4108110 | O99: 14252356 | P99: 282392 | Q99: 805251 | R99: 19394 | S99: 0 | T99: 0 | U99: =IFERROR(CHOOSE(G99,"Público","Privado Nacional","Privado Estrangeiro"),"n.d.") -> Privado Nacional | V99: =IF(AND(ISNUMBER(M99),ISNUMBER(L99)),IF(L99>0,M99/L99,"n.d."),"NI") -> 0.0082899627 | W99: =IF(AND(ISNUMBER(R99),ISNUMBER(Q99)),IF(Q99>0,R99/Q99,"n.d."),"NI") -> 0.024084416 | X99: =IF(ISNUMBER(L99),IF(L99>100000000,"Grande","Média/Pequena"),"Sem dado") -> Média/Pequena | Y99: {=_xlfn.IFS(ISNUMBER(W99)=FALSE,"Sem dado",W99>0.075,"Excelente",W99>0.04,"Bom",W99>0,"Fraco",TRUE,"Prejuízo")} -> Fraco
A100: BANCO MIZUHO DO BRASIL S.A. | B100: 61088183 | C100: MIZUHO - PRUDENCIAL | E100: C0080697 | F100: b1 | G100: 3 | H100: 8 | I100: SAO PAULO | J100: SP | K100: 06/2026 | L100: 15033171 | M100: 3270316 | N100: 5891940 | O100: 13699571 | P100: 12505201 | Q100: 1333599 | R100: 40301 | S100: 2 | T100: 0 | U100: =IFERROR(CHOOSE(G100,"Público","Privado Nacional","Privado Estrangeiro"),"n.d.") -> Privado Estrangeiro | V100: =IF(AND(ISNUMBER(M100),ISNUMBER(L100)),IF(L100>0,M100/L100,"n.d."),"NI") -> 0.21754 | W100: =IF(AND(ISNUMBER(R100),ISNUMBER(Q100)),IF(Q100>0,R100/Q100,"n.d."),"NI") -> 0.030219729 | X100: =IF(ISNUMBER(L100),IF(L100>100000000,"Grande","Média/Pequena"),"Sem dado") -> Média/Pequena | Y100: {=_xlfn.IFS(ISNUMBER(W100)=FALSE,"Sem dado",W100>0.075,"Excelente",W100>0.04,"Bom",W100>0,"Fraco",TRUE,"Prejuízo")} -> Fraco
A101: COOPERATIVA CENTRAL DE CRÉDITO - AILOS | B101: 5463212 | F101: b3C | G101: 2 | H101: 9 | I101: BLUMENAU | J101: SC | K101: 06/2026 | L101: 15013283 | M101: 867026 | N101: 10349258 | O101: 13955963 | P101: 2549732 | Q101: 1057321 | R101: 0 | S101: 0 | T101: 0 | U101: =IFERROR(CHOOSE(G101,"Público","Privado Nacional","Privado Estrangeiro"),"n.d.") -> Privado Nacional | V101: =IF(AND(ISNUMBER(M101),ISNUMBER(L101)),IF(L101>0,M101/L101,"n.d."),"NI") -> 0.057750593 | W101: =IF(AND(ISNUMBER(R101),ISNUMBER(Q101)),IF(Q101>0,R101/Q101,"n.d."),"NI") -> 0 | X101: =IF(ISNUMBER(L101),IF(L101>100000000,"Grande","Média/Pequena"),"Sem dado") -> Média/Pequena | Y101: {=_xlfn.IFS(ISNUMBER(W101)=FALSE,"Sem dado",W101>0.075,"Excelente",W101>0.04,"Bom",W101>0,"Fraco",TRUE,"Prejuízo")} -> Prejuízo
...

Sheet Totais_Fonte
A1: TOTAIS DA FONTE | IFData Junho 2026
A2: Fonte: IF.data, Banco Central do Brasil | Linhas de totais do arquivo IFData_Junho_2026.csv, por TCB, TC e TI | Valores monetários em R$ mil
A4: TCB | Tipo de Consolidado Bancário
A5: Código | B5: Descrição | C5: Linha | D5: Ativo Total (R$ mil) | E5: Carteira de Crédito (R$ mil) | F5: Títulos e Valores Mobiliários (R$ mil) | G5: Passivo Exigível (R$ mil) | H5: Captações (R$ mil) | I5: Patrimônio Líquido (R$ mil) | J5: Lucro Líquido (R$ mil) | K5: Número de Agências | L5: Postos de Atendimento
A6: b1 | B6: Banco Comercial, Banco Múltiplo com Carteira Comercial ou Caixa Econômica | C6: Total | D6: 14285826209 | E6: 5511754811 | F6: 3518123267 | G6: 13157506808 | H6: 11469908861 | I6: 1128319401 | J6: 80608469 | K6: 13386 | L6: 8067
A7: b1 | B7: Banco Comercial, Banco Múltiplo com Carteira Comercial ou Caixa Econômica | C7: % do sistema | D7: 0.7327 | E7: 0.7462 | F7: 0.795 | G7: 0.7537 | H7: 0.8111 | I7: 0.5529 | J7: 0.5252 | K7: 0.8971 | L7: 0.4476
A8: b2 | B8: Banco Múltiplo sem Carteira Comercial ou Banco de Investimento ou Banco de Câmbio | C8: Total | D8: 931799121 | E8: 430091463 | F8: 108094396 | G8: 650002745 | H8: 408314941 | I8: 281796376 | J8: 27442035 | K8: 108 | L8: 7
A9: b2 | B9: Banco Múltiplo sem Carteira Comercial ou Banco de Investimento ou Banco de Câmbio | C9: % do sistema | D9: 0.0478 | E9: 0.0582 | F9: 0.0244 | G9: 0.0372 | H9: 0.0289 | I9: 0.1381 | J9: 0.1788 | K9: 0.0072 | L9: 0.0004
A10: b3S | B10: Cooperativa de Crédito Singulares | C10: Total | D10: 992158871 | E10: 534336219 | F10: 185424312 | G10: 852161871 | H10: 676043108 | I10: 139996999 | J10: 8584458 | K10: 0 | L10: 9928
A11: b3S | B11: Cooperativa de Crédito Singulares | C11: % do sistema | D11: 0.0509 | E11: 0.0723 | F11: 0.0419 | G11: 0.0488 | H11: 0.0478 | I11: 0.0686 | J11: 0.0559 | K11: 0 | L11: 0.5509
A12: b3C | B12: Central e Confederação de Cooperativas de Crédito | C12: Total | D12: 254740242 | E12: 2759784 | F12: 98467430 | G12: 235183278 | H12: 26776352 | I12: 19556964 | J12: 677772 | K12: 0 | L12: 11
A13: b3C | B13: Central e Confederação de Cooperativas de Crédito | C13: % do sistema | D13: 0.0131 | E13: 0.0004 | F13: 0.0223 | G13: 0.0135 | H13: 0.0019 | I13: 0.0096 | J13: 0.0044 | K13: 0 | L13: 0.0006
A14: b4 | B14: Banco de Desenvolvimento | C14: Total | D14: 1121980384 | E14: 410286392 | F14: 219674537 | G14: 932408406 | H14: 697618375 | I14: 189571978 | J14: 11549205 | K14: 13 | L14: 0
A15: b4 | B15: Banco de Desenvolvimento | C15: % do sistema | D15: 0.0575 | E15: 0.0555 | F15: 0.0496 | G15: 0.0534 | H15: 0.0493 | I15: 0.0929 | J15: 0.0753 | K15: 0.0009 | L15: 0
A16: n1 | B16: Não Bancário de Crédito | C16: Total | D16: 734344385 | E16: 384887710 | F16: 143337276 | G16: 624999723 | H16: 522307010 | I16: 109344662 | J16: 9405391 | K16: 656 | L16: 0
A17: n1 | B17: Não Bancário de Crédito | C17: % do sistema | D17: 0.0377 | E17: 0.0521 | F17: 0.0324 | G17: 0.0358 | H17: 0.0369 | I17: 0.0536 | J17: 0.0613 | K17: 0.044 | L17: 0
... A21: n4 | B21: Instituições de Pagamento | C21: % do sistema | D21: 0.047 | E21: 0.0151 | F21: 0.0205 | G21: 0.0454 | H21: 0.0149 | I21: 0.0604 | J21: 0.0677 | K21: 0.0131 | L21: 0
A23: TC | Tipo de Controle
A24: Código | B24: Descrição | C24: Linha | D24: Ativo Total (R$ mil) | E24: Carteira de Crédito (R$ mil) | F24: Títulos e Valores Mobiliários (R$ mil) | G24: Passivo Exigível (R$ mil) | H24: Captações (R$ mil) | I24: Patrimônio Líquido (R$ mil) | J24: Lucro Líquido (R$ mil) | K24: Número de Agências | L24: Postos de Atendimento
A25: 1 | B25: Público | C25: Total | D25: 6391175338 | E25: 2999719019 | F25: 1569544736 | G25: 5837080041 | H25: 5003609740 | I25: 554095297 | J25: 29620371 | K25: 8291 | L25: 1527
A26: 1 | B26: Público | C26: % do sistema | D26: 0.3278 | E26: 0.4061 | F26: 0.3547 | G26: 0.3344 | H26: 0.3538 | I26: 0.2715 | J26: 0.193 | K26: 0.5556 | L26: 0.0847
A27: 2 | B27: Privado Nacional | C27: Total | D27: 9761967937 | E27: 3260463203 | F27: 2123358155 | G27: 8626395920 | H27: 6808625220 | I27: 1135572016 | J27: 96755434 | K27: 4917 | L27: 13628
A28: 2 | B28: Privado Nacional | C28: % do sistema | D28: 0.5007 | E28: 0.4414 | F28: 0.4798 | G28: 0.4941 | H28: 0.4815 | I28: 0.5565 | J28: 0.6305 | K28: 0.3295 | L28: 0.7561
A29: 3 | B29: Privado com Controle Estrangeiro | C29: Total | D29: 3344608879 | E29: 1125986266 | F29: 732464125 | G29: 2993619249 | H29: 2328706032 | I29: 350989630 | J29: 27091362 | K29: 1714 | L29: 2868
A30: 3 | B30: Privado com Controle Estrangeiro | C30: % do sistema | D30: 0.1715 | E30: 0.1524 | F30: 0.1655 | G30: 0.1715 | H30: 0.1647 | I30: 0.172 | J30: 0.1765 | K30: 0.1149 | L30: 0.1591
A32: TI | Tipo de Instituição
A33: Código | B33: Descrição | C33: Linha | D33: Ativo Total (R$ mil) | E33: Carteira de Crédito (R$ mil) | F33: Títulos e Valores Mobiliários (R$ mil) | G33: Passivo Exigível (R$ mil) | H33: Captações (R$ mil) | I33: Patrimônio Líquido (R$ mil) | J33: Lucro Líquido (R$ mil) | K33: Número de Agências | L33: Postos de Atendimento
A34: 1 | B34: Banco do Brasil - Banco Múltiplo | C34: Total | D34: 2461086914 | E34: 1065710905 | F34: 714731784 | G34: 2279753810 | H34: 1974660924 | I34: 181333105 | J34: 6216056 | K34: 3932 | L34: 309
A35: 1 | B35: Banco do Brasil - Banco Múltiplo | C35: % do sistema | D35: 0.1262 | E35: 0.1443 | F35: 0.1615 | G35: 0.1306 | H35: 0.1396 | I35: 0.0889 | J35: 0.0405 | K35: 0.2635 | L35: 0.0171
A36: 2 | B36: Banco Comercial | C36: Total | D36: 135301188 | E36: 77746731 | F36: 34673576 | G36: 121581570 | H36: 58147454 | I36: 13719618 | J36: 734878 | K36: 158 | L36: 1535
A37: 2 | B37: Banco Comercial | C37: % do sistema | D37: 0.0069 | E37: 0.0105 | F37: 0.0078 | G37: 0.007 | H37: 0.0041 | I37: 0.0067 | J37: 0.0048 | K37: 0.0106 | L37: 0.0852
A38: 3 | B38: Banco Comercial Cooperativo | C38: Total | D38: 0 | E38: 0 | F38: 0 | G38: 0 | H38: 0 | I38: 0 | J38: 0 | K38: 0 | L38: 0
A39: 3 | B39: Banco Comercial Cooperativo | C39: % do sistema | D39: 0 | E39: 0 | F39: 0 | G39: 0 | H39: 0 | I39: 0 | J39: 0 | K39: 0 | L39: 0
A40: 4 | B40: BNDES | C40: Total | D40: 1073403746 | E40: 375703869 | F40: 209161034 | G40: 892700475 | H40: 661452493 | I40: 180703272 | J40: 11153448 | K40: 5 | L40: 0
A41: 4 | B41: BNDES | C41: % do sistema | D41: 0.0551 | E41: 0.0509 | F41: 0.0473 | G41: 0.0511 | H41: 0.0468 | I41: 0.0886 | J41: 0.0727 | K41: 0.0003 | L41: 0
A42: 5 | B42: Banco de Desenvolvimento | C42: Total | D42: 48576638 | E42: 34582523 | F42: 10513503 | G42: 39707932 | H42: 36165882 | I42: 8868706 | J42: 395757 | K42: 8 | L42: 0
A43: 5 | B43: Banco de Desenvolvimento | C43: % do sistema | D43: 0.0025 | E43: 0.0047 | F43: 0.0024 | G43: 0.0023 | H43: 0.0026 | I43: 0.0043 | J43: 0.0026 | K43: 0.0005 | L43: 0
A44: 6 | B44: Caixa Econômica Federal | C44: Total | D44: 2368147225 | E44: 1362330927 | F44: 452416774 | G44: 2249779433 | H44: 2063880327 | I44: 118367792 | J44: 6585794 | K44: 3000 | L44: 868
A45: 6 | B45: Caixa Econômica Federal | C45: % do sistema | D45: 0.1215 | E45: 0.1844 | F45: 0.1022 | G45: 0.1289 | H45: 0.146 | I45: 0.058 | J45: 0.0429 | K45: 0.201 | L45: 0.0482
... A85: 44 | B85: Sociedades de Empréstimo entre Pessoas | C85: % do sistema | D85: 0 | E85: 0 | F85: 0 | G85: 0 | H85: 0 | I85: 0 | J85: 0 | K85: 0.0016 | L85: 0

Sheet Dicionário
A1: DICIONÁRIO DE DADOS | IFData Junho 2026
A2: Significado de cada coluna da aba Base_IFData e dos códigos de classificação (TCB, TC e TI). Valores monetários em R$ mil.
A4: COLUNAS DA BASE
A5: Col. | B5: Coluna | C5: Nome completo | D5: Tipo | E5: O que significa na prática
A6: A | B6: Instituição | C6: Nome da instituição financeira | D6: Texto | E6: Razão social registrada no Banco Central. Cada linha é uma instituição individual: holdings e controladas aparecem em linhas separadas.
A7: B | B7: Código | C7: Código de identificação da instituição | D7: Número | E7: Raiz do CNPJ da instituição, sem zeros à esquerda (o Banco do Brasil aparece como 0). Único por linha.
A8: C | B8: Conglomerado Prudencial (Nome) | C8: Nome do conglomerado prudencial | D8: Texto | E8: Grupo prudencial ao qual a instituição pertence. Vazio quando a instituição não integra conglomerado prudencial. Use para agregar instituições do mesmo grupo.
A9: D | B9: Conglomerado Financeiro (Cód.) | C9: Código do conglomerado financeiro | D9: Código | E9: Identificador do conglomerado financeiro (formato C0000000). Vazio quando a instituição não integra conglomerado financeiro.
A10: E | B10: Conglomerado Prudencial (Cód.) | C10: Código do conglomerado prudencial | D10: Código | E10: Identificador do conglomerado prudencial (formato C0000000), correspondente ao nome da coluna C.
A11: F | B11: TCB | C11: Tipo de Consolidado Bancário | D11: Código | E11: Classifica o tipo de instituição. Ver tabela de códigos TCB abaixo.
A12: G | B12: TC | C12: Tipo de Controle | D12: Código | E12: 1 = Público; 2 = Privado Nacional; 3 = Privado com Controle Estrangeiro. Ver tabela abaixo.
A13: H | B13: TI | C13: Tipo de Instituição | D13: Código | E13: Classificação detalhada do tipo de instituição. Ver tabela de códigos TI abaixo.
A14: I | B14: Cidade | C14: Município da sede | D14: Texto | E14: Cidade onde a instituição tem sua sede registrada no Banco Central.
A15: J | B15: UF | C15: Unidade da Federação da sede | D15: Texto | E15: Estado da sede da instituição.
A16: K | B16: Data | C16: Data-base dos dados | D16: Texto | E16: Mês e ano de referência. 06/2026 = posição de junho de 2026.
... A28: W | B28: ROE do semestre | C28: Retorno sobre o Patrimônio Líquido no semestre | D28: Fórmula | E28: Calculado: Lucro Líquido ÷ Patrimônio Líquido. Mede o lucro gerado por real de capital próprio no semestre (não anualizado). Retorna NI quando não informado e n.d. quando o Patrimônio Líquido é zero ou negativo.
A30: NOTAS DE LEITURA
A31: 1 | B31: Unidade: valores monetários em R$ mil. R$ 1 bilhão equivale a 1.000.000 nesta unidade.
A32: 2 | B32: ="NI = não informado na fonte. " & COUNTIF(Base_IFData_Original!$L$5:$L$1626,"NI") & " instituições têm NI nas colunas de valores monetários: entram nas contagens, mas ficam fora de somas, médias e medianas." -> NI = não informado na fonte. 51 instituições têm NI nas colunas de valores monetários: entram nas contagens, mas ficam fora de somas, médias e medianas.
A33: 3 | B33: Instituições individuais: quando uma holding e suas controladas estão na base, seus ativos aparecem em linhas separadas e a soma geral pode conter sobreposição. Para análise por grupo, agregue pelo Conglomerado Prudencial.
A34: 4 | B34: Ordenação: a base está ordenada por Ativo Total decrescente, com as instituições de valores NI ao final.
A35: 5 | B35: Totais da fonte: as linhas de totais do arquivo original (por TCB, TC e TI) ficam na aba Totais_Fonte, conferidas contra as somas da base.
A37: CÓDIGOS TCB | Tipo de Consolidado Bancário (coluna F)
B38: Código | C38: Descrição | D38: Instituições (nº) | E38: Maior instituição por Ativo Total
B39: b1 | C39: Banco Comercial, Banco Múltiplo com Carteira Comercial ou Caixa Econômica | D39: =COUNTIFS(Base_IFData_Original!$F$5:$F$1626,B39) -> 116 | E39: =IF(D39=0,"sem instituições na base",INDEX(Base_IFData_Original!$A$5:$A$1626,MATCH(1,INDEX((Base_IFData_Original!$F$5:$F$1626=B39)*(Base_IFData_Original!$L$5:$L$1626=_xlfn.MAXIFS(Base_IFData_Original!$L$5:$L$1626,Base_IFData_Original!$F$5:$F$1626,B39)),0),0))) -> BANCO DO BRASIL S.A.
B40: b2 | C40: Banco Múltiplo sem Carteira Comercial ou Banco de Investimento ou Banco de Câmbio | D40: =COUNTIFS(Base_IFData_Original!$F$5:$F$1626,B40) -> 50 | E40: =IF(D40=0,"sem instituições na base",INDEX(Base_IFData_Original!$A$5:$A$1626,MATCH(1,INDEX((Base_IFData_Original!$F$5:$F$1626=B40)*(Base_IFData_Original!$L$5:$L$1626=_xlfn.MAXIFS(Base_IFData_Original!$L$5:$L$1626,Base_IFData_Original!$F$5:$F$1626,B40)),0),0))) -> ITAÚ UNIBANCO HOLDING S.A.
B41: b3S | C41: Cooperativa de Crédito Singular | D41: =COUNTIFS(Base_IFData_Original!$F$5:$F$1626,B41) -> 729 | E41: =IF(D41=0,"sem instituições na base",INDEX(Base_IFData_Original!$A$5:$A$1626,MATCH(1,INDEX((Base_IFData_Original!$F$5:$F$1626=B41)*(Base_IFData_Original!$L$5:$L$1626=_xlfn.MAXIFS(Base_IFData_Original!$L$5:$L$1626,Base_IFData_Original!$F$5:$F$1626,B41)),0),0))) -> COOPERATIVA DE CREDITO CREDICITRUS
B42: b3C | C42: Central e Confederação de Cooperativas de Crédito | D42: =COUNTIFS(Base_IFData_Original!$F$5:$F$1626,B42) -> 27 | E42: =IF(D42=0,"sem instituições na base",INDEX(Base_IFData_Original!$A$5:$A$1626,MATCH(1,INDEX((Base_IFData_Original!$F$5:$F$1626=B42)*(Base_IFData_Original!$L$5:$L$1626=_xlfn.MAXIFS(Base_IFData_Original!$L$5:$L$1626,Base_IFData_Original!$F$5:$F$1626,B42)),0),0))) -> COOPERATIVA CENTRAL DE CRÉDITO DE MINAS GERAIS LTDA. - SICOOB CENTRAL CREDIMINAS
B43: b4 | C43: Banco de Desenvolvimento | D43: =COUNTIFS(Base_IFData_Original!$F$5:$F$1626,B43) -> 4 | E43: =IF(D43=0,"sem instituições na base",INDEX(Base_IFData_Original!$A$5:$A$1626,MATCH(1,INDEX((Base_IFData_Original!$F$5:$F$1626=B43)*(Base_IFData_Original!$L$5:$L$1626=_xlfn.MAXIFS(Base_IFData_Original!$L$5:$L$1626,Base_IFData_Original!$F$5:$F$1626,B43)),0),0))) -> BANCO NACIONAL DE DESENVOLVIMENTO ECONOMICO E SOCIAL
B44: n1 | C44: Não Bancário de Crédito | D44: =COUNTIFS(Base_IFData_Original!$F$5:$F$1626,B44) -> 290 | E44: =IF(D44=0,"sem instituições na base",INDEX(Base_IFData_Original!$A$5:$A$1626,MATCH(1,INDEX((Base_IFData_Original!$F$5:$F$1626=B44)*(Base_IFData_Original!$L$5:$L$1626=_xlfn.MAXIFS(Base_IFData_Original!$L$5:$L$1626,Base_IFData_Original!$F$5:$F$1626,B44)),0),0))) -> NU FINANCEIRA S.A. - SOCIEDADE DE CRÉDITO, FINANCIAMENTO E INVESTIMENTO
B45: n2 | C45: Não Bancário de Mercado de Capitais | D45: =COUNTIFS(Base_IFData_Original!$F$5:$F$1626,B45) -> 210 | E45: =IF(D45=0,"sem instituições na base",INDEX(Base_IFData_Original!$A$5:$A$1626,MATCH(1,INDEX((Base_IFData_Original!$F$5:$F$1626=B45)*(Base_IFData_Original!$L$5:$L$1626=_xlfn.MAXIFS(Base_IFData_Original!$L$5:$L$1626,Base_IFData_Original!$F$5:$F$1626,B45)),0),0))) -> XP INVESTIMENTOS CORRETORA DE CÂMBIO,TÍTULOS E VALORES MOBILIÁRIOS S/A
B46: n4 | C46: Instituições de Pagamento | D46: =COUNTIFS(Base_IFData_Original!$F$5:$F$1626,B46) -> 196 | E46: =IF(D46=0,"sem instituições na base",INDEX(Base_IFData_Original!$A$5:$A$1626,MATCH(1,INDEX((Base_IFData_Original!$F$5:$F$1626=B46)*(Base_IFData_Original!$L$5:$L$1626=_xlfn.MAXIFS(Base_IFData_Original!$L$5:$L$1626,Base_IFData_Original!$F$5:$F$1626,B46)),0),0))) -> REDECARD INSTITUIÇÃO DE PAGAMENTO S.A.
A48: CÓDIGOS TC | Tipo de Controle (coluna G)
B49: Código | C49: Descrição | D49: Instituições (nº) | E49: Maior instituição por Ativo Total
B50: 1 | C50: Público | D50: =COUNTIFS(Base_IFData_Original!$G$5:$G$1626,B50) -> 39 | E50: =IF(D50=0,"sem instituições na base",INDEX(Base_IFData_Original!$A$5:$A$1626,MATCH(1,INDEX((Base_IFData_Original!$G$5:$G$1626=B50)*(Base_IFData_Original!$L$5:$L$1626=_xlfn.MAXIFS(Base_IFData_Original!$L$5:$L$1626,Base_IFData_Original!$G$5:$G$1626,B50)),0),0))) -> BANCO DO BRASIL S.A.
B51: 2 | C51: Privado Nacional | D51: =COUNTIFS(Base_IFData_Original!$G$5:$G$1626,B51) -> 1353 | E51: =IF(D51=0,"sem instituições na base",INDEX(Base_IFData_Original!$A$5:$A$1626,MATCH(1,INDEX((Base_IFData_Original!$G$5:$G$1626=B51)*(Base_IFData_Original!$L$5:$L$1626=_xlfn.MAXIFS(Base_IFData_Original!$L$5:$L$1626,Base_IFData_Original!$G$5:$G$1626,B51)),0),0))) -> ITAÚ UNIBANCO S.A.
B52: 3 | C52: Privado com Controle Estrangeiro | D52: =COUNTIFS(Base_IFData_Original!$G$5:$G$1626,B52) -> 230 | E52: =IF(D52=0,"sem instituições na base",INDEX(Base_IFData_Original!$A$5:$A$1626,MATCH(1,INDEX((Base_IFData_Original!$G$5:$G$1626=B52)*(Base_IFData_Original!$L$5:$L$1626=_xlfn.MAXIFS(Base_IFData_Original!$L$5:$L$1626,Base_IFData_Original!$G$5:$G$1626,B52)),0),0))) -> BANCO SANTANDER (BRASIL) S.A.
A54: CÓDIGOS TI | Tipo de Instituição (coluna H)
B55: Código | C55: Descrição | D55: Instituições (nº) | E55: Maior instituição por Ativo Total
B56: 1 | C56: Banco do Brasil - Banco Múltiplo | D56: =COUNTIFS(Base_IFData_Original!$H$5:$H$1626,B56) -> 1 | E56: =IF(D56=0,"sem instituições na base",INDEX(Base_IFData_Original!$A$5:$A$1626,MATCH(1,INDEX((Base_IFData_Original!$H$5:$H$1626=B56)*(Base_IFData_Original!$L$5:$L$1626=_xlfn.MAXIFS(Base_IFData_Original!$L$5:$L$1626,Base_IFData_Original!$H$5:$H$1626,B56)),0),0))) -> BANCO DO BRASIL S.A.
B57: 2 | C57: Banco Comercial | D57: =COUNTIFS(Base_IFData_Original!$H$5:$H$1626,B57) -> 14 | E57: =IF(D57=0,"sem instituições na base",INDEX(Base_IFData_Original!$A$5:$A$1626,MATCH(1,INDEX((Base_IFData_Original!$H$5:$H$1626=B57)*(Base_IFData_Original!$L$5:$L$1626=_xlfn.MAXIFS(Base_IFData_Original!$L$5:$L$1626,Base_IFData_Original!$H$5:$H$1626,B57)),0),0))) -> BANCO DA AMAZONIA S.A.
B58: 3 | C58: Banco Comercial Cooperativo | D58: =COUNTIFS(Base_IFData_Original!$H$5:$H$1626,B58) -> 0 | E58: =IF(D58=0,"sem instituições na base",INDEX(Base_IFData_Original!$A$5:$A$1626,MATCH(1,INDEX((Base_IFData_Original!$H$5:$H$1626=B58)*(Base_IFData_Original!$L$5:$L$1626=_xlfn.MAXIFS(Base_IFData_Original!$L$5:$L$1626,Base_IFData_Original!$H$5:$H$1626,B58)),0),0))) -> sem instituições na base
B59: 4 | C59: BNDES | D59: =COUNTIFS(Base_IFData_Original!$H$5:$H$1626,B59) -> 1 | E59: =IF(D59=0,"sem instituições na base",INDEX(Base_IFData_Original!$A$5:$A$1626,MATCH(1,INDEX((Base_IFData_Original!$H$5:$H$1626=B59)*(Base_IFData_Original!$L$5:$L$1626=_xlfn.MAXIFS(Base_IFData_Original!$L$5:$L$1626,Base_IFData_Original!$H$5:$H$1626,B59)),0),0))) -> BANCO NACIONAL DE DESENVOLVIMENTO ECONOMICO E SOCIAL
B60: 5 | C60: Banco de Desenvolvimento | D60: =COUNTIFS(Base_IFData_Original!$H$5:$H$1626,B60) -> 3 | E60: =IF(D60=0,"sem instituições na base",INDEX(Base_IFData_Original!$A$5:$A$1626,MATCH(1,INDEX((Base_IFData_Original!$H$5:$H$1626=B60)*(Base_IFData_Original!$L$5:$L$1626=_xlfn.MAXIFS(Base_IFData_Original!$L$5:$L$1626,Base_IFData_Original!$H$5:$H$1626,B60)),0),0))) -> BANCO REGIONAL DE DESENVOLVIMENTO DO EXTREMO SUL
B61: 6 | C61: Caixa Econômica Federal | D61: =COUNTIFS(Base_IFData_Original!$H$5:$H$1626,B61) -> 1 | E61: =IF(D61=0,"sem instituições na base",INDEX(Base_IFData_Original!$A$5:$A$1626,MATCH(1,INDEX((Base_IFData_Original!$H$5:$H$1626=B61)*(Base_IFData_Original!$L$5:$L$1626=_xlfn.MAXIFS(Base_IFData_Original!$L$5:$L$1626,Base_IFData_Original!$H$5:$H$1626,B61)),0),0))) -> CAIXA ECONOMICA FEDERAL
B62: 7 | C62: Caixa Econômica Estadual | D62: =COUNTIFS(Base_IFData_Original!$H$5:$H$1626,B62) -> 0 | E62: =IF(D62=0,"sem instituições na base",INDEX(Base_IFData_Original!$A$5:$A$1626,MATCH(1,INDEX((Base_IFData_Original!$H$5:$H$1626=B62)*(Base_IFData_Original!$L$5:$L$1626=_xlfn.MAXIFS(Base_IFData_Original!$L$5:$L$1626,Base_IFData_Original!$H$5:$H$1626,B62)),0),0))) -> sem instituições na base
B63: 8 | C63: Banco Múltiplo | D63: =COUNTIFS(Base_IFData_Original!$H$5:$H$1626,B63) -> 128 | E63: =IF(D63=0,"sem instituições na base",INDEX(Base_IFData_Original!$A$5:$A$1626,MATCH(1,INDEX((Base_IFData_Original!$H$5:$H$1626=B63)*(Base_IFData_Original!$L$5:$L$1626=_xlfn.MAXIFS(Base_IFData_Original!$L$5:$L$1626,Base_IFData_Original!$H$5:$H$1626,B63)),0),0))) -> ITAÚ UNIBANCO S.A.
B64: 9 | C64: Cooperativa de Crédito | D64: =COUNTIFS(Base_IFData_Original!$H$5:$H$1626,B64) -> 756 | E64: =IF(D64=0,"sem instituições na base",INDEX(Base_IFData_Original!$A$5:$A$1626,MATCH(1,INDEX((Base_IFData_Original!$H$5:$H$1626=B64)*(Base_IFData_Original!$L$5:$L$1626=_xlfn.MAXIFS(Base_IFData_Original!$L$5:$L$1626,Base_IFData_Original!$H$5:$H$1626,B64)),0),0))) -> COOPERATIVA CENTRAL DE CRÉDITO DE MINAS GERAIS LTDA. - SICOOB CENTRAL CREDIMINAS
B65: 10 | C65: Sociedade de Crédito ao Microempreendedor | D65: =COUNTIFS(Base_IFData_Original!$H$5:$H$1626,B65) -> 22 | E65: =IF(D65=0,"sem instituições na base",INDEX(Base_IFData_Original!$A$5:$A$1626,MATCH(1,INDEX((Base_IFData_Original!$H$5:$H$1626=B65)*(Base_IFData_Original!$L$5:$L$1626=_xlfn.MAXIFS(Base_IFData_Original!$L$5:$L$1626,Base_IFData_Original!$H$5:$H$1626,B65)),0),0))) -> BMP SOCIEDADE DE CRÉDITO AO MICROEMPREENDEDOR E A EMPRESA DE PEQUENO PORTE LTDA.
B66: 11 | C66: Banco Múltiplo Cooperativo | D66: =COUNTIFS(Base_IFData_Original!$H$5:$H$1626,B66) -> 2 | E66: =IF(D66=0,"sem instituições na base",INDEX(Base_IFData_Original!$A$5:$A$1626,MATCH(1,INDEX((Base_IFData_Original!$H$5:$H$1626=B66)*(Base_IFData_Original!$L$5:$L$1626=_xlfn.MAXIFS(Base_IFData_Original!$L$5:$L$1626,Base_IFData_Original!$H$5:$H$1626,B66)),0),0))) -> BANCO COOPERATIVO SICREDI S.A.
B67: 13 | C67: Banco de Investimento | D67: =COUNTIFS(Base_IFData_Original!$H$5:$H$1626,B67) -> 12 | E67: =IF(D67=0,"sem instituições na base",INDEX(Base_IFData_Original!$A$5:$A$1626,MATCH(1,INDEX((Base_IFData_Original!$H$5:$H$1626=B67)*(Base_IFData_Original!$L$5:$L$1626=_xlfn.MAXIFS(Base_IFData_Original!$L$5:$L$1626,Base_IFData_Original!$H$5:$H$1626,B67)),0),0))) -> BR PARTNERS BANCO DE INVESTIMENTO S.A.
... B81: 44 | C81: Sociedades de Empréstimo entre Pessoas | D81: =COUNTIFS(Base_IFData_Original!$H$5:$H$1626,B81) -> 12 | E81: =IF(D81=0,"sem instituições na base",INDEX(Base_IFData_Original!$A$5:$A$1626,MATCH(1,INDEX((Base_IFData_Original!$H$5:$H$1626=B81)*(Base_IFData_Original!$L$5:$L$1626=_xlfn.MAXIFS(Base_IFData_Original!$L$5:$L$1626,Base_IFData_Original!$H$5:$H$1626,B81)),0),0))) -> MOVA SOCIEDADE DE EMPRÉSTIMO ENTRE PESSOAS S.A.

Sheet Análises 1
A1: ANÁLISES 1 | IFData Junho 2026
A3: MEDIDAS DE RESUMO
A4: Nº | B4: O que fazer | C4: Fórmula aplicada | D4: Resultado | E4: Para reflexão
A5: 1 | B5: Qual é o ATIVO TOTAL MÉDIO das instituições da base? → Coluna L da Base_IFData | C5: =MÉDIA(Base_IFData!L5:L1626) | D5: =AVERAGE(Base_IFData!L5:L1626) -> 12411045 | E5: Compare com a mediana (exercício 2). O que a diferença entre as duas diz sobre a distribuição?
A6: 2 | B6: Qual é a MEDIANA do Ativo Total? → A mediana é mais representativa que a média neste caso? Por quê? | C6: =MED(Base_IFData!L5:L1626) | D6: =MEDIAN(Base_IFData!L5:L1626) -> 293113 | E6: Se a média for muito maior que a mediana, há concentração nos grandes bancos.
A7: 3 | B7: Qual é o MAIOR Ativo Total? Qual é o MENOR? → Use MÁXIMO e MÍNIMO | C7: Maior: =MÁXIMO(Base_IFData!L5:L1626) | Menor: =MÍNIMO(Base_IFData!L5:L1626) | D7: ="Maior: "&FIXED(MAX(Base_IFData!L5:L1626),0)&" | Menor: "&FIXED(MIN(Base_IFData!L5:L1626),0) -> Maior: 2.461.086.914 | Menor: 365 | E7: A diferença entre o maior e o menor ativo mostra a amplitude do setor. Quantas vezes o maior supera o menor?
A8: 4 | B8: Qual é o QUARTIL 1 (Q1) e o QUARTIL 3 (Q3) da Carteira de Crédito? → Coluna M | C8: Q1: =QUARTIL(Base_IFData!M5:M1626;1) | Q2: =QUARTIL(Base_IFData!M5:M1626;2) | Q3: =QUARTIL(Base_IFData!M5:M1626;3) | D8: ="Q1: "&FIXED(QUARTILE(Base_IFData!M5:M1626,1),0)&" | Q2: "&FIXED(QUARTILE(Base_IFData!M5:M1626,2),0)&" | Q3: "&FIXED(QUARTILE(Base_IFData!M5:M1626,3),0) -> Q1: 0 | Q2: 32.400 | Q3: 537.952 | E8: Q1 e Q3 delimitam os 50% centrais da distribuição. Interprete o valor de Q1: o que ele revela sobre a carteira de crédito do sistema?
A9: 5 | B9: Qual é o PERCENTIL 90 do Patrimônio Líquido? → Coluna Q | C9: =PERCENTIL(Base_IFData!Q5:Q1626;0,9) | D9: =PERCENTILE(Base_IFData!Q5:Q1626,0.9) -> 1114820 | E9: 90% das instituições têm PL abaixo deste valor. Só 10% estão acima.
A10: 6 | B10: Quantas agências existem no total? Qual é a média por instituição? → Coluna S | C10: Soma: =SOMA(Base_IFData!S5:S1626) | Média: =MÉDIA(Base_IFData!S5:S1626) | D10: ="Soma: "&FIXED(SUM(Base_IFData!S5:S1626),0)&" | Média: "&FIXED(AVERAGE(Base_IFData!S5:S1626),2) -> Soma: 14.922 | Média: 9,20 | E10: Compare com a mediana de agências. A distribuição é concentrada em poucas instituições?
A12: CONTAGEM E SOMA CONDICIONAL
A13: Nº | B13: O que fazer | C13: Fórmula aplicada | D13: Resultado | E13: Para reflexão
A14: 7 | B14: Quantas instituições são de CONTROLE PÚBLICO (TC = 1)? → Coluna G da Base_IFData | C14: =CONT.SE(Base_IFData!G5:G1626; "= 1") | D14: =COUNTIF(Base_IFData!G5:G1626, "= 1") -> 39 | E14: Compare a quantidade de instituições públicas com a participação delas no ativo total (exercício 9).
A15: 8 | B15: Quantas instituições são do TCB b1 (bancos comerciais, bancos múltiplos com carteira comercial e Caixa Econômica)? → Coluna F | C15: =CONT.SE(Base_IFData!F5:F1626; "b1") | D15: =COUNTIF(Base_IFData!F5:F1626, "b1") -> 116 | E15: O grupo b1 reúne os grandes bancos de varejo. Que parcela do ativo total ele representa?
A16: 9 | B16: Qual é a SOMA do Ativo Total das instituições PÚBLICAS (TC = 1)? → Use SOMASE | C16: =SOMASE(Base_IFData!G5:G1626;1;Base_IFData!L5:L1626) | D16: =SUMIF(Base_IFData!G5:G1626,1,Base_IFData!L5:L1626) -> 6391175337 | E16: Compare com a soma total. Qual percentual do ativo é público?
A17: 10 | B17: Qual é a MÉDIA da Carteira de Crédito das instituições PRIVADAS NACIONAIS (TC = 2)? → Use MÉDIASE | C17: =MÉDIASE(Base_IFData!G5:G1626;2;Base_IFData!M5:M1626) | D17: =AVERAGEIF(Base_IFData!G5:G1626,2,Base_IFData!M5:M1626) -> 2487004.7 | E17: Compare com a média das públicas (TC = 1) e das estrangeiras (TC = 3).
A18: 11 | B18: Quantas instituições com sede em SP têm Lucro Líquido POSITIVO? → Use CONT.SES com duas condições (colunas J e R) | C18: =CONT.SES(Base_IFData!J5:J1626; "SP"; Base_IFData!R5:R1626; ">0") | D18: =COUNTIFS(Base_IFData!J5:J1626,"SP",Base_IFData!R5:R1626,">0") -> 495 | E18: Qual percentual das instituições da base tem sede em SP? E qual percentual delas tem lucro positivo?
A19: 12 | B19: Qual é a SOMA do Lucro Líquido das instituições de CONTROLE ESTRANGEIRO (TC = 3)? → Use SOMASE | C19: =SOMASE(Base_IFData!G5:G1626;3;Base_IFData!R5:R1626) | D19: =SUMIF(Base_IFData!G5:G1626,3,Base_IFData!R5:R1626) -> 27091361 | E19: Como o lucro das estrangeiras se compara com o das públicas e o das privadas nacionais?
A21: CLASSIFICAÇÃO E LÓGICA
A22: Nº | B22: O que fazer | C22: Fórmula aplicada | D22: Resultado | E22: Para reflexão
A23: 13 | B23: Em uma coluna auxiliar, classifique cada instituição: 'Grande' se o Ativo Total for maior que 100 bilhões, senão 'Média/Pequena'. → Use SE (100 bi = 100.000.000 em R$ mil). Trate o NI com ÉNÚM: no Excel, texto é maior que qualquer número em comparações. | C23: Base_IFData!X5 (copiada até X1626): =SE(ÉNÚM(L5); SE(L5>100000000; "Grande"; "Média/Pequena"); "Sem dado") | D23: =COUNTIF(Base_IFData!X5:X1626,"Grande") -> 24 | E23: Quantas são 'Grandes'? Esse grupo representa qual percentual do ativo total?
A24: 14 | B24: Classifique o ROE do semestre (coluna W): 'Excelente' se > 7,5%, 'Bom' se > 4%, 'Fraco' se > 0%, 'Prejuízo' se ≤ 0%. Valores NI e n.d. ficam como 'Sem dado'. → Use SES. Os cortes são os de referência anual (15% e 8%) divididos por dois, pois o ROE da base é semestral. | C24: Base_IFData!Y5 (copiada até Y1626): =SES(ÉNÚM(W5)=FALSO; "Sem dado"; W5>7,5%; "Excelente"; W5>4%; "Bom"; W5>0%; "Fraco"; VERDADEIRO; "Prejuízo") | D24: =COUNTIF(Base_IFData!Y5:Y1626,"Excelente") -> 458 | E24: Quantas instituições têm ROE 'Excelente'? São as que você esperaria?
A25: 15 | B25: Use PROCV para buscar o Ativo Total da instituição cujo nome começa com NU FINANCEIRA. → A chave é o nome na coluna A da Base_IFData. Use o curinga *: 'NU FINANCEIRA*' | C25: =PROCV("NU FINANCEIRA*";Base_IFData!A5:L1626;12;FALSO) | D25: =VLOOKUP("NU FINANCEIRA*",Base_IFData!A5:L1626,12,FALSE) -> 267624695 | E25: Agora busque o Patrimônio Líquido e o Lucro Líquido da mesma instituição. Por que o PROCV precisa de correspondência exata (quarto argumento FALSO)?

Sheet Análises 2
A1: ANÁLISES 2 | IFData Junho 2026
A3: ANÁLISE COMPARATIVA POR TIPO DE CONSOLIDADO BANCÁRIO (TCB)
A4: Nº | B4: O que fazer | C4: Fórmula aplicada | D4: Resultado | E4: Para reflexão
A5: 1 | B5: Monte uma tabela comparativa: para cada TCB (b1, b2, b3S, b3C, b4, n1, n2 e n4), calcule: a) Quantidade de instituições b) Soma do Ativo Total c) Média da Carteira de Crédito d) Soma do Lucro Líquido → Use CONT.SE, SOMASE e MÉDIASE para cada TCB | C5: Tabela completa na aba Tabela_TCB (A4:H13). Fórmulas da linha 5, copiadas até a linha 12: a) =CONT.SE(Base_IFData!$F$5:$F$1626; $A5) b) =SOMASE(Base_IFData!$F$5:$F$1626; $A5; Base_IFData!$L$5:$L$1626) c) =MÉDIASE(Base_IFData!$F$5:$F$1626; $A5; Base_IFData!$M$5:$M$1626) d) =SOMASE(Base_IFData!$F$5:$F$1626; $A5; Base_IFData!$R$5:$R$1626) | D5: ="Total: "&FIXED(Tabela_TCB!B13,0)&" instituições. Maior ativo: "&INDEX(Tabela_TCB!A5:A12,MATCH(MAX(Tabela_TCB!C5:C12),Tabela_TCB!C5:C12,0))&" ("&FIXED(MAX(Tabela_TCB!G5:G12)*100,1)&"%"&" do ativo). Maior lucro: "&INDEX(Tabela_TCB!A5:A12,MATCH(MAX(Tabela_TCB!E5:E12),Tabela_TCB!E5:E12,0))&" ("&FIXED(MAX(Tabela_TCB!H5:H12)*100,1)&"%"&" do lucro). Tabela completa na aba Tabela_TCB." -> Total: 1.622 instituições. Maior ativo: b1 (73,3% do ativo). Maior lucro: b1 (52,5% do lucro). Tabela completa na aba Tabela_TCB. | E5: Qual TCB concentra mais ativos? E mais lucro? A distribuição é equilibrada?
A6: 2 | B6: Compare o ROE do semestre por tipo de controle: a) Média simples dos ROEs: MÉDIASE na coluna W (TC = 1, 2 e 3) b) ROE agregado: SOMASE do Lucro Líquido ÷ SOMASE do Patrimônio Líquido (colunas R e Q) → Compare as duas medidas | C6: Calc_Intermediário!D12 (copiada até D14), item (a): =MÉDIASE(Base_IFData!$G$5:$G$1626; $A12; Base_IFData!$W$5:$W$1626) Calc_Intermediário!G12 (copiada até G14), item (b): =E12/F12, com E12: =SOMASE(Base_IFData!$G$5:$G$1626; $A12; Base_IFData!$R$5:$R$1626) F12: =SOMASE(Base_IFData!$G$5:$G$1626; $A12; Base_IFData!$Q$5:$Q$1626) A12:A14 = 1, 2 e 3 (TC). | D6: ="Média simples dos ROEs: Público "&FIXED(Cálculos_Apoio!D11*100,1)&"%"&"; Privado Nacional "&FIXED(Cálculos_Apoio!D12*100,1)&"%"&"; Privado Estrangeiro "&FIXED(Cálculos_Apoio!D13*100,1)&"%"&"."&CHAR(10)&"ROE agregado (Lucro ÷ PL): Público "&FIXED(Cálculos_Apoio!G11*100,1)&"%"&"; Privado Nacional "&FIXED(Cálculos_Apoio!G12*100,1)&"%"&"; Privado Estrangeiro "&FIXED(Cálculos_Apoio!G13*100,1)&"%"&"."&CHAR(10)&"Mais rentável pela média simples: "&INDEX(Cálculos_Apoio!B11:B13,MATCH(MAX(Cálculos_Apoio!D11:D13),Cálculos_Apoio!D11:D13,0))&". Pelo ROE agregado: "&INDEX(Cálculos_Apoio!B11:B13,MATCH(MAX(Cálculos_Apoio!G11:G13),Cálculos_Apoio!G11:G13,0))&"." -> Média simples dos ROEs: Público 8,0%; Privado Nacional 1,4%; Privado Estrangeiro -3,4%. ROE agregado (Lucro ÷ PL): Público 5,3%; Privado Nacional 8,5%; Privado Estrangeiro 7,7%. Mais rentável pela média simples: Público. Pelo ROE agregado: Privado Nacional. | E6: As duas medidas apontam o mesmo tipo de controle como o mais rentável? O que explica a diferença?
A7: 3 | B7: Calcule a participação de cada tipo de controle no Ativo Total: % Público = Soma do Ativo Público ÷ Soma do Ativo Total → Use SOMASE e operações simples | C7: Calc_Intermediário!C19 (copiada até C21): =SOMASE(Base_IFData!$G$5:$G$1626; $A19; Base_IFData!$L$5:$L$1626) Calc_Intermediário!D19 (copiada até D21): =C19/C$22 (C22 = soma dos três tipos de controle; a % Público é D19). | D7: ="Público: "&FIXED(Cálculos_Apoio!D18*100,1)&"%"&" do ativo ("&FIXED(Cálculos_Apoio!E18,0)&" instituições, "&FIXED(Cálculos_Apoio!F18*100,1)&"%"&" do total)."&CHAR(10)&"Privado Nacional: "&FIXED(Cálculos_Apoio!D19*100,1)&"%"&" do ativo ("&FIXED(Cálculos_Apoio!E19,0)&" instituições, "&FIXED(Cálculos_Apoio!F19*100,1)&"%"&")."&CHAR(10)&"Privado Estrangeiro: "&FIXED(Cálculos_Apoio!D20*100,1)&"%"&" do ativo ("&FIXED(Cálculos_Apoio!E20,0)&" instituições, "&FIXED(Cálculos_Apoio!F20*100,1)&"%"&")." -> Público: 32,8% do ativo (39 instituições, 2,4% do total). Privado Nacional: 50,1% do ativo (1.353 instituições, 83,4%). Privado Estrangeiro: 17,2% do ativo (230 instituições, 14,2%). | E7: A concentração está nos bancos públicos ou nos privados? Compare com o número de instituições de cada grupo.
A9: ANÁLISE DE EFICIÊNCIA E RENTABILIDADE
A10: Nº | B10: O que fazer | C10: Fórmula aplicada | D10: Resultado | E10: Para reflexão
A11: 4 | B11: Identifique as 5 instituições com MAIOR ROE do semestre na base: a) Considerando toda a base b) Considerando só instituições com Ativo Total acima de R$ 1 bilhão (1.000.000 em R$ mil) → Use MAIOR com ÍNDICE e CORRESP, ou ordene com filtro | C11: Calc_Intermediário!E28 (copiada até E32), item (a): =MAIOR(Base_IFData!$W$5:$W$1626; $A28) B28 (nome): =ÍNDICE(Base_IFData!$A$5:$A$1626; CORRESP($E28; Base_IFData!$W$5:$W$1626; 0)) Item (b): mesma lógica em B36:E40, sobre a coluna auxiliar M, que traz o ROE só se Ativo > R$ 1 bi: M5 (copiada até M1626): =SE(E(ÉNÚM(Base_IFData!L5); ÉNÚM(Base_IFData!W5)); SE(Base_IFData!L5>$B$5; Base_IFData!W5; ""); "") | D11: ="(a) Toda a base:"&CHAR(10)&"1º "&IF(LEN(Cálculos_Apoio!B27)>28,LEFT(Cálculos_Apoio!B27,28)&"...",Cálculos_Apoio!B27)&" ("&FIXED(Cálculos_Apoio!E27*100,1)&"%"&")"&CHAR(10)&"2º "&IF(LEN(Cálculos_Apoio!B28)>28,LEFT(Cálculos_Apoio!B28,28)&"...",Cálculos_Apoio!B28)&" ("&FIXED(Cálculos_Apoio!E28*100,1)&"%"&")"&CHAR(10)&"3º "&IF(LEN(Cálculos_Apoio!B29)>28,LEFT(Cálculos_Apoio!B29,28)&"...",Cálculos_Apoio!B29)&" ("&FIXED(Cálculos_Apoio!E29*100,1)&"%"&")"&CHAR(10)&"4º "&IF(LEN(Cálculos_Apoio!B30)>28,LEFT(Cálculos_Apoio!B30,28)&"...",Cálculos_Apoio!B30)&" ("&FIXED(Cálculos_Apoio!E30*100,1)&"%"&")"&CHAR(10)&"5º "&IF(LEN(Cálculos_Apoio!B31)>28,LEFT(Cálculos_Apoio!B31,28)&"...",Cálculos_Apoio!B31)&" ("&FIXED(Cálculos_Apoio!E31*100,1)&"%"&")"&CHAR(10)&"(b) Ativo > R$ "&FIXED(Cálculos_Apoio!B4/1000000,0)&" bi:"&CHAR(10)&"1º "&IF(LEN(Cálculos_Apoio!B35)>28,LEFT(Cálculos_Apoio!B35,28)&"...",Cálculos_Apoio!B35)&" ("&FIXED(Cálculos_Apoio!E35*100,1)&"%"&")"&CHAR(10)&"2º "&IF(LEN(Cálculos_Apoio!B36)>28,LEFT(Cálculos_Apoio!B36,28)&"...",Cálculos_Apoio!B36)&" ("&FIXED(Cálculos_Apoio!E36*100,1)&"%"&")"&CHAR(10)&"3º "&IF(LEN(Cálculos_Apoio!B37)>28,LEFT(Cálculos_Apoio!B37,28)&"...",Cálculos_Apoio!B37)&" ("&FIXED(Cálculos_Apoio!E37*100,1)&"%"&")"&CHAR(10)&"4º "&IF(LEN(Cálculos_Apoio!B38)>28,LEFT(Cálculos_Apoio!B38,28)&"...",Cálculos_Apoio!B38)&" ("&FIXED(Cálculos_Apoio!E38*100,1)&"%"&")"&CHAR(10)&"5º "&IF(LEN(Cálculos_Apoio!B39)>28,LEFT(Cálculos_Apoio!B39,28)&"...",Cálculos_Apoio!B39)&" ("&FIXED(Cálculos_Apoio!E39*100,1)&"%"&")" -> (a) Toda a base: 1º GREENPASS TECNOLOGIA E INSTI... (168,5%) 2º BOC BRASIL S.A. - CRÉDITO, F... (147,1%) 3º CAIXA DISTRIBUIDORA DE TÍTUL... (90,7%) 4º BB GESTÃO DE RECURSOS - DIST... (87,1%) 5º EFEX INSTITUIÇÃO DE PAGAMENT... (82,1%) (b) Ativo > R$ 1 bi: 1º BB GESTÃO DE RECURSOS - DIST... (87,1%) 2º CITIBANK DISTRIBUIDORA DE TI... (63,3%) 3º DAYCOVAL LEASING SOCIEDADE D... (56,0%) 4º BTG PACTUAL SERVIÇOS FINANCE... (46,9%) 5º CLOUDWALK FINANCEIRA S.A. CR... (44,5%) | E11: As mais rentáveis são as maiores instituições ou as menores? O que muda quando se aplica o filtro de tamanho?
A12: 5 | B12: Calcule o Índice de Alavancagem (Passivo Exigível ÷ Patrimônio Líquido) de cada instituição. → Crie uma coluna auxiliar com a fórmula e trate PL menor ou igual a zero e valores NI | C12: Calc_Intermediário!N5 (copiada até N1626): =SE(E(ÉNÚM(Base_IFData!O5); ÉNÚM(Base_IFData!Q5)); SE(Base_IFData!Q5>0; Base_IFData!O5/Base_IFData!Q5; "PL ≤ 0"); "NI") Maior valor: B46 =MÁXIMO($N$5:$N$1626); nome: B47 =ÍNDICE(Base_IFData!$A$5:$A$1626; CORRESP($B$46; $N$5:$N$1626; 0)) | D12: ="Calculada para "&FIXED(Cálculos_Apoio!B42,0)&" instituições (excluídas: "&FIXED(Cálculos_Apoio!B43,0)&" com PL ≤ 0 e "&FIXED(Cálculos_Apoio!B44,0)&" NI). Maior: "&Cálculos_Apoio!B46&" ("&FIXED(Cálculos_Apoio!B45,1)&"x; TCB "&Cálculos_Apoio!B47&"). Mediana: "&FIXED(Cálculos_Apoio!B48,1)&"x." -> Calculada para 1.565 instituições (excluídas: 6 com PL ≤ 0 e 51 NI). Maior: BANCO DIGIO S.A. (505,2x; TCB b2). Mediana: 3,5x. | E12: Alavancagem alta pode indicar maior risco. Quem tem a maior alavancagem entre as instituições com PL positivo?
A13: 6 | B13: Quantas instituições têm Carteira de Crédito igual ou maior que 10 vezes o Patrimônio Líquido? → CONT.SES não compara duas colunas entre si: use SOMARPRODUTO com SEERRO, ou uma coluna auxiliar Crédito/PL com CONT.SE | C13: Calc_Intermediário!O5 (copiada até O1626): =SE(E(ÉNÚM(Base_IFData!M5); ÉNÚM(Base_IFData!Q5)); SE(Base_IFData!Q5>0; Base_IFData!M5/Base_IFData!Q5; "PL ≤ 0"); "NI") Calc_Intermediário!B52: =CONT.SE($O$5:$O$1626; ">="&$B$6) (B6 = 10) Por TCB (B56:B63): =CONT.SES($L$5:$L$1626; $A56; $O$5:$O$1626; ">="&$B$6) | D13: =FIXED(Cálculos_Apoio!B51,0)&" instituições têm Carteira ≥ "&FIXED(Cálculos_Apoio!B5,0)&"x o PL ("&FIXED(Cálculos_Apoio!B53*100,1)&"%"&" das "&FIXED(Cálculos_Apoio!B52,0)&" com PL > 0). Mais frequente no TCB "&INDEX(Cálculos_Apoio!A55:A62,MATCH(MAX(Cálculos_Apoio!B55:B62),Cálculos_Apoio!B55:B62,0))&" ("&FIXED(MAX(Cálculos_Apoio!B55:B62),0)&" instituições)." -> 21 instituições têm Carteira ≥ 10x o PL (1,3% das 1.565 com PL > 0). Mais frequente no TCB b1 (11 instituições). | E13: Alta relação crédito/PL é característica de algum tipo de instituição? Verifique o TCB das instituições encontradas.
A15: ANÁLISE REGIONAL E ESTRUTURAL
A16: Nº | B16: O que fazer | C16: Fórmula aplicada | D16: Resultado | E16: Para reflexão
A17: 7 | B17: Quantas instituições com sede em SP têm Ativo Total acima de R$ 1 bilhão (1.000.000 em R$ mil)? → Use CONT.SES com UF = 'SP' e Ativo > 1000000 | C17: Calc_Intermediário!B67: =CONT.SES(Base_IFData!$J$5:$J$1626; $B$7; Base_IFData!$L$5:$L$1626; ">"&$B$5) (B7 = "SP"; B5 = 1.000.000) B68 (total do país): =CONT.SE(Base_IFData!$L$5:$L$1626; ">"&$B$5) | D17: =FIXED(Cálculos_Apoio!B66,0)&" instituições com sede em "&Cálculos_Apoio!B6&" têm Ativo > R$ "&FIXED(Cálculos_Apoio!B4/1000000,0)&" bi, de "&FIXED(Cálculos_Apoio!B67,0)&" no país ("&FIXED(Cálculos_Apoio!B68*100,1)&"%"&" do total acima desse corte)." -> 207 instituições com sede em SP têm Ativo > R$ 1 bi, de 511 no país (40,5% do total acima desse corte). | E17: Que percentual do total de instituições acima de R$ 1 bilhão isso representa?
A18: 8 | B18: Qual é a soma do Ativo Total das instituições SEM AGÊNCIAS FÍSICAS (Número de Agências = 0)? → Use SOMASE com a condição Agências = 0 | C18: Calc_Intermediário!B72: =CONT.SE(Base_IFData!$S$5:$S$1626; $B$8) (B8 = 0) B73: =SOMASE(Base_IFData!$S$5:$S$1626; $B$8; Base_IFData!$L$5:$L$1626) B74: =B73/SOMA(Base_IFData!$L$5:$L$1626) Cruzamento com TCB: B76:E83 (CONT.SES e SOMASES). | D18: =FIXED(Cálculos_Apoio!B71,0)&" instituições sem agência física somam R$ "&FIXED(Cálculos_Apoio!B72,0)&" mil, ou "&FIXED(Cálculos_Apoio!B73*100,1)&"%"&" do ativo total. Estão em "&COUNTIF(Cálculos_Apoio!B75:B82,">0")&" TCBs: "&Cálculos_Apoio!A77&" ("&FIXED(Cálculos_Apoio!B77,0)&") e "&Cálculos_Apoio!A78&" ("&FIXED(Cálculos_Apoio!B78,0)&"). Nos TCBs "&Cálculos_Apoio!A80&" e "&Cálculos_Apoio!A82&" há "&FIXED(Cálculos_Apoio!B80+Cálculos_Apoio!B82,0)&" sem agência." -> 756 instituições sem agência física somam R$ 1.246.899.112 mil, ou 6,4% do ativo total. Estão em 2 TCBs: b3S (729) e b3C (27). Nos TCBs n1 e n4 há 0 sem agência. | E18: Que parcela do ativo total esse grupo representa? Cruze com o TCB: 'sem agência física' é o mesmo que 'digital'?
A19: 9 | B19: Monte um resumo: quantas instituições de cada UF estão na base? → Use CONT.SE para as cinco UFs com mais instituições: SP, MG, RS, PR e SC | C19: Calc_Intermediário!B88 (copiada até B92): =CONT.SE(Base_IFData!$J$5:$J$1626; $A88) (A88:A92 = SP, MG, RS, PR e SC) C88 (copiada até C92): =B88/B$94 (B94 = total de instituições da base) | D19: ="SP: "&FIXED(Cálculos_Apoio!B87,0)&" ("&FIXED(Cálculos_Apoio!C87*100,1)&"%"&")"&CHAR(10)&"MG: "&FIXED(Cálculos_Apoio!B88,0)&" ("&FIXED(Cálculos_Apoio!C88*100,1)&"%"&")"&CHAR(10)&"RS: "&FIXED(Cálculos_Apoio!B89,0)&" ("&FIXED(Cálculos_Apoio!C89*100,1)&"%"&")"&CHAR(10)&"PR: "&FIXED(Cálculos_Apoio!B90,0)&" ("&FIXED(Cálculos_Apoio!C90*100,1)&"%"&")"&CHAR(10)&"SC: "&FIXED(Cálculos_Apoio!B91,0)&" ("&FIXED(Cálculos_Apoio!C91*100,1)&"%"&")"&CHAR(10)&"Demais UFs: "&FIXED(Cálculos_Apoio!B92,0)&" ("&FIXED(Cálculos_Apoio!C92*100,1)&"%"&"). Total: "&FIXED(Cálculos_Apoio!B93,0) -> SP: 684 (42,2%) MG: 210 (12,9%) RS: 145 (8,9%) PR: 121 (7,5%) SC: 118 (7,3%) Demais UFs: 344 (21,2%). Total: 1.622 | E19: A distribuição geográfica reflete o PIB de cada estado?
A21: SÍNTESE FINAL
A22: Nº | B22: O que fazer | C22: Fórmula aplicada | D22: Resultado | E22: Para reflexão
A23: 10 | B23: Com base em todos os exercícios anteriores, escreva sua análise respondendo: 1. Qual é o perfil do sistema financeiro brasileiro segundo esta base? 2. Qual insight mais surpreendeu? 3. Se fosse apresentar isto a um diretor em 2 minutos, o que diria? → Use a aba Template_Análise | C23: Texto montado com fórmulas (concatenação com &) sobre os resultados da aba Tabela_TCB (item 1) e da aba Calc_Intermediário (itens 2 a 9). Não há função de cálculo própria; as frases se atualizam se a base mudar. A aba Template_Análise não foi alterada. | D23: ="1. PERFIL: sistema muito concentrado e dominado por bancos. O TCB b1 reúne "&FIXED(Tabela_TCB!F5*100,1)&"%"&" das instituições e "&FIXED(Tabela_TCB!G5*100,1)&"%"&" do ativo; as cooperativas singulares (b3S) são "&FIXED(Tabela_TCB!F7*100,1)&"%"&" das instituições e só "&FIXED(Tabela_TCB!G7*100,1)&"%"&" do ativo."&" Por controle, o setor privado nacional detém "&FIXED(Cálculos_Apoio!D19*100,1)&"%"&" do ativo, o público "&FIXED(Cálculos_Apoio!D18*100,1)&"%"&" e o estrangeiro "&FIXED(Cálculos_Apoio!D20*100,1)&"%"&"."&CHAR(10)&CHAR(10)&"2. INSIGHT MAIS SURPREENDENTE: a média simples dos ROEs do sistema é "&FIXED(Cálculos_Apoio!D14*100,1)&"%"&", mas o ROE agregado (Lucro ÷ PL) é "&FIXED(Cálculos_Apoio!G14*100,1)&"%"&". Entre os estrangeiros, a média simples é "&FIXED(Cálculos_Apoio!D13*100,1)&"%"&" e o agregado "&FIXED(Cálculos_Apoio!G13*100,1)&"%"&"."&" Muitas instituições pequenas distorcem a média. O maior ROE da base ("&FIXED(Cálculos_Apoio!E27*100,1)&"%"&") é de uma instituição com Ativo de R$ "&FIXED(Cálculos_Apoio!D27/1000,0)&" milhões."&CHAR(10)&CHAR(10)&"3. EM 2 MINUTOS: o sistema tem "&FIXED(Tabela_TCB!B13,0)&" instituições, mas poucas concentram o ativo ("&FIXED(Tabela_TCB!G5*100,1)&"%"&" no b1). Para rentabilidade, use o ROE agregado, não a média simples."&" Ressalvas: "&FIXED(Cálculos_Apoio!B44,0)&" instituições com NI ficam fora das somas, e holdings e controladas podem duplicar ativo. Recomendação: repetir a análise por grupo econômico (conglomerado)." -> 1. PERFIL: sistema muito concentrado e dominado por bancos. O TCB b1 reúne 7,2% das instituições e 73,3% do ativo; as cooperativas singulares (b3S) são 44,9% das instituições e só 5,1% do ativo. Por controle, o setor privado nacional detém 50,1% do ativo, o público 32,8% e o estrangeiro 17,2%. 2. INSIGHT MAIS SURPREENDENTE: a média simples dos ROEs do sistema é 0,8%, mas o ROE agregado (Lucro ÷ PL) é 7,5%. Entre os estrangeiros, a média simples é -3,4% e o agregado 7,7%. Muitas instituições pequenas distorcem a média. O maior ROE da base (168,5%) é de uma instituição com Ativo de R$ 420 milhões. 3. EM 2 MINUTOS: o sistema tem 1.622 instituições, mas poucas concentram o ativo (73,3% no b1). Para rentabilidade, use o ROE agregado, não a média simples. Ressalvas: 51 instituições com NI ficam fora das somas, e holdings e controladas podem duplicar ativo. Recomendação: repetir a análise por grupo econômico (conglomerado). | E23: Estruture a resposta em três partes: evidência, interpretação e recomendação.

Sheet Tabela_TCB
A1: ANÁLISE COMPARATIVA POR TIPO DE CONSOLIDADO BANCÁRIO (TCB)
A4: TCB | B4: Qtd. de instituições | C4: Soma do Ativo Total (R$ mil) | D4: Média da Carteira de Crédito (R$ mil) | E4: Soma do Lucro Líquido (R$ mil) | F4: % das instituições | G4: % do Ativo Total | H4: % do Lucro Líquido
A5: b1 | B5: =COUNTIF(Base_IFData!$F$5:$F$1626,$A5) -> 116 | C5: =SUMIF(Base_IFData!$F$5:$F$1626,$A5,Base_IFData!$L$5:$L$1626) -> 14285826206 | D5: =AVERAGEIF(Base_IFData!$F$5:$F$1626,$A5,Base_IFData!$M$5:$M$1626) -> 48348726 | E5: =SUMIF(Base_IFData!$F$5:$F$1626,$A5,Base_IFData!$R$5:$R$1626) -> 80608476 | F5: =B5/B$13 -> 0.071516646 | G5: =C5/C$13 -> 0.73269093 | H5: =E5/E$13 -> 0.52524896
A6: b2 | B6: =COUNTIF(Base_IFData!$F$5:$F$1626,$A6) -> 50 | C6: =SUMIF(Base_IFData!$F$5:$F$1626,$A6,Base_IFData!$L$5:$L$1626) -> 931799119 | D6: =AVERAGEIF(Base_IFData!$F$5:$F$1626,$A6,Base_IFData!$M$5:$M$1626) -> 8601829.3 | E6: =SUMIF(Base_IFData!$F$5:$F$1626,$A6,Base_IFData!$R$5:$R$1626) -> 27442031 | F6: =B6/B$13 -> 0.030826141 | G6: =C6/C$13 -> 0.047790079 | H6: =E6/E$13 -> 0.17881368
A7: b3S | B7: =COUNTIF(Base_IFData!$F$5:$F$1626,$A7) -> 729 | C7: =SUMIF(Base_IFData!$F$5:$F$1626,$A7,Base_IFData!$L$5:$L$1626) -> 992158870 | D7: =AVERAGEIF(Base_IFData!$F$5:$F$1626,$A7,Base_IFData!$M$5:$M$1626) -> 752586.23 | E7: =SUMIF(Base_IFData!$F$5:$F$1626,$A7,Base_IFData!$R$5:$R$1626) -> 8584469 | F7: =B7/B$13 -> 0.44944513 | G7: =C7/C$13 -> 0.050885808 | H7: =E7/E$13 -> 0.05593684
A8: b3C | B8: =COUNTIF(Base_IFData!$F$5:$F$1626,$A8) -> 27 | C8: =SUMIF(Base_IFData!$F$5:$F$1626,$A8,Base_IFData!$L$5:$L$1626) -> 254740242 | D8: =AVERAGEIF(Base_IFData!$F$5:$F$1626,$A8,Base_IFData!$M$5:$M$1626) -> 102214.26 | E8: =SUMIF(Base_IFData!$F$5:$F$1626,$A8,Base_IFData!$R$5:$R$1626) -> 677773 | F8: =B8/B$13 -> 0.016646116 | G8: =C8/C$13 -> 0.013065108 | H8: =E8/E$13 -> 0.0044164036
A9: b4 | B9: =COUNTIF(Base_IFData!$F$5:$F$1626,$A9) -> 4 | C9: =SUMIF(Base_IFData!$F$5:$F$1626,$A9,Base_IFData!$L$5:$L$1626) -> 1121980384 | D9: =AVERAGEIF(Base_IFData!$F$5:$F$1626,$A9,Base_IFData!$M$5:$M$1626) -> 102571598 | E9: =SUMIF(Base_IFData!$F$5:$F$1626,$A9,Base_IFData!$R$5:$R$1626) -> 11549205 | F9: =B9/B$13 -> 0.0024660912 | G9: =C9/C$13 -> 0.057544089 | H9: =E9/E$13 -> 0.075255212
A10: n1 | B10: =COUNTIF(Base_IFData!$F$5:$F$1626,$A10) -> 290 | C10: =SUMIF(Base_IFData!$F$5:$F$1626,$A10,Base_IFData!$L$5:$L$1626) -> 734344384 | D10: =AVERAGEIF(Base_IFData!$F$5:$F$1626,$A10,Base_IFData!$M$5:$M$1626) -> 1384488.2 | E10: =SUMIF(Base_IFData!$F$5:$F$1626,$A10,Base_IFData!$R$5:$R$1626) -> 9405388 | F10: =B10/B$13 -> 0.17879162 | G10: =C10/C$13 -> 0.037663028 | H10: =E10/E$13 -> 0.06128599
A11: n2 | B11: =COUNTIF(Base_IFData!$F$5:$F$1626,$A11) -> 210 | C11: =SUMIF(Base_IFData!$F$5:$F$1626,$A11,Base_IFData!$L$5:$L$1626) -> 261394666 | D11: =AVERAGEIF(Base_IFData!$F$5:$F$1626,$A11,Base_IFData!$M$5:$M$1626) -> 863.00976 | E11: =SUMIF(Base_IFData!$F$5:$F$1626,$A11,Base_IFData!$R$5:$R$1626) -> 4805470 | F11: =B11/B$13 -> 0.12946979 | G11: =C11/C$13 -> 0.0134064 | H11: =E11/E$13 -> 0.031312689
A12: n4 | B12: =COUNTIF(Base_IFData!$F$5:$F$1626,$A12) -> 196 | C12: =SUMIF(Base_IFData!$F$5:$F$1626,$A12,Base_IFData!$L$5:$L$1626) -> 915508281 | D12: =AVERAGEIF(Base_IFData!$F$5:$F$1626,$A12,Base_IFData!$M$5:$M$1626) -> 611339.85 | E12: =SUMIF(Base_IFData!$F$5:$F$1626,$A12,Base_IFData!$R$5:$R$1626) -> 10394366 | F12: =B12/B$13 -> 0.12083847 | G12: =C12/C$13 -> 0.046954555 | H12: =E12/E$13 -> 0.067730222
A13: Total | B13: =SUM(B5:B12) -> 1622 | C13: =SUM(C5:C12) -> 19497752152 | D13: =AVERAGE(Base_IFData!$M$5:$M$1626) -> 4701571.3 | E13: =SUM(E5:E12) -> 153467178 | F13: =SUM(F5:F12) -> 1 | G13: =SUM(G5:G12) -> 1 | H13: =SUM(H5:H12) -> 1
A15: Conferência: qtd. da tabela − linhas da base | B15: =B13-COUNTA(Base_IFData!$A$5:$A$1626) -> 0
A16: Conferência: ativo da tabela − soma da base | B16: =C13-SUM(Base_IFData!$L$5:$L$1626) -> 0

Sheet Cálculos_Apoio
A1: CÁLCULOS DE APOIO | IFData Junho 2026
Q2: AUXILIAR DO GRÁFICO DE DISPERSÃO (Gráficos_Análise, seção C): ROE das 30 maiores instituições por Ativo Total, separado por tipo de controle | W2: DADOS DOS GRÁFICOS (Gráficos_Análise, seções B e C) | tudo calculado sobre a Base_IFData
A3: PARÂMETROS | K3: Instituição | L3: TCB | M3: ROE do semestre (Ativo > corte) | N3: Alavancagem (Passivo Exigível ÷ PL) | O3: Carteira de Crédito ÷ PL | Q3: Ativo Total (R$ bi) | R3: Público | S3: Privado Nacional | T3: Privado Estrangeiro | U3: Posição na base (linha relativa) | W3: TCB | X3: ROE agregado do semestre (Lucro ÷ PL) | Y3: Ativo Total médio (R$ bi) | Z3: Índice Crédito/Ativo (Carteira ÷ Ativo)
A4: Corte de Ativo Total (R$ mil): R$ 1 bilhão | B4: 1000000 | K4: =Base_IFData!A5 -> BANCO DO BRASIL S.A. | L4: =Base_IFData!F5 -> b1 | M4: =IF(AND(ISNUMBER(Base_IFData!L5),ISNUMBER(Base_IFData!W5)),IF(Base_IFData!L5>$B$4,Base_IFData!W5,""),"") -> 0.034279764 | N4: =IF(AND(ISNUMBER(Base_IFData!O5),ISNUMBER(Base_IFData!Q5)),IF(Base_IFData!Q5>0,Base_IFData!O5/Base_IFData!Q5,"PL ≤ 0"),"NI") -> 12.572188 | O4: =IF(AND(ISNUMBER(Base_IFData!M5),ISNUMBER(Base_IFData!Q5)),IF(Base_IFData!Q5>0,Base_IFData!M5/Base_IFData!Q5,"PL ≤ 0"),"NI") -> 5.8770896 | Q4: {=INDEX(Base_IFData!$L$5:$L$1626,$U4)/1000000} -> 2461.0869 | R4: {=IF(INDEX(Base_IFData!$U$5:$U$1626,$U4)=R$3,INDEX(Base_IFData!$W$5:$W$1626,$U4),NA())} -> 0.034279764 | S4: {=IF(INDEX(Base_IFData!$U$5:$U$1626,$U4)=S$3,INDEX(Base_IFData!$W$5:$W$1626,$U4),NA())} -> #N/A | T4: {=IF(INDEX(Base_IFData!$U$5:$U$1626,$U4)=T$3,INDEX(Base_IFData!$W$5:$W$1626,$U4),NA())} -> #N/A | U4: =MATCH(LARGE(Base_IFData!$L$5:$L$1626,ROWS(U$4:U4)),Base_IFData!$L$5:$L$1626,0) -> 1 | W4: b1 | X4: =SUMIF(Base_IFData!$F$5:$F$1626,$W4,Base_IFData!$R$5:$R$1626)/SUMIF(Base_IFData!$F$5:$F$1626,$W4,Base_IFData!$Q$5:$Q$1626) -> 0.071441186 | Y4: =AVERAGEIF(Base_IFData!$F$5:$F$1626,$W4,Base_IFData!$L$5:$L$1626)/1000000 -> 125.31426 | Z4: =SUMIF(Base_IFData!$F$5:$F$1626,$W4,Base_IFData!$M$5:$M$1626)/SUMIF(Base_IFData!$F$5:$F$1626,$W4,Base_IFData!$L$5:$L$1626) -> 0.38581981
A5: Múltiplo Carteira de Crédito ÷ Patrimônio Líquido | B5: 10 | K5: =Base_IFData!A6 -> CAIXA ECONOMICA FEDERAL | L5: =Base_IFData!F6 -> b1 | M5: =IF(AND(ISNUMBER(Base_IFData!L6),ISNUMBER(Base_IFData!W6)),IF(Base_IFData!L6>$B$4,Base_IFData!W6,""),"") -> 0.055638395 | N5: =IF(AND(ISNUMBER(Base_IFData!O6),ISNUMBER(Base_IFData!Q6)),IF(Base_IFData!Q6>0,Base_IFData!O6/Base_IFData!Q6,"PL ≤ 0"),"NI") -> 19.006686 | O5: =IF(AND(ISNUMBER(Base_IFData!M6),ISNUMBER(Base_IFData!Q6)),IF(Base_IFData!Q6>0,Base_IFData!M6/Base_IFData!Q6,"PL ≤ 0"),"NI") -> 11.509304 | Q5: {=INDEX(Base_IFData!$L$5:$L$1626,$U5)/1000000} -> 2368.1472 | R5: {=IF(INDEX(Base_IFData!$U$5:$U$1626,$U5)=R$3,INDEX(Base_IFData!$W$5:$W$1626,$U5),NA())} -> 0.055638395 | S5: {=IF(INDEX(Base_IFData!$U$5:$U$1626,$U5)=S$3,INDEX(Base_IFData!$W$5:$W$1626,$U5),NA())} -> #N/A | T5: {=IF(INDEX(Base_IFData!$U$5:$U$1626,$U5)=T$3,INDEX(Base_IFData!$W$5:$W$1626,$U5),NA())} -> #N/A | U5: =MATCH(LARGE(Base_IFData!$L$5:$L$1626,ROWS(U$4:U5)),Base_IFData!$L$5:$L$1626,0) -> 2 | W5: b2 | X5: =SUMIF(Base_IFData!$F$5:$F$1626,$W5,Base_IFData!$R$5:$R$1626)/SUMIF(Base_IFData!$F$5:$F$1626,$W5,Base_IFData!$Q$5:$Q$1626) -> 0.097382484 | Y5: =AVERAGEIF(Base_IFData!$F$5:$F$1626,$W5,Base_IFData!$L$5:$L$1626)/1000000 -> 18.635982 | Z5: =SUMIF(Base_IFData!$F$5:$F$1626,$W5,Base_IFData!$M$5:$M$1626)/SUMIF(Base_IFData!$F$5:$F$1626,$W5,Base_IFData!$L$5:$L$1626) -> 0.46157101
A6: UF analisada (item 7) | B6: SP | K6: =Base_IFData!A7 -> ITAÚ UNIBANCO S.A. | L6: =Base_IFData!F7 -> b1 | M6: =IF(AND(ISNUMBER(Base_IFData!L7),ISNUMBER(Base_IFData!W7)),IF(Base_IFData!L7>$B$4,Base_IFData!W7,""),"") -> 0.12132917 | N6: =IF(AND(ISNUMBER(Base_IFData!O7),ISNUMBER(Base_IFData!Q7)),IF(Base_IFData!Q7>0,Base_IFData!O7/Base_IFData!Q7,"PL ≤ 0"),"NI") -> 12.320589 | O6: =IF(AND(ISNUMBER(Base_IFData!M7),ISNUMBER(Base_IFData!Q7)),IF(Base_IFData!Q7>0,Base_IFData!M7/Base_IFData!Q7,"PL ≤ 0"),"NI") -> 4.2987797 | Q6: {=INDEX(Base_IFData!$L$5:$L$1626,$U6)/1000000} -> 2169.4096 | R6: {=IF(INDEX(Base_IFData!$U$5:$U$1626,$U6)=R$3,INDEX(Base_IFData!$W$5:$W$1626,$U6),NA())} -> #N/A | S6: {=IF(INDEX(Base_IFData!$U$5:$U$1626,$U6)=S$3,INDEX(Base_IFData!$W$5:$W$1626,$U6),NA())} -> 0.12132917 | T6: {=IF(INDEX(Base_IFData!$U$5:$U$1626,$U6)=T$3,INDEX(Base_IFData!$W$5:$W$1626,$U6),NA())} -> #N/A | U6: =MATCH(LARGE(Base_IFData!$L$5:$L$1626,ROWS(U$4:U6)),Base_IFData!$L$5:$L$1626,0) -> 3 | W6: b3S | X6: =SUMIF(Base_IFData!$F$5:$F$1626,$W6,Base_IFData!$R$5:$R$1626)/SUMIF(Base_IFData!$F$5:$F$1626,$W6,Base_IFData!$Q$5:$Q$1626) -> 0.061318956 | Y6: =AVERAGEIF(Base_IFData!$F$5:$F$1626,$W6,Base_IFData!$L$5:$L$1626)/1000000 -> 1.3974069 | Z6: =SUMIF(Base_IFData!$F$5:$F$1626,$W6,Base_IFData!$M$5:$M$1626)/SUMIF(Base_IFData!$F$5:$F$1626,$W6,Base_IFData!$L$5:$L$1626) -> 0.53855914
A7: Nº de agências para 'sem agência física' (item 8) | B7: 0 | K7: =Base_IFData!A8 -> BANCO BRADESCO S.A. | L7: =Base_IFData!F8 -> b1 | M7: =IF(AND(ISNUMBER(Base_IFData!L8),ISNUMBER(Base_IFData!W8)),IF(Base_IFData!L8>$B$4,Base_IFData!W8,""),"") -> 0.068938204 | N7: =IF(AND(ISNUMBER(Base_IFData!O8),ISNUMBER(Base_IFData!Q8)),IF(Base_IFData!Q8>0,Base_IFData!O8/Base_IFData!Q8,"PL ≤ 0"),"NI") -> 10.142274 | O7: =IF(AND(ISNUMBER(Base_IFData!M8),ISNUMBER(Base_IFData!Q8)),IF(Base_IFData!Q8>0,Base_IFData!M8/Base_IFData!Q8,"PL ≤ 0"),"NI") -> 4.3144062 | Q7: {=INDEX(Base_IFData!$L$5:$L$1626,$U7)/1000000} -> 1952.4643 | R7: {=IF(INDEX(Base_IFData!$U$5:$U$1626,$U7)=R$3,INDEX(Base_IFData!$W$5:$W$1626,$U7),NA())} -> #N/A | S7: {=IF(INDEX(Base_IFData!$U$5:$U$1626,$U7)=S$3,INDEX(Base_IFData!$W$5:$W$1626,$U7),NA())} -> 0.068938204 | T7: {=IF(INDEX(Base_IFData!$U$5:$U$1626,$U7)=T$3,INDEX(Base_IFData!$W$5:$W$1626,$U7),NA())} -> #N/A | U7: =MATCH(LARGE(Base_IFData!$L$5:$L$1626,ROWS(U$4:U7)),Base_IFData!$L$5:$L$1626,0) -> 4 | W7: b3C | X7: =SUMIF(Base_IFData!$F$5:$F$1626,$W7,Base_IFData!$R$5:$R$1626)/SUMIF(Base_IFData!$F$5:$F$1626,$W7,Base_IFData!$Q$5:$Q$1626) -> 0.034656352 | Y7: =AVERAGEIF(Base_IFData!$F$5:$F$1626,$W7,Base_IFData!$L$5:$L$1626)/1000000 -> 9.4348238 | Z7: =SUMIF(Base_IFData!$F$5:$F$1626,$W7,Base_IFData!$M$5:$M$1626)/SUMIF(Base_IFData!$F$5:$F$1626,$W7,Base_IFData!$L$5:$L$1626) -> 0.010833722
K8: =Base_IFData!A9 -> BANCO SANTANDER (BRASIL) S.A. | L8: =Base_IFData!F9 -> b1 | M8: =IF(AND(ISNUMBER(Base_IFData!L9),ISNUMBER(Base_IFData!W9)),IF(Base_IFData!L9>$B$4,Base_IFData!W9,""),"") -> 0.074772555 | N8: =IF(AND(ISNUMBER(Base_IFData!O9),ISNUMBER(Base_IFData!Q9)),IF(Base_IFData!Q9>0,Base_IFData!O9/Base_IFData!Q9,"PL ≤ 0"),"NI") -> 11.249233 | O8: =IF(AND(ISNUMBER(Base_IFData!M9),ISNUMBER(Base_IFData!Q9)),IF(Base_IFData!Q9>0,Base_IFData!M9/Base_IFData!Q9,"PL ≤ 0"),"NI") -> 3.6996118 | Q8: {=INDEX(Base_IFData!$L$5:$L$1626,$U8)/1000000} -> 1209.4431 | R8: {=IF(INDEX(Base_IFData!$U$5:$U$1626,$U8)=R$3,INDEX(Base_IFData!$W$5:$W$1626,$U8),NA())} -> #N/A | S8: {=IF(INDEX(Base_IFData!$U$5:$U$1626,$U8)=S$3,INDEX(Base_IFData!$W$5:$W$1626,$U8),NA())} -> #N/A | T8: {=IF(INDEX(Base_IFData!$U$5:$U$1626,$U8)=T$3,INDEX(Base_IFData!$W$5:$W$1626,$U8),NA())} -> 0.074772555 | U8: =MATCH(LARGE(Base_IFData!$L$5:$L$1626,ROWS(U$4:U8)),Base_IFData!$L$5:$L$1626,0) -> 5 | W8: b4 | X8: =SUMIF(Base_IFData!$F$5:$F$1626,$W8,Base_IFData!$R$5:$R$1626)/SUMIF(Base_IFData!$F$5:$F$1626,$W8,Base_IFData!$Q$5:$Q$1626) -> 0.060922532 | Y8: =AVERAGEIF(Base_IFData!$F$5:$F$1626,$W8,Base_IFData!$L$5:$L$1626)/1000000 -> 280.4951 | Z8: =SUMIF(Base_IFData!$F$5:$F$1626,$W8,Base_IFData!$M$5:$M$1626)/SUMIF(Base_IFData!$F$5:$F$1626,$W8,Base_IFData!$L$5:$L$1626) -> 0.36568054
A9: ITEM 2 | ROE do semestre por tipo de controle (TC) | K9: =Base_IFData!A10 -> BANCO NACIONAL DE DESENVOLVIMENTO ECONOMICO E SOCIAL | L9: =Base_IFData!F10 -> b4 | M9: =IF(AND(ISNUMBER(Base_IFData!L10),ISNUMBER(Base_IFData!W10)),IF(Base_IFData!L10>$B$4,Base_IFData!W10,""),"") -> 0.061722446 | N9: =IF(AND(ISNUMBER(Base_IFData!O10),ISNUMBER(Base_IFData!Q10)),IF(Base_IFData!Q10>0,Base_IFData!O10/Base_IFData!Q10,"PL ≤ 0"),"NI") -> 4.9401456 | O9: =IF(AND(ISNUMBER(Base_IFData!M10),ISNUMBER(Base_IFData!Q10)),IF(Base_IFData!Q10>0,Base_IFData!M10/Base_IFData!Q10,"PL ≤ 0"),"NI") -> 2.0791205 | Q9: {=INDEX(Base_IFData!$L$5:$L$1626,$U9)/1000000} -> 1073.4037 | R9: {=IF(INDEX(Base_IFData!$U$5:$U$1626,$U9)=R$3,INDEX(Base_IFData!$W$5:$W$1626,$U9),NA())} -> 0.061722446 | S9: {=IF(INDEX(Base_IFData!$U$5:$U$1626,$U9)=S$3,INDEX(Base_IFData!$W$5:$W$1626,$U9),NA())} -> #N/A | T9: {=IF(INDEX(Base_IFData!$U$5:$U$1626,$U9)=T$3,INDEX(Base_IFData!$W$5:$W$1626,$U9),NA())} -> #N/A | U9: =MATCH(LARGE(Base_IFData!$L$5:$L$1626,ROWS(U$4:U9)),Base_IFData!$L$5:$L$1626,0) -> 6 | W9: n1 | X9: =SUMIF(Base_IFData!$F$5:$F$1626,$W9,Base_IFData!$R$5:$R$1626)/SUMIF(Base_IFData!$F$5:$F$1626,$W9,Base_IFData!$Q$5:$Q$1626) -> 0.08601598 | Y9: =AVERAGEIF(Base_IFData!$F$5:$F$1626,$W9,Base_IFData!$L$5:$L$1626)/1000000 -> 2.6415266 | Z9: =SUMIF(Base_IFData!$F$5:$F$1626,$W9,Base_IFData!$M$5:$M$1626)/SUMIF(Base_IFData!$F$5:$F$1626,$W9,Base_IFData!$L$5:$L$1626) -> 0.52412426
A10: TC | B10: Tipo de controle | C10: Nº de instituições | D10: (a) Média simples dos ROEs | E10: Soma do Lucro Líquido (R$ mil) | F10: Soma do Patrimônio Líquido (R$ mil) | G10: (b) ROE agregado (Lucro ÷ PL) | H10: Diferença (b) − (a) | K10: =Base_IFData!A11 -> BANCO BTG PACTUAL S.A. | L10: =Base_IFData!F11 -> b1 | M10: =IF(AND(ISNUMBER(Base_IFData!L11),ISNUMBER(Base_IFData!W11)),IF(Base_IFData!L11>$B$4,Base_IFData!W11,""),"") -> 0.11905877 | N10: =IF(AND(ISNUMBER(Base_IFData!O11),ISNUMBER(Base_IFData!Q11)),IF(Base_IFData!Q11>0,Base_IFData!O11/Base_IFData!Q11,"PL ≤ 0"),"NI") -> 8.3428834 | O10: =IF(AND(ISNUMBER(Base_IFData!M11),ISNUMBER(Base_IFData!Q11)),IF(Base_IFData!Q11>0,Base_IFData!M11/Base_IFData!Q11,"PL ≤ 0"),"NI") -> 1.0259462 | Q10: {=INDEX(Base_IFData!$L$5:$L$1626,$U10)/1000000} -> 743.25896 | R10: {=IF(INDEX(Base_IFData!$U$5:$U$1626,$U10)=R$3,INDEX(Base_IFData!$W$5:$W$1626,$U10),NA())} -> #N/A | S10: {=IF(INDEX(Base_IFData!$U$5:$U$1626,$U10)=S$3,INDEX(Base_IFData!$W$5:$W$1626,$U10),NA())} -> 0.11905877 | T10: {=IF(INDEX(Base_IFData!$U$5:$U$1626,$U10)=T$3,INDEX(Base_IFData!$W$5:$W$1626,$U10),NA())} -> #N/A | U10: =MATCH(LARGE(Base_IFData!$L$5:$L$1626,ROWS(U$4:U10)),Base_IFData!$L$5:$L$1626,0) -> 7 | W10: n2 | X10: =SUMIF(Base_IFData!$F$5:$F$1626,$W10,Base_IFData!$R$5:$R$1626)/SUMIF(Base_IFData!$F$5:$F$1626,$W10,Base_IFData!$Q$5:$Q$1626) -> 0.098449741 | Y10: =AVERAGEIF(Base_IFData!$F$5:$F$1626,$W10,Base_IFData!$L$5:$L$1626)/1000000 -> 1.2750959 | Z10: =SUMIF(Base_IFData!$F$5:$F$1626,$W10,Base_IFData!$M$5:$M$1626)/SUMIF(Base_IFData!$F$5:$F$1626,$W10,Base_IFData!$L$5:$L$1626) -> 0.00067681947
A11: 1 | B11: =INDEX(Base_IFData!$U$5:$U$1626,MATCH($A11,Base_IFData!$G$5:$G$1626,0)) -> Público | C11: =COUNTIF(Base_IFData!$G$5:$G$1626,$A11) -> 39 | D11: =AVERAGEIF(Base_IFData!$G$5:$G$1626,$A11,Base_IFData!$W$5:$W$1626) -> 0.079884687 | E11: =SUMIF(Base_IFData!$G$5:$G$1626,$A11,Base_IFData!$R$5:$R$1626) -> 29620372 | F11: =SUMIF(Base_IFData!$G$5:$G$1626,$A11,Base_IFData!$Q$5:$Q$1626) -> 554095297 | G11: =E11/F11 -> 0.05345718 | H11: =G11-D11 -> -0.026427507 | K11: =Base_IFData!A12 -> ITAÚ UNIBANCO HOLDING S.A. | L11: =Base_IFData!F12 -> b2 | M11: =IF(AND(ISNUMBER(Base_IFData!L12),ISNUMBER(Base_IFData!W12)),IF(Base_IFData!L12>$B$4,Base_IFData!W12,""),"") -> 0.11175156 | N11: =IF(AND(ISNUMBER(Base_IFData!O12),ISNUMBER(Base_IFData!Q12)),IF(Base_IFData!Q12>0,Base_IFData!O12/Base_IFData!Q12,"PL ≤ 0"),"NI") -> 1.3750898 | O11: =IF(AND(ISNUMBER(Base_IFData!M12),ISNUMBER(Base_IFData!Q12)),IF(Base_IFData!Q12>0,Base_IFData!M12/Base_IFData!Q12,"PL ≤ 0"),"NI") -> 0.83254895 | Q11: {=INDEX(Base_IFData!$L$5:$L$1626,$U11)/1000000} -> 493.1834 | R11: {=IF(INDEX(Base_IFData!$U$5:$U$1626,$U11)=R$3,INDEX(Base_IFData!$W$5:$W$1626,$U11),NA())} -> #N/A | S11: {=IF(INDEX(Base_IFData!$U$5:$U$1626,$U11)=S$3,INDEX(Base_IFData!$W$5:$W$1626,$U11),NA())} -> 0.11175156 | T11: {=IF(INDEX(Base_IFData!$U$5:$U$1626,$U11)=T$3,INDEX(Base_IFData!$W$5:$W$1626,$U11),NA())} -> #N/A | U11: =MATCH(LARGE(Base_IFData!$L$5:$L$1626,ROWS(U$4:U11)),Base_IFData!$L$5:$L$1626,0) -> 8 | W11: n4 | X11: =SUMIF(Base_IFData!$F$5:$F$1626,$W11,Base_IFData!$R$5:$R$1626)/SUMIF(Base_IFData!$F$5:$F$1626,$W11,Base_IFData!$Q$5:$Q$1626) -> 0.084329359 | Y11: =AVERAGEIF(Base_IFData!$F$5:$F$1626,$W11,Base_IFData!$L$5:$L$1626)/1000000 -> 5.0027775 | Z11: =SUMIF(Base_IFData!$F$5:$F$1626,$W11,Base_IFData!$M$5:$M$1626)/SUMIF(Base_IFData!$F$5:$F$1626,$W11,Base_IFData!$L$5:$L$1626) -> 0.12220009
A12: 2 | B12: =INDEX(Base_IFData!$U$5:$U$1626,MATCH($A12,Base_IFData!$G$5:$G$1626,0)) -> Privado Nacional | C12: =COUNTIF(Base_IFData!$G$5:$G$1626,$A12) -> 1353 | D12: =AVERAGEIF(Base_IFData!$G$5:$G$1626,$A12,Base_IFData!$W$5:$W$1626) -> 0.013724569 | E12: =SUMIF(Base_IFData!$G$5:$G$1626,$A12,Base_IFData!$R$5:$R$1626) -> 96755445 | F12: =SUMIF(Base_IFData!$G$5:$G$1626,$A12,Base_IFData!$Q$5:$Q$1626) -> 1135572000 | G12: =E12/F12 -> 0.085204148 | H12: =G12-D12 -> 0.071479579 | K12: =Base_IFData!A13 -> NU FINANCEIRA S.A. - SOCIEDADE DE CRÉDITO, FINANCIAMENTO E INVESTIMENTO | L12: =Base_IFData!F13 -> n1 | M12: =IF(AND(ISNUMBER(Base_IFData!L13),ISNUMBER(Base_IFData!W13)),IF(Base_IFData!L13>$B$4,Base_IFData!W13,""),"") -> 0.27930884 | N12: =IF(AND(ISNUMBER(Base_IFData!O13),ISNUMBER(Base_IFData!Q13)),IF(Base_IFData!Q13>0,Base_IFData!O13/Base_IFData!Q13,"PL ≤ 0"),"NI") -> 16.81957 | O12: =IF(AND(ISNUMBER(Base_IFData!M13),ISNUMBER(Base_IFData!Q13)),IF(Base_IFData!Q13>0,Base_IFData!M13/Base_IFData!Q13,"PL ≤ 0"),"NI") -> 5.0657643 | Q12: {=INDEX(Base_IFData!$L$5:$L$1626,$U12)/1000000} -> 267.62469 | R12: {=IF(INDEX(Base_IFData!$U$5:$U$1626,$U12)=R$3,INDEX(Base_IFData!$W$5:$W$1626,$U12),NA())} -> #N/A | S12: {=IF(INDEX(Base_IFData!$U$5:$U$1626,$U12)=S$3,INDEX(Base_IFData!$W$5:$W$1626,$U12),NA())} -> #N/A | T12: {=IF(INDEX(Base_IFData!$U$5:$U$1626,$U12)=T$3,INDEX(Base_IFData!$W$5:$W$1626,$U12),NA())} -> 0.27930884 | U12: =MATCH(LARGE(Base_IFData!$L$5:$L$1626,ROWS(U$4:U12)),Base_IFData!$L$5:$L$1626,0) -> 9
A13: 3 | B13: =INDEX(Base_IFData!$U$5:$U$1626,MATCH($A13,Base_IFData!$G$5:$G$1626,0)) -> Privado Estrangeiro | C13: =COUNTIF(Base_IFData!$G$5:$G$1626,$A13) -> 230 | D13: =AVERAGEIF(Base_IFData!$G$5:$G$1626,$A13,Base_IFData!$W$5:$W$1626) -> -0.033812466 | E13: =SUMIF(Base_IFData!$G$5:$G$1626,$A13,Base_IFData!$R$5:$R$1626) -> 27091361 | F13: =SUMIF(Base_IFData!$G$5:$G$1626,$A13,Base_IFData!$Q$5:$Q$1626) -> 350989626 | G13: =E13/F13 -> 0.077185646 | H13: =G13-D13 -> 0.11099811 | K13: =Base_IFData!A14 -> BANCO SAFRA S.A. | L13: =Base_IFData!F14 -> b1 | M13: =IF(AND(ISNUMBER(Base_IFData!L14),ISNUMBER(Base_IFData!W14)),IF(Base_IFData!L14>$B$4,Base_IFData!W14,""),"") -> 0.10468489 | N13: =IF(AND(ISNUMBER(Base_IFData!O14),ISNUMBER(Base_IFData!Q14)),IF(Base_IFData!Q14>0,Base_IFData!O14/Base_IFData!Q14,"PL ≤ 0"),"NI") -> 13.254481 | O13: =IF(AND(ISNUMBER(Base_IFData!M14),ISNUMBER(Base_IFData!Q14)),IF(Base_IFData!Q14>0,Base_IFData!M14/Base_IFData!Q14,"PL ≤ 0"),"NI") -> 5.1739049 | Q13: {=INDEX(Base_IFData!$L$5:$L$1626,$U13)/1000000} -> 256.68347 | R13: {=IF(INDEX(Base_IFData!$U$5:$U$1626,$U13)=R$3,INDEX(Base_IFData!$W$5:$W$1626,$U13),NA())} -> #N/A | S13: {=IF(INDEX(Base_IFData!$U$5:$U$1626,$U13)=S$3,INDEX(Base_IFData!$W$5:$W$1626,$U13),NA())} -> 0.10468489 | T13: {=IF(INDEX(Base_IFData!$U$5:$U$1626,$U13)=T$3,INDEX(Base_IFData!$W$5:$W$1626,$U13),NA())} -> #N/A | U13: =MATCH(LARGE(Base_IFData!$L$5:$L$1626,ROWS(U$4:U13)),Base_IFData!$L$5:$L$1626,0) -> 10 | W13: Top 10 instituições por Ativo Total (R$ bi), separado por tipo de controle
A14: Total do sistema | C14: =SUM(C11:C13) -> 1622 | D14: =AVERAGE(Base_IFData!$W$5:$W$1626) -> 0.0084424404 | E14: =SUM(E11:E13) -> 153467178 | F14: =SUM(F11:F13) -> 2040656923 | G14: =E14/F14 -> 0.075204791 | H14: =G14-D14 -> 0.066762351 | K14: =Base_IFData!A15 -> BANCO COOPERATIVO SICREDI S.A. | L14: =Base_IFData!F15 -> b1 | M14: =IF(AND(ISNUMBER(Base_IFData!L15),ISNUMBER(Base_IFData!W15)),IF(Base_IFData!L15>$B$4,Base_IFData!W15,""),"") -> 0.029671509 | N14: =IF(AND(ISNUMBER(Base_IFData!O15),ISNUMBER(Base_IFData!Q15)),IF(Base_IFData!Q15>0,Base_IFData!O15/Base_IFData!Q15,"PL ≤ 0"),"NI") -> 41.772693 | O14: =IF(AND(ISNUMBER(Base_IFData!M15),ISNUMBER(Base_IFData!Q15)),IF(Base_IFData!Q15>0,Base_IFData!M15/Base_IFData!Q15,"PL ≤ 0"),"NI") -> 9.1724051 | Q14: {=INDEX(Base_IFData!$L$5:$L$1626,$U14)/1000000} -> 234.40608 | R14: {=IF(INDEX(Base_IFData!$U$5:$U$1626,$U14)=R$3,INDEX(Base_IFData!$W$5:$W$1626,$U14),NA())} -> #N/A | S14: {=IF(INDEX(Base_IFData!$U$5:$U$1626,$U14)=S$3,INDEX(Base_IFData!$W$5:$W$1626,$U14),NA())} -> 0.029671509 | T14: {=IF(INDEX(Base_IFData!$U$5:$U$1626,$U14)=T$3,INDEX(Base_IFData!$W$5:$W$1626,$U14),NA())} -> #N/A | U14: =MATCH(LARGE(Base_IFData!$L$5:$L$1626,ROWS(U$4:U14)),Base_IFData!$L$5:$L$1626,0) -> 11 | W14: Posição | X14: Posição na base (linha relativa) | Y14: Instituição | Z14: Ativo Total (R$ bi) | AA14: Tipo de controle | AB14: Público | AC14: Privado Nacional | AD14: Privado Estrangeiro
K15: =Base_IFData!A16 -> BANCO COOPERATIVO SICOOB S.A. - BANCO SICOOB | L15: =Base_IFData!F16 -> b1 | M15: =IF(AND(ISNUMBER(Base_IFData!L16),ISNUMBER(Base_IFData!W16)),IF(Base_IFData!L16>$B$4,Base_IFData!W16,""),"") -> 0.065711032 | N15: =IF(AND(ISNUMBER(Base_IFData!O16),ISNUMBER(Base_IFData!Q16)),IF(Base_IFData!Q16>0,Base_IFData!O16/Base_IFData!Q16,"PL ≤ 0"),"NI") -> 30.95113 | O15: =IF(AND(ISNUMBER(Base_IFData!M16),ISNUMBER(Base_IFData!Q16)),IF(Base_IFData!Q16>0,Base_IFData!M16/Base_IFData!Q16,"PL ≤ 0"),"NI") -> 6.4298999 | Q15: {=INDEX(Base_IFData!$L$5:$L$1626,$U15)/1000000} -> 223.15941 | R15: {=IF(INDEX(Base_IFData!$U$5:$U$1626,$U15)=R$3,INDEX(Base_IFData!$W$5:$W$1626,$U15),NA())} -> #N/A | S15: {=IF(INDEX(Base_IFData!$U$5:$U$1626,$U15)=S$3,INDEX(Base_IFData!$W$5:$W$1626,$U15),NA())} -> 0.065711032 | T15: {=IF(INDEX(Base_IFData!$U$5:$U$1626,$U15)=T$3,INDEX(Base_IFData!$W$5:$W$1626,$U15),NA())} -> #N/A | U15: =MATCH(LARGE(Base_IFData!$L$5:$L$1626,ROWS(U$4:U15)),Base_IFData!$L$5:$L$1626,0) -> 12 | W15: 1 | X15: =MATCH(LARGE(Base_IFData!$L$5:$L$1626,$W15),Base_IFData!$L$5:$L$1626,0) -> 1 | Y15: {=IF(LEN(INDEX(Base_IFData!$A$5:$A$1626,$X15))>34,LEFT(INDEX(Base_IFData!$A$5:$A$1626,$X15),34)&"…",INDEX(Base_IFData!$A$5:$A$1626,$X15))} -> BANCO DO BRASIL S.A. | Z15: {=INDEX(Base_IFData!$L$5:$L$1626,$X15)/1000000} -> 2461.0869 | AA15: {=INDEX(Base_IFData!$U$5:$U$1626,$X15)} -> Público | AB15: =IF($AA15=AB$14,$Z15,0) -> 2461.0869 | AC15: =IF($AA15=AC$14,$Z15,0) -> 0 | AD15: =IF($AA15=AD$14,$Z15,0) -> 0
A16: ITEM 3 | Participação de cada tipo de controle no Ativo Total | K16: =Base_IFData!A17 -> BANCO XP S.A. | L16: =Base_IFData!F17 -> b1 | M16: =IF(AND(ISNUMBER(Base_IFData!L17),ISNUMBER(Base_IFData!W17)),IF(Base_IFData!L17>$B$4,Base_IFData!W17,""),"") -> 0.029489504 | N16: =IF(AND(ISNUMBER(Base_IFData!O17),ISNUMBER(Base_IFData!Q17)),IF(Base_IFData!Q17>0,Base_IFData!O17/Base_IFData!Q17,"PL ≤ 0"),"NI") -> 16.829843 | O16: =IF(AND(ISNUMBER(Base_IFData!M17),ISNUMBER(Base_IFData!Q17)),IF(Base_IFData!Q17>0,Base_IFData!M17/Base_IFData!Q17,"PL ≤ 0"),"NI") -> 2.5938582 | Q16: {=INDEX(Base_IFData!$L$5:$L$1626,$U16)/1000000} -> 221.73225 | R16: {=IF(INDEX(Base_IFData!$U$5:$U$1626,$U16)=R$3,INDEX(Base_IFData!$W$5:$W$1626,$U16),NA())} -> #N/A | S16: {=IF(INDEX(Base_IFData!$U$5:$U$1626,$U16)=S$3,INDEX(Base_IFData!$W$5:$W$1626,$U16),NA())} -> 0.029489504 | T16: {=IF(INDEX(Base_IFData!$U$5:$U$1626,$U16)=T$3,INDEX(Base_IFData!$W$5:$W$1626,$U16),NA())} -> #N/A | U16: =MATCH(LARGE(Base_IFData!$L$5:$L$1626,ROWS(U$4:U16)),Base_IFData!$L$5:$L$1626,0) -> 13 | W16: 2 | X16: =MATCH(LARGE(Base_IFData!$L$5:$L$1626,$W16),Base_IFData!$L$5:$L$1626,0) -> 2 | Y16: {=IF(LEN(INDEX(Base_IFData!$A$5:$A$1626,$X16))>34,LEFT(INDEX(Base_IFData!$A$5:$A$1626,$X16),34)&"…",INDEX(Base_IFData!$A$5:$A$1626,$X16))} -> CAIXA ECONOMICA FEDERAL | Z16: {=INDEX(Base_IFData!$L$5:$L$1626,$X16)/1000000} -> 2368.1472 | AA16: {=INDEX(Base_IFData!$U$5:$U$1626,$X16)} -> Público | AB16: =IF($AA16=AB$14,$Z16,0) -> 2368.1472 | AC16: =IF($AA16=AC$14,$Z16,0) -> 0 | AD16: =IF($AA16=AD$14,$Z16,0) -> 0
A17: TC | B17: Tipo de controle | C17: Soma do Ativo Total (R$ mil) | D17: % do Ativo Total | E17: Nº de instituições | F17: % das instituições | K17: =Base_IFData!A18 -> REDECARD INSTITUIÇÃO DE PAGAMENTO S.A. | L17: =Base_IFData!F18 -> n4 | M17: =IF(AND(ISNUMBER(Base_IFData!L18),ISNUMBER(Base_IFData!W18)),IF(Base_IFData!L18>$B$4,Base_IFData!W18,""),"") -> 0.036334416 | N17: =IF(AND(ISNUMBER(Base_IFData!O18),ISNUMBER(Base_IFData!Q18)),IF(Base_IFData!Q18>0,Base_IFData!O18/Base_IFData!Q18,"PL ≤ 0"),"NI") -> 3.3290051 | O17: =IF(AND(ISNUMBER(Base_IFData!M18),ISNUMBER(Base_IFData!Q18)),IF(Base_IFData!Q18>0,Base_IFData!M18/Base_IFData!Q18,"PL ≤ 0"),"NI") -> 0 | Q17: {=INDEX(Base_IFData!$L$5:$L$1626,$U17)/1000000} -> 178.38909 | R17: {=IF(INDEX(Base_IFData!$U$5:$U$1626,$U17)=R$3,INDEX(Base_IFData!$W$5:$W$1626,$U17),NA())} -> #N/A | S17: {=IF(INDEX(Base_IFData!$U$5:$U$1626,$U17)=S$3,INDEX(Base_IFData!$W$5:$W$1626,$U17),NA())} -> 0.036334416 | T17: {=IF(INDEX(Base_IFData!$U$5:$U$1626,$U17)=T$3,INDEX(Base_IFData!$W$5:$W$1626,$U17),NA())} -> #N/A | U17: =MATCH(LARGE(Base_IFData!$L$5:$L$1626,ROWS(U$4:U17)),Base_IFData!$L$5:$L$1626,0) -> 14 | W17: 3 | X17: =MATCH(LARGE(Base_IFData!$L$5:$L$1626,$W17),Base_IFData!$L$5:$L$1626,0) -> 3 | Y17: {=IF(LEN(INDEX(Base_IFData!$A$5:$A$1626,$X17))>34,LEFT(INDEX(Base_IFData!$A$5:$A$1626,$X17),34)&"…",INDEX(Base_IFData!$A$5:$A$1626,$X17))} -> ITAÚ UNIBANCO S.A. | Z17: {=INDEX(Base_IFData!$L$5:$L$1626,$X17)/1000000} -> 2169.4096 | AA17: {=INDEX(Base_IFData!$U$5:$U$1626,$X17)} -> Privado Nacional | AB17: =IF($AA17=AB$14,$Z17,0) -> 0 | AC17: =IF($AA17=AC$14,$Z17,0) -> 2169.4096 | AD17: =IF($AA17=AD$14,$Z17,0) -> 0
A18: 1 | B18: =INDEX(Base_IFData!$U$5:$U$1626,MATCH($A18,Base_IFData!$G$5:$G$1626,0)) -> Público | C18: =SUMIF(Base_IFData!$G$5:$G$1626,$A18,Base_IFData!$L$5:$L$1626) -> 6391175337 | D18: =C18/C$21 -> 0.32779037 | E18: =COUNTIF(Base_IFData!$G$5:$G$1626,$A18) -> 39 | F18: =E18/E$21 -> 0.02404439 | K18: =Base_IFData!A19 -> BANCO DO ESTADO DO RIO GRANDE DO SUL S.A. | L18: =Base_IFData!F19 -> b1 | M18: =IF(AND(ISNUMBER(Base_IFData!L19),ISNUMBER(Base_IFData!W19)),IF(Base_IFData!L19>$B$4,Base_IFData!W19,""),"") -> 0.047315896 | N18: =IF(AND(ISNUMBER(Base_IFData!O19),ISNUMBER(Base_IFData!Q19)),IF(Base_IFData!Q19>0,Base_IFData!O19/Base_IFData!Q19,"PL ≤ 0"),"NI") -> 13.962134 | O18: =IF(AND(ISNUMBER(Base_IFData!M19),ISNUMBER(Base_IFData!Q19)),IF(Base_IFData!Q19>0,Base_IFData!M19/Base_IFData!Q19,"PL ≤ 0"),"NI") -> 5.2302446 | Q18: {=INDEX(Base_IFData!$L$5:$L$1626,$U18)/1000000} -> 172.82796 | R18: {=IF(INDEX(Base_IFData!$U$5:$U$1626,$U18)=R$3,INDEX(Base_IFData!$W$5:$W$1626,$U18),NA())} -> 0.047315896 | S18: {=IF(INDEX(Base_IFData!$U$5:$U$1626,$U18)=S$3,INDEX(Base_IFData!$W$5:$W$1626,$U18),NA())} -> #N/A | T18: {=IF(INDEX(Base_IFData!$U$5:$U$1626,$U18)=T$3,INDEX(Base_IFData!$W$5:$W$1626,$U18),NA())} -> #N/A | U18: =MATCH(LARGE(Base_IFData!$L$5:$L$1626,ROWS(U$4:U18)),Base_IFData!$L$5:$L$1626,0) -> 15 | W18: 4 | X18: =MATCH(LARGE(Base_IFData!$L$5:$L$1626,$W18),Base_IFData!$L$5:$L$1626,0) -> 4 | Y18: {=IF(LEN(INDEX(Base_IFData!$A$5:$A$1626,$X18))>34,LEFT(INDEX(Base_IFData!$A$5:$A$1626,$X18),34)&"…",INDEX(Base_IFData!$A$5:$A$1626,$X18))} -> BANCO BRADESCO S.A. | Z18: {=INDEX(Base_IFData!$L$5:$L$1626,$X18)/1000000} -> 1952.4643 | AA18: {=INDEX(Base_IFData!$U$5:$U$1626,$X18)} -> Privado Nacional | AB18: =IF($AA18=AB$14,$Z18,0) -> 0 | AC18: =IF($AA18=AC$14,$Z18,0) -> 1952.4643 | AD18: =IF($AA18=AD$14,$Z18,0) -> 0
A19: 2 | B19: =INDEX(Base_IFData!$U$5:$U$1626,MATCH($A19,Base_IFData!$G$5:$G$1626,0)) -> Privado Nacional | C19: =SUMIF(Base_IFData!$G$5:$G$1626,$A19,Base_IFData!$L$5:$L$1626) -> 9761967942 | D19: =C19/C$21 -> 0.50067146 | E19: =COUNTIF(Base_IFData!$G$5:$G$1626,$A19) -> 1353 | F19: =E19/E$21 -> 0.83415536 | K19: =Base_IFData!A20 -> BANCO CITIBANK S.A. | L19: =Base_IFData!F20 -> b1 | M19: =IF(AND(ISNUMBER(Base_IFData!L20),ISNUMBER(Base_IFData!W20)),IF(Base_IFData!L20>$B$4,Base_IFData!W20,""),"") -> 0.16980334 | N19: =IF(AND(ISNUMBER(Base_IFData!O20),ISNUMBER(Base_IFData!Q20)),IF(Base_IFData!Q20>0,Base_IFData!O20/Base_IFData!Q20,"PL ≤ 0"),"NI") -> 31.674086 | O19: =IF(AND(ISNUMBER(Base_IFData!M20),ISNUMBER(Base_IFData!Q20)),IF(Base_IFData!Q20>0,Base_IFData!M20/Base_IFData!Q20,"PL ≤ 0"),"NI") -> 5.0219813 | Q19: {=INDEX(Base_IFData!$L$5:$L$1626,$U19)/1000000} -> 169.40334 | R19: {=IF(INDEX(Base_IFData!$U$5:$U$1626,$U19)=R$3,INDEX(Base_IFData!$W$5:$W$1626,$U19),NA())} -> #N/A | S19: {=IF(INDEX(Base_IFData!$U$5:$U$1626,$U19)=S$3,INDEX(Base_IFData!$W$5:$W$1626,$U19),NA())} -> #N/A | T19: {=IF(INDEX(Base_IFData!$U$5:$U$1626,$U19)=T$3,INDEX(Base_IFData!$W$5:$W$1626,$U19),NA())} -> 0.16980334 | U19: =MATCH(LARGE(Base_IFData!$L$5:$L$1626,ROWS(U$4:U19)),Base_IFData!$L$5:$L$1626,0) -> 16 | W19: 5 | X19: =MATCH(LARGE(Base_IFData!$L$5:$L$1626,$W19),Base_IFData!$L$5:$L$1626,0) -> 5 | Y19: {=IF(LEN(INDEX(Base_IFData!$A$5:$A$1626,$X19))>34,LEFT(INDEX(Base_IFData!$A$5:$A$1626,$X19),34)&"…",INDEX(Base_IFData!$A$5:$A$1626,$X19))} -> BANCO SANTANDER (BRASIL) S.A. | Z19: {=INDEX(Base_IFData!$L$5:$L$1626,$X19)/1000000} -> 1209.4431 | AA19: {=INDEX(Base_IFData!$U$5:$U$1626,$X19)} -> Privado Estrangeiro | AB19: =IF($AA19=AB$14,$Z19,0) -> 0 | AC19: =IF($AA19=AC$14,$Z19,0) -> 0 | AD19: =IF($AA19=AD$14,$Z19,0) -> 1209.4431
A20: 3 | B20: =INDEX(Base_IFData!$U$5:$U$1626,MATCH($A20,Base_IFData!$G$5:$G$1626,0)) -> Privado Estrangeiro | C20: =SUMIF(Base_IFData!$G$5:$G$1626,$A20,Base_IFData!$L$5:$L$1626) -> 3344608873 | D20: =C20/C$21 -> 0.17153818 | E20: =COUNTIF(Base_IFData!$G$5:$G$1626,$A20) -> 230 | F20: =E20/E$21 -> 0.14180025 | K20: =Base_IFData!A21 -> BANCO VOTORANTIM S.A. | L20: =Base_IFData!F21 -> b1 | M20: =IF(AND(ISNUMBER(Base_IFData!L21),ISNUMBER(Base_IFData!W21)),IF(Base_IFData!L21>$B$4,Base_IFData!W21,""),"") -> 0.074115473 | N20: =IF(AND(ISNUMBER(Base_IFData!O21),ISNUMBER(Base_IFData!Q21)),IF(Base_IFData!Q21>0,Base_IFData!O21/Base_IFData!Q21,"PL ≤ 0"),"NI") -> 10.374002 | O20: =IF(AND(ISNUMBER(Base_IFData!M21),ISNUMBER(Base_IFData!Q21)),IF(Base_IFData!Q21>0,Base_IFData!M21/Base_IFData!Q21,"PL ≤ 0"),"NI") -> 5.5488389 | Q20: {=INDEX(Base_IFData!$L$5:$L$1626,$U20)/1000000} -> 147.54755 | R20: {=IF(INDEX(Base_IFData!$U$5:$U$1626,$U20)=R$3,INDEX(Base_IFData!$W$5:$W$1626,$U20),NA())} -> #N/A | S20: {=IF(INDEX(Base_IFData!$U$5:$U$1626,$U20)=S$3,INDEX(Base_IFData!$W$5:$W$1626,$U20),NA())} -> 0.074115473 | T20: {=IF(INDEX(Base_IFData!$U$5:$U$1626,$U20)=T$3,INDEX(Base_IFData!$W$5:$W$1626,$U20),NA())} -> #N/A | U20: =MATCH(LARGE(Base_IFData!$L$5:$L$1626,ROWS(U$4:U20)),Base_IFData!$L$5:$L$1626,0) -> 17 | W20: 6 | X20: =MATCH(LARGE(Base_IFData!$L$5:$L$1626,$W20),Base_IFData!$L$5:$L$1626,0) -> 6 | Y20: {=IF(LEN(INDEX(Base_IFData!$A$5:$A$1626,$X20))>34,LEFT(INDEX(Base_IFData!$A$5:$A$1626,$X20),34)&"…",INDEX(Base_IFData!$A$5:$A$1626,$X20))} -> BANCO NACIONAL DE DESENVOLVIMENTO … | Z20: {=INDEX(Base_IFData!$L$5:$L$1626,$X20)/1000000} -> 1073.4037 | AA20: {=INDEX(Base_IFData!$U$5:$U$1626,$X20)} -> Público | AB20: =IF($AA20=AB$14,$Z20,0) -> 1073.4037 | AC20: =IF($AA20=AC$14,$Z20,0) -> 0 | AD20: =IF($AA20=AD$14,$Z20,0) -> 0
A21: Total do sistema | C21: =SUM(C18:C20) -> 19497752152 | D21: =SUM(D18:D20) -> 1 | E21: =SUM(E18:E20) -> 1622 | F21: =SUM(F18:F20) -> 1 | K21: =Base_IFData!A22 -> XP INVESTIMENTOS CORRETORA DE CÂMBIO,TÍTULOS E VALORES MOBILIÁRIOS S/A | L21: =Base_IFData!F22 -> n2 | M21: =IF(AND(ISNUMBER(Base_IFData!L22),ISNUMBER(Base_IFData!W22)),IF(Base_IFData!L22>$B$4,Base_IFData!W22,""),"") -> -0.0054785049 | N21: =IF(AND(ISNUMBER(Base_IFData!O22),ISNUMBER(Base_IFData!Q22)),IF(Base_IFData!Q22>0,Base_IFData!O22/Base_IFData!Q22,"PL ≤ 0"),"NI") -> 17.077968 | O21: =IF(AND(ISNUMBER(Base_IFData!M22),ISNUMBER(Base_IFData!Q22)),IF(Base_IFData!Q22>0,Base_IFData!M22/Base_IFData!Q22,"PL ≤ 0"),"NI") -> 0.020064603 | Q21: {=INDEX(Base_IFData!$L$5:$L$1626,$U21)/1000000} -> 132.45065 | R21: {=IF(INDEX(Base_IFData!$U$5:$U$1626,$U21)=R$3,INDEX(Base_IFData!$W$5:$W$1626,$U21),NA())} -> #N/A | S21: {=IF(INDEX(Base_IFData!$U$5:$U$1626,$U21)=S$3,INDEX(Base_IFData!$W$5:$W$1626,$U21),NA())} -> -0.0054785049 | T21: {=IF(INDEX(Base_IFData!$U$5:$U$1626,$U21)=T$3,INDEX(Base_IFData!$W$5:$W$1626,$U21),NA())} -> #N/A | U21: =MATCH(LARGE(Base_IFData!$L$5:$L$1626,ROWS(U$4:U21)),Base_IFData!$L$5:$L$1626,0) -> 18 | W21: 7 | X21: =MATCH(LARGE(Base_IFData!$L$5:$L$1626,$W21),Base_IFData!$L$5:$L$1626,0) -> 7 | Y21: {=IF(LEN(INDEX(Base_IFData!$A$5:$A$1626,$X21))>34,LEFT(INDEX(Base_IFData!$A$5:$A$1626,$X21),34)&"…",INDEX(Base_IFData!$A$5:$A$1626,$X21))} -> BANCO BTG PACTUAL S.A. | Z21: {=INDEX(Base_IFData!$L$5:$L$1626,$X21)/1000000} -> 743.25896 | AA21: {=INDEX(Base_IFData!$U$5:$U$1626,$X21)} -> Privado Nacional | AB21: =IF($AA21=AB$14,$Z21,0) -> 0 | AC21: =IF($AA21=AC$14,$Z21,0) -> 743.25896 | AD21: =IF($AA21=AD$14,$Z21,0) -> 0
A22: Conferência: total da tabela − soma da base | C22: =C21-SUM(Base_IFData!$L$5:$L$1626) -> 0 | K22: =Base_IFData!A23 -> NU PAGAMENTOS S.A. - INSTITUIÇÃO DE PAGAMENTO | L22: =Base_IFData!F23 -> n4 | M22: =IF(AND(ISNUMBER(Base_IFData!L23),ISNUMBER(Base_IFData!W23)),IF(Base_IFData!L23>$B$4,Base_IFData!W23,""),"") -> 0.17607426 | N22: =IF(AND(ISNUMBER(Base_IFData!O23),ISNUMBER(Base_IFData!Q23)),IF(Base_IFData!Q23>0,Base_IFData!O23/Base_IFData!Q23,"PL ≤ 0"),"NI") -> 4.263852 | O22: =IF(AND(ISNUMBER(Base_IFData!M23),ISNUMBER(Base_IFData!Q23)),IF(Base_IFData!Q23>0,Base_IFData!M23/Base_IFData!Q23,"PL ≤ 0"),"NI") -> 3.2608502 | Q22: {=INDEX(Base_IFData!$L$5:$L$1626,$U22)/1000000} -> 122.36323 | R22: {=IF(INDEX(Base_IFData!$U$5:$U$1626,$U22)=R$3,INDEX(Base_IFData!$W$5:$W$1626,$U22),NA())} -> #N/A | S22: {=IF(INDEX(Base_IFData!$U$5:$U$1626,$U22)=S$3,INDEX(Base_IFData!$W$5:$W$1626,$U22),NA())} -> #N/A | T22: {=IF(INDEX(Base_IFData!$U$5:$U$1626,$U22)=T$3,INDEX(Base_IFData!$W$5:$W$1626,$U22),NA())} -> 0.17607426 | U22: =MATCH(LARGE(Base_IFData!$L$5:$L$1626,ROWS(U$4:U22)),Base_IFData!$L$5:$L$1626,0) -> 19 | W22: 8 | X22: =MATCH(LARGE(Base_IFData!$L$5:$L$1626,$W22),Base_IFData!$L$5:$L$1626,0) -> 8 | Y22: {=IF(LEN(INDEX(Base_IFData!$A$5:$A$1626,$X22))>34,LEFT(INDEX(Base_IFData!$A$5:$A$1626,$X22),34)&"…",INDEX(Base_IFData!$A$5:$A$1626,$X22))} -> ITAÚ UNIBANCO HOLDING S.A. | Z22: {=INDEX(Base_IFData!$L$5:$L$1626,$X22)/1000000} -> 493.1834 | AA22: {=INDEX(Base_IFData!$U$5:$U$1626,$X22)} -> Privado Nacional | AB22: =IF($AA22=AB$14,$Z22,0) -> 0 | AC22: =IF($AA22=AC$14,$Z22,0) -> 493.1834 | AD22: =IF($AA22=AD$14,$Z22,0) -> 0
K23: =Base_IFData!A24 -> BANCO C6 S.A. | L23: =Base_IFData!F24 -> b1 | M23: =IF(AND(ISNUMBER(Base_IFData!L24),ISNUMBER(Base_IFData!W24)),IF(Base_IFData!L24>$B$4,Base_IFData!W24,""),"") -> 0.23547373 | N23: =IF(AND(ISNUMBER(Base_IFData!O24),ISNUMBER(Base_IFData!Q24)),IF(Base_IFData!Q24>0,Base_IFData!O24/Base_IFData!Q24,"PL ≤ 0"),"NI") -> 40.68102 | O23: =IF(AND(ISNUMBER(Base_IFData!M24),ISNUMBER(Base_IFData!Q24)),IF(Base_IFData!Q24>0,Base_IFData!M24/Base_IFData!Q24,"PL ≤ 0"),"NI") -> 18.675035 | Q23: {=INDEX(Base_IFData!$L$5:$L$1626,$U23)/1000000} -> 117.19373 | R23: {=IF(INDEX(Base_IFData!$U$5:$U$1626,$U23)=R$3,INDEX(Base_IFData!$W$5:$W$1626,$U23),NA())} -> #N/A | S23: {=IF(INDEX(Base_IFData!$U$5:$U$1626,$U23)=S$3,INDEX(Base_IFData!$W$5:$W$1626,$U23),NA())} -> 0.23547373 | T23: {=IF(INDEX(Base_IFData!$U$5:$U$1626,$U23)=T$3,INDEX(Base_IFData!$W$5:$W$1626,$U23),NA())} -> #N/A | U23: =MATCH(LARGE(Base_IFData!$L$5:$L$1626,ROWS(U$4:U23)),Base_IFData!$L$5:$L$1626,0) -> 20 | W23: 9 | X23: =MATCH(LARGE(Base_IFData!$L$5:$L$1626,$W23),Base_IFData!$L$5:$L$1626,0) -> 9 | Y23: {=IF(LEN(INDEX(Base_IFData!$A$5:$A$1626,$X23))>34,LEFT(INDEX(Base_IFData!$A$5:$A$1626,$X23),34)&"…",INDEX(Base_IFData!$A$5:$A$1626,$X23))} -> NU FINANCEIRA S.A. - SOCIEDADE DE … | Z23: {=INDEX(Base_IFData!$L$5:$L$1626,$X23)/1000000} -> 267.62469 | AA23: {=INDEX(Base_IFData!$U$5:$U$1626,$X23)} -> Privado Estrangeiro | AB23: =IF($AA23=AB$14,$Z23,0) -> 0 | AC23: =IF($AA23=AC$14,$Z23,0) -> 0 | AD23: =IF($AA23=AD$14,$Z23,0) -> 267.62469
A24: ITEM 4 | As 5 instituições com maior ROE do semestre | K24: =Base_IFData!A25 -> CIELO S.A. - INSTITUIÇÃO DE PAGAMENTO | L24: =Base_IFData!F25 -> n4 | M24: =IF(AND(ISNUMBER(Base_IFData!L25),ISNUMBER(Base_IFData!W25)),IF(Base_IFData!L25>$B$4,Base_IFData!W25,""),"") -> 0.04854604 | N24: =IF(AND(ISNUMBER(Base_IFData!O25),ISNUMBER(Base_IFData!Q25)),IF(Base_IFData!Q25>0,Base_IFData!O25/Base_IFData!Q25,"PL ≤ 0"),"NI") -> 8.9943628 | O24: =IF(AND(ISNUMBER(Base_IFData!M25),ISNUMBER(Base_IFData!Q25)),IF(Base_IFData!Q25>0,Base_IFData!M25/Base_IFData!Q25,"PL ≤ 0"),"NI") -> 0 | Q24: {=INDEX(Base_IFData!$L$5:$L$1626,$U24)/1000000} -> 116.68089 | R24: {=IF(INDEX(Base_IFData!$U$5:$U$1626,$U24)=R$3,INDEX(Base_IFData!$W$5:$W$1626,$U24),NA())} -> #N/A | S24: {=IF(INDEX(Base_IFData!$U$5:$U$1626,$U24)=S$3,INDEX(Base_IFData!$W$5:$W$1626,$U24),NA())} -> 0.04854604 | T24: {=IF(INDEX(Base_IFData!$U$5:$U$1626,$U24)=T$3,INDEX(Base_IFData!$W$5:$W$1626,$U24),NA())} -> #N/A | U24: =MATCH(LARGE(Base_IFData!$L$5:$L$1626,ROWS(U$4:U24)),Base_IFData!$L$5:$L$1626,0) -> 21 | W24: 10 | X24: =MATCH(LARGE(Base_IFData!$L$5:$L$1626,$W24),Base_IFData!$L$5:$L$1626,0) -> 10 | Y24: {=IF(LEN(INDEX(Base_IFData!$A$5:$A$1626,$X24))>34,LEFT(INDEX(Base_IFData!$A$5:$A$1626,$X24),34)&"…",INDEX(Base_IFData!$A$5:$A$1626,$X24))} -> BANCO SAFRA S.A. | Z24: {=INDEX(Base_IFData!$L$5:$L$1626,$X24)/1000000} -> 256.68347 | AA24: {=INDEX(Base_IFData!$U$5:$U$1626,$X24)} -> Privado Nacional | AB24: =IF($AA24=AB$14,$Z24,0) -> 0 | AC24: =IF($AA24=AC$14,$Z24,0) -> 256.68347 | AD24: =IF($AA24=AD$14,$Z24,0) -> 0
A25: (a) Toda a base | K25: =Base_IFData!A26 -> BANCO J.P. MORGAN S.A. | L25: =Base_IFData!F26 -> b1 | M25: =IF(AND(ISNUMBER(Base_IFData!L26),ISNUMBER(Base_IFData!W26)),IF(Base_IFData!L26>$B$4,Base_IFData!W26,""),"") -> 0.088197036 | N25: =IF(AND(ISNUMBER(Base_IFData!O26),ISNUMBER(Base_IFData!Q26)),IF(Base_IFData!Q26>0,Base_IFData!O26/Base_IFData!Q26,"PL ≤ 0"),"NI") -> 8.3461031 | O25: =IF(AND(ISNUMBER(Base_IFData!M26),ISNUMBER(Base_IFData!Q26)),IF(Base_IFData!Q26>0,Base_IFData!M26/Base_IFData!Q26,"PL ≤ 0"),"NI") -> 0.31733032 | Q25: {=INDEX(Base_IFData!$L$5:$L$1626,$U25)/1000000} -> 110.02535 | R25: {=IF(INDEX(Base_IFData!$U$5:$U$1626,$U25)=R$3,INDEX(Base_IFData!$W$5:$W$1626,$U25),NA())} -> #N/A | S25: {=IF(INDEX(Base_IFData!$U$5:$U$1626,$U25)=S$3,INDEX(Base_IFData!$W$5:$W$1626,$U25),NA())} -> #N/A | T25: {=IF(INDEX(Base_IFData!$U$5:$U$1626,$U25)=T$3,INDEX(Base_IFData!$W$5:$W$1626,$U25),NA())} -> 0.088197036 | U25: =MATCH(LARGE(Base_IFData!$L$5:$L$1626,ROWS(U$4:U25)),Base_IFData!$L$5:$L$1626,0) -> 22
A26: Posição | B26: Instituição | C26: TCB | D26: Ativo Total (R$ mil) | E26: ROE do semestre | K26: =Base_IFData!A27 -> MERCADO PAGO INSTITUIÇÃO DE PAGAMENTO LTDA. | L26: =Base_IFData!F27 -> n4 | M26: =IF(AND(ISNUMBER(Base_IFData!L27),ISNUMBER(Base_IFData!W27)),IF(Base_IFData!L27>$B$4,Base_IFData!W27,""),"") -> -0.063502439 | N26: =IF(AND(ISNUMBER(Base_IFData!O27),ISNUMBER(Base_IFData!Q27)),IF(Base_IFData!Q27>0,Base_IFData!O27/Base_IFData!Q27,"PL ≤ 0"),"NI") -> 34.371096 | O26: =IF(AND(ISNUMBER(Base_IFData!M27),ISNUMBER(Base_IFData!Q27)),IF(Base_IFData!Q27>0,Base_IFData!M27/Base_IFData!Q27,"PL ≤ 0"),"NI") -> 7.522146 | Q26: {=INDEX(Base_IFData!$L$5:$L$1626,$U26)/1000000} -> 105.73156 | R26: {=IF(INDEX(Base_IFData!$U$5:$U$1626,$U26)=R$3,INDEX(Base_IFData!$W$5:$W$1626,$U26),NA())} -> #N/A | S26: {=IF(INDEX(Base_IFData!$U$5:$U$1626,$U26)=S$3,INDEX(Base_IFData!$W$5:$W$1626,$U26),NA())} -> #N/A | T26: {=IF(INDEX(Base_IFData!$U$5:$U$1626,$U26)=T$3,INDEX(Base_IFData!$W$5:$W$1626,$U26),NA())} -> -0.063502439 | U26: =MATCH(LARGE(Base_IFData!$L$5:$L$1626,ROWS(U$4:U26)),Base_IFData!$L$5:$L$1626,0) -> 23
A27: 1 | B27: =INDEX(Base_IFData!$A$5:$A$1626,MATCH($E27,Base_IFData!$W$5:$W$1626,0)) -> GREENPASS TECNOLOGIA E INSTITUICAO DE PAGAMENTO HUE S.A. | C27: =INDEX(Base_IFData!$F$5:$F$1626,MATCH($E27,Base_IFData!$W$5:$W$1626,0)) -> n4 | D27: =INDEX(Base_IFData!$L$5:$L$1626,MATCH($E27,Base_IFData!$W$5:$W$1626,0)) -> 420288 | E27: =LARGE(Base_IFData!$W$5:$W$1626,$A27) -> 1.6845695 | K27: =Base_IFData!A28 -> BANCO INTER S.A. | L27: =Base_IFData!F28 -> b1 | M27: =IF(AND(ISNUMBER(Base_IFData!L28),ISNUMBER(Base_IFData!W28)),IF(Base_IFData!L28>$B$4,Base_IFData!W28,""),"") -> 0.095552451 | N27: =IF(AND(ISNUMBER(Base_IFData!O28),ISNUMBER(Base_IFData!Q28)),IF(Base_IFData!Q28>0,Base_IFData!O28/Base_IFData!Q28,"PL ≤ 0"),"NI") -> 12.540067 | O27: =IF(AND(ISNUMBER(Base_IFData!M28),ISNUMBER(Base_IFData!Q28)),IF(Base_IFData!Q28>0,Base_IFData!M28/Base_IFData!Q28,"PL ≤ 0"),"NI") -> 6.1919015 | Q27: {=INDEX(Base_IFData!$L$5:$L$1626,$U27)/1000000} -> 100.89833 | R27: {=IF(INDEX(Base_IFData!$U$5:$U$1626,$U27)=R$3,INDEX(Base_IFData!$W$5:$W$1626,$U27),NA())} -> #N/A | S27: {=IF(INDEX(Base_IFData!$U$5:$U$1626,$U27)=S$3,INDEX(Base_IFData!$W$5:$W$1626,$U27),NA())} -> 0.095552451 | T27: {=IF(INDEX(Base_IFData!$U$5:$U$1626,$U27)=T$3,INDEX(Base_IFData!$W$5:$W$1626,$U27),NA())} -> #N/A | U27: =MATCH(LARGE(Base_IFData!$L$5:$L$1626,ROWS(U$4:U27)),Base_IFData!$L$5:$L$1626,0) -> 24
A28: 2 | B28: =INDEX(Base_IFData!$A$5:$A$1626,MATCH($E28,Base_IFData!$W$5:$W$1626,0)) -> BOC BRASIL S.A. - CRÉDITO, FINANCIAMENTOS E INVESTIMENTOS | C28: =INDEX(Base_IFData!$F$5:$F$1626,MATCH($E28,Base_IFData!$W$5:$W$1626,0)) -> n1 | D28: =INDEX(Base_IFData!$L$5:$L$1626,MATCH($E28,Base_IFData!$W$5:$W$1626,0)) -> 52762 | E28: =LARGE(Base_IFData!$W$5:$W$1626,$A28) -> 1.4711538 | K28: =Base_IFData!A29 -> BANCO DAYCOVAL S.A. | L28: =Base_IFData!F29 -> b1 | M28: =IF(AND(ISNUMBER(Base_IFData!L29),ISNUMBER(Base_IFData!W29)),IF(Base_IFData!L29>$B$4,Base_IFData!W29,""),"") -> 0.11777088 | N28: =IF(AND(ISNUMBER(Base_IFData!O29),ISNUMBER(Base_IFData!Q29)),IF(Base_IFData!Q29>0,Base_IFData!O29/Base_IFData!Q29,"PL ≤ 0"),"NI") -> 12.033215 | O28: =IF(AND(ISNUMBER(Base_IFData!M29),ISNUMBER(Base_IFData!Q29)),IF(Base_IFData!Q29>0,Base_IFData!M29/Base_IFData!Q29,"PL ≤ 0"),"NI") -> 7.0288417 | Q28: {=INDEX(Base_IFData!$L$5:$L$1626,$U28)/1000000} -> 99.778656 | R28: {=IF(INDEX(Base_IFData!$U$5:$U$1626,$U28)=R$3,INDEX(Base_IFData!$W$5:$W$1626,$U28),NA())} -> #N/A | S28: {=IF(INDEX(Base_IFData!$U$5:$U$1626,$U28)=S$3,INDEX(Base_IFData!$W$5:$W$1626,$U28),NA())} -> 0.11777088 | T28: {=IF(INDEX(Base_IFData!$U$5:$U$1626,$U28)=T$3,INDEX(Base_IFData!$W$5:$W$1626,$U28),NA())} -> #N/A | U28: =MATCH(LARGE(Base_IFData!$L$5:$L$1626,ROWS(U$4:U28)),Base_IFData!$L$5:$L$1626,0) -> 25
A29: 3 | B29: =INDEX(Base_IFData!$A$5:$A$1626,MATCH($E29,Base_IFData!$W$5:$W$1626,0)) -> CAIXA DISTRIBUIDORA DE TÍTULOS E VALORES MOBILIÁRIOS S.A. | C29: =INDEX(Base_IFData!$F$5:$F$1626,MATCH($E29,Base_IFData!$W$5:$W$1626,0)) -> n2 | D29: =INDEX(Base_IFData!$L$5:$L$1626,MATCH($E29,Base_IFData!$W$5:$W$1626,0)) -> 743604 | E29: =LARGE(Base_IFData!$W$5:$W$1626,$A29) -> 0.90728844 | K29: =Base_IFData!A30 -> SANTANDER SOCIEDADE DE CRÉDITO, FINANCIAMENTO E INVESTIMENTO S.A. | L29: =Base_IFData!F30 -> n1 | M29: =IF(AND(ISNUMBER(Base_IFData!L30),ISNUMBER(Base_IFData!W30)),IF(Base_IFData!L30>$B$4,Base_IFData!W30,""),"") -> 0.075106981 | N29: =IF(AND(ISNUMBER(Base_IFData!O30),ISNUMBER(Base_IFData!Q30)),IF(Base_IFData!Q30>0,Base_IFData!O30/Base_IFData!Q30,"PL ≤ 0"),"NI") -> 18.741194 | O29: =IF(AND(ISNUMBER(Base_IFData!M30),ISNUMBER(Base_IFData!Q30)),IF(Base_IFData!Q30>0,Base_IFData!M30/Base_IFData!Q30,"PL ≤ 0"),"NI") -> 16.414789 | Q29: {=INDEX(Base_IFData!$L$5:$L$1626,$U29)/1000000} -> 94.908733 | R29: {=IF(INDEX(Base_IFData!$U$5:$U$1626,$U29)=R$3,INDEX(Base_IFData!$W$5:$W$1626,$U29),NA())} -> #N/A | S29: {=IF(INDEX(Base_IFData!$U$5:$U$1626,$U29)=S$3,INDEX(Base_IFData!$W$5:$W$1626,$U29),NA())} -> #N/A | T29: {=IF(INDEX(Base_IFData!$U$5:$U$1626,$U29)=T$3,INDEX(Base_IFData!$W$5:$W$1626,$U29),NA())} -> 0.075106981 | U29: =MATCH(LARGE(Base_IFData!$L$5:$L$1626,ROWS(U$4:U29)),Base_IFData!$L$5:$L$1626,0) -> 26
A30: 4 | B30: =INDEX(Base_IFData!$A$5:$A$1626,MATCH($E30,Base_IFData!$W$5:$W$1626,0)) -> BB GESTÃO DE RECURSOS - DISTRIBUIDORA DE TÍTULOS E VALORES MOBILIÁRIOS S.A. | C30: =INDEX(Base_IFData!$F$5:$F$1626,MATCH($E30,Base_IFData!$W$5:$W$1626,0)) -> n2 | D30: =INDEX(Base_IFData!$L$5:$L$1626,MATCH($E30,Base_IFData!$W$5:$W$1626,0)) -> 3841544 | E30: =LARGE(Base_IFData!$W$5:$W$1626,$A30) -> 0.87126301 | K30: =Base_IFData!A31 -> STONE INSTITUIÇÃO DE PAGAMENTO S.A. | L30: =Base_IFData!F31 -> n4 | M30: =IF(AND(ISNUMBER(Base_IFData!L31),ISNUMBER(Base_IFData!W31)),IF(Base_IFData!L31>$B$4,Base_IFData!W31,""),"") -> 0.27016715 | N30: =IF(AND(ISNUMBER(Base_IFData!O31),ISNUMBER(Base_IFData!Q31)),IF(Base_IFData!Q31>0,Base_IFData!O31/Base_IFData!Q31,"PL ≤ 0"),"NI") -> 26.803934 | O30: =IF(AND(ISNUMBER(Base_IFData!M31),ISNUMBER(Base_IFData!Q31)),IF(Base_IFData!Q31>0,Base_IFData!M31/Base_IFData!Q31,"PL ≤ 0"),"NI") -> 0 | Q30: {=INDEX(Base_IFData!$L$5:$L$1626,$U30)/1000000} -> 89.229885 | R30: {=IF(INDEX(Base_IFData!$U$5:$U$1626,$U30)=R$3,INDEX(Base_IFData!$W$5:$W$1626,$U30),NA())} -> #N/A | S30: {=IF(INDEX(Base_IFData!$U$5:$U$1626,$U30)=S$3,INDEX(Base_IFData!$W$5:$W$1626,$U30),NA())} -> #N/A | T30: {=IF(INDEX(Base_IFData!$U$5:$U$1626,$U30)=T$3,INDEX(Base_IFData!$W$5:$W$1626,$U30),NA())} -> 0.27016715 | U30: =MATCH(LARGE(Base_IFData!$L$5:$L$1626,ROWS(U$4:U30)),Base_IFData!$L$5:$L$1626,0) -> 27
A31: 5 | B31: =INDEX(Base_IFData!$A$5:$A$1626,MATCH($E31,Base_IFData!$W$5:$W$1626,0)) -> EFEX INSTITUIÇÃO DE PAGAMENTO S.A. | C31: =INDEX(Base_IFData!$F$5:$F$1626,MATCH($E31,Base_IFData!$W$5:$W$1626,0)) -> n4 | D31: =INDEX(Base_IFData!$L$5:$L$1626,MATCH($E31,Base_IFData!$W$5:$W$1626,0)) -> 1839 | E31: =LARGE(Base_IFData!$W$5:$W$1626,$A31) -> 0.82136895 | K31: =Base_IFData!A32 -> BANCO DO NORDESTE DO BRASIL S.A. | L31: =Base_IFData!F32 -> b1 | M31: =IF(AND(ISNUMBER(Base_IFData!L32),ISNUMBER(Base_IFData!W32)),IF(Base_IFData!L32>$B$4,Base_IFData!W32,""),"") -> 0.062892486 | N31: =IF(AND(ISNUMBER(Base_IFData!O32),ISNUMBER(Base_IFData!Q32)),IF(Base_IFData!Q32>0,Base_IFData!O32/Base_IFData!Q32,"PL ≤ 0"),"NI") -> 3.8200639 | O31: =IF(AND(ISNUMBER(Base_IFData!M32),ISNUMBER(Base_IFData!Q32)),IF(Base_IFData!Q32>0,Base_IFData!M32/Base_IFData!Q32,"PL ≤ 0"),"NI") -> 1.0575096 | Q31: {=INDEX(Base_IFData!$L$5:$L$1626,$U31)/1000000} -> 81.039783 | R31: {=IF(INDEX(Base_IFData!$U$5:$U$1626,$U31)=R$3,INDEX(Base_IFData!$W$5:$W$1626,$U31),NA())} -> 0.062892486 | S31: {=IF(INDEX(Base_IFData!$U$5:$U$1626,$U31)=S$3,INDEX(Base_IFData!$W$5:$W$1626,$U31),NA())} -> #N/A | T31: {=IF(INDEX(Base_IFData!$U$5:$U$1626,$U31)=T$3,INDEX(Base_IFData!$W$5:$W$1626,$U31),NA())} -> #N/A | U31: =MATCH(LARGE(Base_IFData!$L$5:$L$1626,ROWS(U$4:U31)),Base_IFData!$L$5:$L$1626,0) -> 28
